Workbook

Sheet porcionados
B1: PORCIONADOS | AF1: dólar
B2: ENTRADA | AB2: ACUMULADO | AC2: precio | AD2: Total | AF2: 40.216
A3: Códigos | B3: Productos | AB3: kls. | AC3: U$S | AD3: U$S
A4: 3000 | B4: Asado 13 costillas Pasto | AB4: =SUM(C4:AA4) -> 6654.6 | AC4: =+VNR!G4 -> 4.2151137 | AD4: =-ABS(AB4*AC4) -> -28049.895
A5: 3001 | B5: Asado 13 costillas s/p Pasto | AB5: 12007.3 | AC5: =+VNR!G5 -> 4.1501137 | AD5: =-ABS(AB5*AC5) -> -49831.66
A6: 3010 | B6: Asado 13/C (Grano) | AB6: 2979.8 | AD6: =-ABS(AB6*AC6) -> 0
A7: 3011 | B7: Asado 13 costillas Grano s/p | AB7: 64367.7 | AC7: =hacienda!O44 -> 5.8794795 | AD7: -378448.57
A8: 3911 | B8: Asado 13/c s/pulpon (grano) Compra | AB8: 9558.7 | AC8: 6.63 | AD8: -63374.181
A9: 4000 | B9: Falda con hueso Pasto | AB9: 14181.3 | AC9: =+VNR!G6 -> 3.8501137 | AD9: -54599.617
A10: 4003 | B10: Vacio (Bolsa) | AB10: 1027.2 | AD10: =-ABS(AB10*AC10) -> 0
A11: 4010 | B11: Falda con hueso Grano | AB11: 20608.6 | AC11: =+VNR!G7 -> 4.5501137 | AD11: -93771.473 | AE11: =SUM(AD4:AD11) -> -668075.4
A12: 4403 | B12: Entraña Gruesa Fresca | AB12: 1425.17 | AC12: =+VNR!G8 -> 5.2481746 | AD12: -7479.541
A13: 4404 | B13: Entraña fina | AB13: 71.9 | AC13: 12.77 | AD13: -918.163
A14: 4407 | B14: Quijada | AB14: 2284.77 | AC14: =+VNR!G9 -> 5.9342413 | AD14: -13558.376
A15: 4411 | B15: Mondongo | AB15: =SUM(C15:AA15) -> 0 | AC15: =180/40.18 -> 4.4798407 | AD15: =-ABS(AB15*AC15) -> 0
A16: 4470 | B16: Entraña Fina | AB16: 8365.7 | AC16: =+AC11 -> 4.5501137 | AD16: -38064.886
A17: 4490 | B17: TRIMMING ESPECIAL | AB17: =SUM(C17:AA17) -> 0 | AC17: 3.1 | AD17: =-ABS(AB17*AC17) -> 0
A18: 4503 | B18: Entraña Gruesa Fresca | AB18: 2139.93 | AC18: =+AC12 -> 5.2481746 | AD18: -11230.726
A19: 4514 | B19: Chinchulines | AB19: 376.53 | AC19: =125.28/40.48 -> 3.0948617 | AD19: -1165.3083
A20: 4516 | B20: Mollejas | AB20: 988.61 | AC20: =238.6/40.48 -> 5.8942688 | AD20: -5827.1331
A21: 4543 | B21: Riñon c/grasa | AB21: 453.84 | AC21: 1.71 | AD21: -776.0664
A22: 4607 | B22: Quijada Feedlot Fresca | AB22: 2163.64 | AC22: =+AC14 -> 5.9342413 | AD22: -12839.562
A23: 9407 | B23: Quijadas - Cheek Meat | AB23: =SUM(C23:AA23) -> 0 | AC23: =+AC14 -> 5.9342413 | AD23: =-ABS(AB23*AC23) -> 0
A24: 9408 | B24: Carne Chica | AB24: 48 | AC24: 4.5 | AD24: -216
A25: 9490 | B25: Trimmings Especial | AB25: 144 | AC25: 4.84 | AD25: -696.96
A26: 9607 | B26: Quijada | AB26: =SUM(C26:AA26) -> 0 | AC26: =+AC23 -> 5.9342413 | AD26: =-ABS(AB26*AC26) -> 0
A27: 437016 | B27: Bife Ancho 7/c 1x1 GF | AB27: =SUM(C27:AA27) -> 0 | AC27: =1105/1.1391184/40.3 -> 24.07068 | AD27: =-ABS(AB27*AC27) -> 0
A28: 438031 | B28: Bife Angosto Vila Congelado | AB28: =SUM(C28:AA28) -> 0 | AC28: =+VNR!G15 -> 23.836515 | AD28: =-ABS(AB28*AC28) -> 0
A29: 438037 | B29: Osobuco Vila Cong. | AB29: =SUM(C29:AA29) -> 0 | AC29: =595/1.1391184/40.3 -> 12.961136 | AD29: =-ABS(AB29*AC29) -> 0
A30: 438124 | B30: Colita de Cuadril Vila Congelada | AB30: =SUM(C30:AA30) -> 0 | AC30: 12.7 | AD30: =-ABS(AB30*AC30) -> 0
A31: 439010 | B31: Chuck Vila | AB31: =SUM(C31:AA31) -> 0 | AC31: 12.802 | AD31: =-ABS(AB31*AC31) -> 0
A32: 439016 | B32: Bife Ancho Vila | AB32: =SUM(C32:AA32) -> 0 | AC32: 28.789 | AD32: =-ABS(AB32*AC32) -> 0
A33: 439070 | B33: Entraña Fina | AB33: =SUM(C33:AA33) -> 0 | AC33: =+AC13 -> 12.77 | AD33: =-ABS(AB33*AC33) -> 0
A34: 439130 | B34: Lomo Vila | AB34: =SUM(C34:AA34) -> 0 | AC34: =1055/1.1391184/40.3 -> 22.981509 | AD34: =-ABS(AB34*AC34) -> 0
A35: 439909 | B35: Lomito de Paleta Vila | AB35: =SUM(C35:AA35) -> 0 | AC35: 8 | AD35: =-ABS(AB35*AC35) -> 0
A36: 442070 | B36: Entraña Fina EL RANCHO | AB36: =SUM(C36:AA36) -> 0 | AC36: =720/1.1391184/40.3 -> 15.684063 | AD36: =-ABS(AB36*AC36) -> 0
A37: 980006 | B37: Sobrante - Aguja | AB37: 657.91 | AC37: 7.4 | AD37: -4868.534
A38: 980011 | B38: Sobrante - Denver | AB38: 66.68 | AC38: =+AC32 -> 28.789 | AD38: -1919.6505
A39: 980012 | B39: Sobrante - Paleta | AB39: =SUM(C39:AA39) -> 0 | AC39: 5.7 | AD39: =-ABS(AB39*AC39) -> 0
A40: 980016 | B40: Sobrante - Bife Ancho | AB40: 83.97 | AC40: =392/1.1391184/40.48 -> 8.5011308 | AD40: -713.83995
A41: 980024 | B41: Sobrante - Colita | AB41: 1864.84 | AC41: =681/1.1391184/40.48 -> 14.768546 | AD41: -27540.975
A42: 980025 | B42: Sobrante - Picaña | AB42: =SUM(C42:AA42) -> 0 | AC42: 15 | AD42: =-ABS(AB42*AC42) -> 0
A43: 980026 | B43: Sobrante - Cuadrada | AB43: 9.7 | AC43: 6.5 | AD43: -63.05
A44: 980028 | B44: Sobrante - Peceto | AB44: =SUM(C44:AA44) -> 0 | AC44: 6.5 | AD44: =-ABS(AB44*AC44) -> 0
A45: 980030 | B45: Sobrante - Lomo 980030 | AB45: 40.27 | AC45: 22.53 | AD45: -907.2831
A46: 980031 | B46: Sobrante - Bife Angosto | AB46: 34.76 | AC46: 13.9 | AD46: -483.164
A47: 980032 | B47: Sobrante - Vacio 980032 | AB47: 469.55 | AC47: 12 | AD47: -5634.6
A48: 980033 | B48: Sobrante - Palomita 980033 | AB48: 102.82 | AC48: 10.5 | AD48: -1079.61
A49: 980035 | B49: Sobrante - Matambre | AB49: 925.39 | AC49: 5.5 | AD49: -5089.645
A50: 980039 | B50: Sobrante - falda | AB50: 613.81 | AC50: =+AC9 -> 3.8501137 | AD50: -2363.2383
A51: 980041 | B51: Sobrante - Arañita | AB51: =SUM(C51:AA51) -> 0 | AC51: 5.5 | AD51: =-ABS(AB51*AC51) -> 0
A52: 980060 | B52: Sobrante - Asado 980060 | AB52: 11497.96 | AC52: =AVERAGE(AC4:AC7) -> 4.7482356 | AD52: -54595.023
A53: 980070 | B53: Sobrante - Entraña | AB53: 1980.14 | AC53: =+AC33 -> 12.77 | AD53: -25286.388
A54: 980090 | B54: Sobrante - Trimming | AB54: 3965.27 | AC54: 5.5 | AD54: -21808.985
A55: 980091 | B55: Sobrante - Manta | AB55: 599.31 | AC55: 5.5 | AD55: -3296.205
A56: 980099 | B56: Sobrante - Molleja | AB56: 499.52 | AD56: =-ABS(AB56*AC56) -> 0
A57: 981035 | B57: Matambre block - Carne sin envasar logs | AB57: =SUM(C57:AA57) -> 0 | AC57: 5.5 | AD57: =-ABS(AB57*AC57) -> 0
A58: 991420 | B58: Brazuelo s/h c/conical | AB58: =SUM(C58:AA58) -> 0 | AD58: =-ABS(AB58*AC58) -> 0
A59: 998040 | B59: Pasta Abasto | AB59: =SUM(C59:AA59) -> 0 | AC59: 1.37 | AD59: =-ABS(AB59*AC59) -> 0
A60: 998140 | B60: Trimmings Picada (25 kg) | AB60: =SUM(C60:AA60) -> 0 | AC60: =+AC59 -> 1.37 | AD60: =-ABS(AB60*AC60) -> 0
A61: 1987134 | B61: Brazuelo Garron x1kg - Shin/shank Angus GF | AB61: =SUM(C61:AA61) -> 0 | AC61: 7.1 | AD61: =-ABS(AB61*AC61) -> 0
A62: 1987420 | B62: Brazuelo s/h c/conical GF Angus | AB62: =SUM(C62:AA62) -> 0 | AC62: 7.1 | AD62: =-ABS(AB62*AC62) -> 0
A63: 1987421 | B63: Tortuguita c/bananita Grain Fed Angus - Heel Muscle With Golden Coin | AB63: =SUM(C63:AA63) -> 0 | AC63: 7.1 | AD63: =-ABS(AB63*AC63) -> 0
A64: 1987434 | B64: Garron s/h GF Angus | AB64: =SUM(C64:AA64) -> 0 | AC64: 7.1 | AD64: =-ABS(AB64*AC64) -> 0
A65: 2000008 | B65: Recorte (C.F.) | AB65: 166.25 | AC65: 4.5 | AD65: -748.125
A66: 2000012 | B66: Paleta sin marcuha Logs | AB66: 23.22 | AC66: 5.5 | AD66: -127.71
A67: 2000013 | B67: Marucha para Porcionar | AB67: 57.89 | AC67: =392/1.1391184/40.48 -> 8.5011308 | AD67: -492.13046
A68: 2000023 | B68: Nalga S/T | AB68: 1160.13 | AC68: 8.1 | AD68: -9397.053
A69: 2000024 | B69: Colita de Cuadril | AB69: 4989.9 | AC69: 8.6 | AD69: -42913.14
A70: 2000025 | B70: Picanhas | AB70: =SUM(C70:AA70) -> 0 | AC70: 14 | AD70: =-ABS(AB70*AC70) -> 0
A71: 2000027 | B71: Bola de Logo logs | AB71: 190.62 | AC71: 6.5 | AD71: -1239.03
A72: 2000028 | B72: Peceto Logs | AB72: 875.4 | AC72: 6.5 | AD72: -5690.1
A73: 2000030 | B73: Lomo s/c para porcionar | AB73: 116.26 | AC73: 19 | AD73: -2208.94
A74: 2000032 | B74: Tapa de Vacio Logs | AB74: 56.04 | AC74: 5.5 | AD74: -308.22
A75: 2000033 | B75: Bife de Vacio | AB75: 1821.93 | AC75: 11.5 | AD75: -20952.195
A76: 2000035 | B76: Punta de Matambre logs | AB76: 16.89 | AC76: 4.5 | AD76: -76.005
A77: 2000034 | B77: Garron para Porcionar | AB77: =SUM(C77:AA77) -> 0 | AC77: 7.1 | AD77: =-ABS(AB77*AC77) -> 0
A78: 2000037 | B78: Osobuco | AB78: =SUM(C78:AA78) -> 0 | AC78: 14.791 | AD78: =-ABS(AB78*AC78) -> 0
A79: 2000041 | B79: Arañita | AB79: 912.7 | AC79: 5.5 | AD79: -5019.85
A80: 2000060 | B80: Tapa de Asado logs | AB80: 24.95 | AC80: 5.5 | AD80: -137.225
A81: 2000071 | B81: Entraña Interna | AB81: 1958.52 | AC81: 10 | AD81: -19585.2
A82: 2000123 | B82: Tapa de Nalga Logs | AB82: =SUM(C82:AA82) -> 0 | AC82: 4.5 | AD82: =-ABS(AB82*AC82) -> 0
A83: 2000132 | B83: Flap | AB83: 5250.42 | AC83: 14 | AD83: -73505.88
A84: 2000135 | B84: Matambre para porcionado | AB84: 2499.1 | AC84: 5.5 | AD84: -13745.05
A85: 2000216 | B85: Bife Ancho + 2 kls. Grano | AB85: 974.4 | AC85: 14.9 | AD85: -14518.56
A86: 2000231 | B86: Bife Angosto c/c c/grasa de 3 a 4 kls. | AB86: 296.59 | AC86: 12.8 | AD86: -3796.352
A87: 2000506 | B87: Aguja GF | AB87: 6486.76 | AC87: 7.4 | AD87: -48002.024
A88: 2000531 | B88: Bife Angosto para logs | AB88: =SUM(C88:AA88) -> 0 | AC88: 5.5 | AD88: =-ABS(AB88*AC88) -> 0
A89: 2000593 | B89: Tejido Conectivo Logs | AB89: 24.28 | AC89: 4.5 | AD89: -109.26
A90: 2000909 | B90: Bife de Paleta | AB90: 71.14 | AC90: 8 | AD90: -569.12
A91: 2838229 | B91: Corazon de Cuadril ER - Heart of Rump | AB91: =SUM(C91:AA91) -> 0 | AC91: 11.62 | AD91: =-ABS(AB91*AC91) -> 0
A92: 4313016 | B92: Bife Ancho Vila - Filé de costela
A93: 4314116 | B93: Bife Ancho Porcion 330g UMI - Filé de Costela Fatiado | AB93: =SUM(C93:AA93) -> 0 | AD93: =-ABS(AB93*AC93) -> 0
A94: 4315116 | B94: Bife Ancho Porcion 330g INK - Filé de Costela Fatiado | AB94: =SUM(C94:AA94) -> 0 | AD94: =-ABS(AB94*AC94) -> 0
A95: 5595013 | B95: Marucha UMI - Flat Iron | AB95: =SUM(C95:AA95) -> 0 | AD95: =-ABS(AB95*AC95) -> 0
A96: 5595016 | B96: Bife Ancho UMI - Ribeye | AB96: =SUM(C96:AA96) -> 0 | AC96: 34.5 | AD96: =-ABS(AB96*AC96) -> 0
A97: 5596016 | B97: Bife Ancho INK - Ribeye | AB97: =SUM(C97:AA97) -> 0 | AC97: =678.57/40.48 -> 16.763093 | AD97: =-ABS(AB97*AC97) -> 0
A98: 5596031 | B98: Bife Angosto INK - Striploin | AB98: =SUM(C98:AA98) -> 0 | AC98: 42.35 | AD98: =-ABS(AB98*AC98) -> 0
A99: 6173036 | B99: Carne picada x500 g UMI | AB99: =SUM(C99:AA99) -> 0 | AC99: 7.5 | AD99: =-ABS(AB99*AC99) -> 0
A100: 16018990 | B100: Asado 4c Manta Grano | AB100: =SUM(C100:AA100) -> 0 | AD100: =-ABS(AB100*AC100) -> 0
...

Sheet asados
B2: entrada de Materia prima | C2: 46235 | D2: 46237 | E2: 46238 | F2: 46239 | G2: 46240 | H2: 46241 | I2: 46242 | J2: 46244 | K2: 46245 | L2: 46246 | M2: 46247 | N2: 46248 | O2: 46249 | P2: 46251 | Q2: 46252 | R2: 46253 | S2: 46254 | T2: 46255 | U2: 46256 | V2: 46257 | W2: 46258 | X2: 46259 | Y2: 46260 | Z2: 46261 | AA2: 46262 | AB2: ACUMULADO | AC2: precio | AD2: Total
A3: código | B3: Producto | C3: kls. | D3: kls. | E3: kls. | F3: kls. | G3: kls. | H3: kls. | I3: kls. | J3: kls. | K3: kls. | L3: kls. | M3: kls. | N3: kls. | O3: kls. | P3: kls. | Q3: kls. | R3: kls. | S3: kls. | T3: kls. | U3: kls. | V3: kls. | W3: kls. | X3: kls. | Y3: kls. | Z3: kls. | AA3: kls. | AB3: kls. | AC3: U$S | AD3: U$S
A4: 3000 | B4: Asado 13 costillas Pasto | F4: 538.1 | I4: 242 | J4: 262.2 | M4: 742.9 | O4: 31.1 | AB4: =SUM(C4:AA4) -> 1816.3 | AC4: =-VNR!G5 -> -4.1501137 | AD4: =AB4*AC4 -> -7537.8515
A5: 3001 | B5: Asado 13 costillas s/p Pasto | E5: 1864.2 | G5: 1375.5 | I5: 1575.2 | J5: 3531.8 | M5: 3098.1 | N5: 1638.1 | O5: 1486.8 | AB5: 14569.7 | AC5: =-VNR!G4 -> -4.2151137 | AD5: -61412.942 | AF5: $ c/imp.
A6: 3011 | B6: Asado 13 costillas Grano s/p | D6: 12629.9 | E6: 12628.9 | F6: 12379.2 | G6: 14195.5 | H6: 11974.4 | I6: 4156.7 | J6: 15211.2 | L6: 14129.4 | M6: 3726.5 | N6: 6379.1 | O6: 8753.1 | AB6: 116163.9 | AC6: =-hacienda!O19 -> 0 | AD6: =AB6*AC6 -> 0 | AF6: =+AC6*1.1391184*40.48 -> 0
A7: 3101 | B7: Asado 13 costillas Pasto s/p Nirea | AB7: =SUM(C7:AA7) -> 0 | AC7: =-VNR!G13 -> -4.3891947 | AD7: =AB7*AC7 -> 0
A8: 3911 | B8: Asado 13 costillas Grano s/p Nirea | AB8: =SUM(C8:AA8) -> 0 | AC8: =-VNR!G12 -> -5.1391947 | AD8: =AB8*AC8 -> 0
A9: 4000 | B9: Falda con hueso Pasto | D9: 1725.8 | F9: 2000.7 | G9: 854.4 | H9: 1728.4 | I9: 1370.8 | J9: 290.3 | L9: 832.7 | N9: 2238.9 | O9: 439.3 | AB9: 11481.3 | AC9: =-VNR!G6 -> -3.8501137 | AD9: -44204.31
A10: 4010 | B10: Falda con hueso Grano | D10: 5699.9 | E10: 5970 | F10: 4718.8 | H10: 3910 | I10: 2466.7 | J10: 1743.5 | L10: 5070.1 | M10: 2739.1 | N10: 2512.4 | O10: 3010.8 | AB10: 37841.3 | AC10: =-VNR!G7 -> -4.5501137 | AD10: -172182.22
A11: 980039 | B11: Sobrante - falda | D11: 47.47 | E11: 30.61 | F11: 30.97 | G11: 35.64 | H11: 34.38 | I11: 3.82 | K11: 271.9 | L11: 22 | M11: 1179.69 | N11: 359.04 | O11: 88.05 | AB11: 2103.57 | AC11: =+AC9 -> -3.8501137 | AD11: -8098.9836
A12: 980060 | B12: Sobrante - Asado 980060 | C12: 167.91 | D12: 1502.59 | E12: 547.79 | F12: 424.27 | G12: 486.26 | H12: 410.12 | I12: 855.42 | J12: 831.98 | K12: 1190.17 | L12: 491.92 | M12: 339.62 | N12: 239.63 | O12: 214.87 | AB12: 7702.55 | AC12: =+AC5 -> -4.2151137 | AD12: -32467.124
A13: 980090 | B13: Sobrante - Trimming | D13: 340.98 | E13: 972.04 | F13: 590.81 | G13: 505.35 | H13: 536.53 | I13: 90.45 | J13: 1015.06 | L13: 987.07 | M13: 723.5 | N13: 119.92 | O13: 72.11 | AB13: 5953.82 | AC13: -4.5 | AD13: -26792.19
A14: 980091 | B14: Sobrante - Manta | H14: 9.67 | L14: 5.53 | N14: 108.92 | O14: 13.13 | AB14: 137.25 | AC14: -16.543 | AD14: -2270.5267
A15: 441160 | B15: Asado 1 Costilla UMI | AB15: =SUM(C15:AA15) -> 0 | AC15: -20.571 | AD15: =AB15*AC15 -> 0
A16: 441860 | B16: Asado 8c (manta) UMI | AB16: =SUM(C16:AA16) -> 0 | AC16: -15.512 | AD16: =AB16*AC16 -> 0
A17: 2000008 | B17: Recorte (C.F.) | H17: 16.97 | J17: 20.21 | L17: 50.03 | O17: 68.44 | AB17: 155.65 | AC17: -4.5 | AD17: -700.425
A18: 1987420 | B18: Brazuelo s/h c/conical GF Angus | D18: 324.5 | E18: 86.77 | F18: 195.94 | G18: 328.14 | H18: 228.13 | I18: 21.97 | J18: 88.64 | AB18: =SUM(C18:AA18) -> 1274.09 | AD18: =-AB18*AC18 -> 0
A19: 1987434 | B19: Garron s/h GF Angus | J19: 279.58 | M19: 331.98 | N19: 370.87 | O19: 195.55 | AB19: =SUM(C19:AA19) -> 1177.98 | AD19: =-AB19*AC19 -> 0
A20: 16018990 | B20: Asado 4c Manta Grano | L20: 2238.04
A21: 16101790 | B21: ASADO | AB21: =SUM(C21:AA21) -> 0 | AC21: =-VNR!G18 -> -11.770102 | AD21: =AB21*AC21 -> 0
A22: 16103290 | B22: ASADO 3C | AB22: =SUM(C22:AA22) -> 0 | AC22: =-VNR!G19 -> -11.770102 | AD22: =AB22*AC22 -> 0
A23: 16105240 | B23: ASADO NIREA | AB23: =SUM(C23:AA23) -> 0 | AC23: =-VNR!G20 -> -11.960102 | AD23: =AB23*AC23 -> 0
A24: 16601910 | B24: ASADO 5C | AB24: =SUM(C24:AA24) -> 0 | AC24: =-VNR!G21 -> -3.6301016 | AD24: =AB24*AC24 -> 0
A25: 17001910 | B25: ASADO CON HUESO | AB25: =SUM(C25:AA25) -> 0 | AC25: =-VNR!G22 -> -3.1101016 | AD25: =AB25*AC25 -> 0
A26: 17071910 | B26: ASADO C/H TRASERO | AB26: =SUM(C26:AA26) -> 0 | AC26: =-VNR!G23 -> -3.6601016 | AD26: =AB26*AC26 -> 0
A27: 18001510 | B27: Falda Nirea Pasto (bins) | AB27: =SUM(C27:AA27) -> 0 | AC27: =-VNR!G10 -> -3.1540168 | AD27: =AB27*AC27 -> 0
A28: 18001511 | B28: Falda Nirea Grano (bins) | AB28: =SUM(C28:AA28) -> 0 | AC28: =-VNR!G11 -> -4.3452224 | AD28: =AB28*AC28 -> 0
A29: 18001830 | B29: FALDA C/H BOV CONG. BLOQ. | AB29: =SUM(C29:AA29) -> 0 | AC29: =-VNR!G10 -> -3.1540168 | AD29: =AB29*AC29 -> 0
A30: 25169820 | B30: ASADO SIN HUESO | AB30: =SUM(C30:AA30) -> 0 | AC30: =-VNR!G26 -> -13.390117 | AD30: =AB30*AC30 -> 0
A31: 21765230 | B31: Falda s/h Taurus | K31: 8703.47 | AB31: 8703.47 | AC31: =-VNR!G25 -> -7.2601016 | AD31: -63188.077
A32: 21769820 | B32: Falda s/h Grano | D32: 2089.11 | E32: 1456.51 | F32: 944.63 | G32: 2246.42 | H32: 1757.97 | I32: 6464.73 | J32: 2999.56 | K32: 2354.59 | L32: 1777.97 | M32: 17.49 | N32: 3120.18 | O32: 2081.71 | AB32: 27310.87 | AC32: =-VNR!G24 -> -7.3601016 | AD32: -201010.78
B33: Total | C33: =SUM(C4:C32) -> 167.91 | D33: 24360.25 | E33: 23556.82 | F33: 21823.42 | G33: 20027.21 | H33: 20606.57 | I33: 17247.79 | J33: 26274.03 | K33: 12520.13 | L33: 25604.76 | M33: 12898.88 | N33: 17087.06 | O33: 16454.96 | P33: =SUM(P4:P32) -> 0 | Q33: =SUM(Q4:Q32) -> 0 | R33: =SUM(R4:R32) -> 0 | S33: =SUM(S4:S32) -> 0 | T33: =SUM(T4:T32) -> 0 | U33: =SUM(U4:U32) -> 0 | V33: =SUM(V4:V32) -> 0 | W33: =SUM(W4:W32) -> 0 | ... AA33: =SUM(AA4:AA32) -> 0 | AB33: 236391.75 | AD33: =SUM(AD4:AD32) -> -619865.42
B35: Salida Producto Final | C35: =C2 -> 46235 | D35: 46237 | E35: 46238 | F35: 46239 | G35: 46240 | H35: 46241 | I35: 46242 | J35: 46244 | K35: 46245 | L35: 46246 | M35: 46247 | N35: 46248 | O35: 46249 | P35: 46251 | Q35: 46252 | R35: 46253 | S35: 46254 | T35: 46255 | U35: 46256 | V35: 46257 | W35: 46258 | X35: 46259 | Y35: 46260 | Z35: 46261 | AA35: 46262 | AB35: ACUMULADO | AC35: precio | AD35: Total | AG35: Envasado
A36: código | B36: Producto | C36: kls. | D36: kls. | E36: kls. | F36: kls. | G36: kls. | H36: kls. | I36: kls. | J36: kls. | K36: kls. | L36: kls. | M36: kls. | N36: kls. | O36: kls. | P36: kls. | Q36: kls. | R36: kls. | S36: kls. | T36: kls. | U36: kls. | V36: kls. | W36: kls. | X36: kls. | Y36: kls. | Z36: kls. | AA36: kls. | AB36: kls. | AC36: U$S | AD36: U$S | AG36: U$S total x kg
A37: 13390 | B37: TRIMMINGS ANGUS 80 CL (13) | D37: 136.05 | E37: 81.63 | G37: 108.84 | H37: 81.63 | J37: 27.21 | L37: 136.05 | M37: 217.68 | N37: 272.1 | AB37: =SUM(C37:AA37) -> 1061.19 | AC37: 5.5 | AD37: =AB37*AC37 -> 5836.545 | AE37: =+AD37*0.03 -> 175.09635 | AF37: =-AD37*0.015 -> -87.548175 | AG37: =-envases!BL19*AB37 -> -56.251249
A38: 437060 | B38: ASADO TIRA 8/C (Vacum pack) GF | D38: 270.52 | E38: 620.73 | F38: 671.33 | G38: 945.58 | H38: 145.63 | I38: 1864.76 | J38: 974.05 | L38: 655.51 | N38: 758.96 | AB38: =SUM(C38:AA38) -> 6907.07 | AC38: =envases!J106 -> 12.916046 | AD38: 89212.032 | AG38: =-envases!I121*AB38 -> -2090.9908
A39: 437660 | B39: Asado (al vacio) 8 costillas | D39: 35.99 | E39: 983.68 | F39: 656.75 | G39: 391.57 | I39: 22.59 | J39: 279.76 | L39: 113.85 | N39: 562.88 | O39: 16.25 | AB39: 3063.32 | AC39: =envases!J174 -> 12.170889 | AD39: 37283.328 | AG39: =-envases!I189*AB39 -> -1027.2349
A40: 438160 | B40: Asado del Rey VILA cong. | AB40: =SUM(C40:AA40) -> 0 | AC40: =envases!E399 -> 15.772479 | AD40: =AB40*AC40 -> 0 | AG40: =-envases!D416*AB40 -> 0
A41: 438260 | B41: Asado 2 y medio Vila | AB41: =SUM(C41:AA41) -> 0 | AC41: =690/40.18 -> 17.172723 | AD41: =AB41*AC41 -> 0 | AG41: =-envases!D552*AB41 -> 0
A42: 438360 | B42: Asado 3/c en tiras Vila | D42: 136.14 | E42: 243.73 | F42: 59.66 | G42: 230.86 | H42: 95.93 | I42: 144.29 | J42: 243.78 | L42: 59.9 | M42: 145.03 | N42: 103.66 | O42: 49.69 | AB42: 1512.67 | AC42: =envases!E418 -> 14.778937 | AD42: 22355.654 | AG42: =-envases!D435*AB42 -> -1134.0942
A43: 438460 | B43: Asado 4 costillas en tiras | C43: 46.4 | D43: 691.62 | F43: 44.03 | G43: 110.97 | H43: 584.41 | J43: 107.49 | L43: 51.82 | M43: 50.67 | N43: 75.47 | O43: 91.43 | AB43: 1854.31 | AC43: =envases!E456 -> 16.766021 | AD43: 31089.4 | AG43: =-envases!D474*AB43 -> -1122.8504
A44: 438560 | B44: Asado 5 costillas en tiras | D44: 278.47 | E44: 561.61 | F44: 117.75 | G44: 554.45 | H44: 144.26 | I44: 260.76 | J44: 554.39 | L44: 183.7 | M44: 305.65 | N44: 239.75 | O44: 86.03 | AB44: 3286.82 | AC44: =envases!E437 -> 15.772479 | AD44: 51841.299 | AG44: =-envases!D454*AB44 -> -2059.0637
A45: 441160 | B45: Asado 1 Costilla (Asado del Rey) UMI | AB45: =SUM(C45:AA45) -> 0 | AC45: 20.571 | AD45: =AB45*AC45 -> 0
A46: 443060 | B46: Asado 4 costillas manta EL RANCHO | I46: 202.15 | AB46: 202.15 | AC46: =630/40.18 -> 15.679443 | AD46: 3169.5993 | AG46: =-envases!BG122*AB46 -> -67.831865
A47: 443160 | B47: Asado del Rey EL RANCHO | AB47: =SUM(C47:AA47) -> 0 | AC47: 11.16 | AD47: =AB47*AC47 -> 0
A48: 443360 | B48: Asado 3 costillas tira EL RANCHO | AB48: =SUM(C48:AA48) -> 0 | AD48: =AB48*AC48 -> 0
A49: 443560 | B49: Asado 5 costillas tira EL RANCHO | AB49: =SUM(C49:AA49) -> 0 | AC49: =660/40.18 -> 16.426083 | AD49: =AB49*AC49 -> 0 | AG49: =-envases!BG142*AB49 -> 0
A50: 443760 | B50: Asado 7 costillas tira EL RANCHO | AB50: =SUM(C50:AA50) -> 0 | AC50: =616/40.18 -> 15.33101 | AD50: =AB50*AC50 -> 0 | AG50: =-envases!BG162*AB50 -> 0
A51: 980039 | B51: Sobrante - falda | D51: 48.12 | E51: 41.25 | F51: 35.64 | G51: 23.94 | H51: 3.82 | J51: 293.9 | K51: 1174.7 | L51: 281.7 | N51: 99.27 | O51: 17.78 | AB51: 2020.12 | AC51: 4.155 | AD51: 8393.5986
A52: 980060 | B52: SOBRANTE - ASADO 980060 | C52: 117 | D52: 336.54 | E52: 364.31 | F52: 687.02 | G52: 447.88 | H52: 581.75 | I52: 1044.33 | J52: 1128.63 | K52: 355.63 | L52: 749.1 | M52: =424.59-349.1 -> 75.49 | N52: 66.72 | O52: 354.05 | AB52: 6308.45 | AC52: 4.8 | AD52: 30280.56
A53: 980090 | B53: Sobrante - Trimmings 980090 | D53: 999 | E53: 590.81 | F53: 505.35 | G53: 539.53 | H53: 63.59 | I53: 1041.92 | J53: 669.99 | K53: 356.03 | L53: 695.72 | M53: 133.82 | N53: 72.11 | O53: 410.12 | AB53: 6077.99 | AC53: 4.5 | AD53: 27350.955
A54: 980035 | B54: SOBRANTE - MATAMBRE | AB54: =SUM(C54:AA54) -> 0 | AC54: 4.5 | AD54: =AB54*AC54 -> 0
A55: 981035 | B55: Matambre block -carne sin envasar logs | AB55: =SUM(C55:AA55) -> 0 | AC55: 4.5 | AD55: =AB55*AC55 -> 0
A56: 991039 | B56: FALDA C/H INTERF. Bone In Beef Navel Plate | D56: 1725.08 | F56: 1960.63 | G56: 811.97 | H56: 1638.94 | I56: 1367.98 | J56: 294.02 | L56: 757.93 | N56: 2100.32 | O56: 456.65 | AB56: 11113.52 | AC56: 4.6 | AD56: 51122.192 | AE56: =+AD56*0.03 -> 1533.6658 | AF56: =-AD56*0.015 -> -766.83288 | AG56: =-envases!AC121*AB56 -> -758.54378
A57: 991090 | B57: Trozos de carne 70VL - BEEF PIECES 70VL GF ANGUS | D57: 516.99 | E57: 380.94 | F57: 299.31 | G57: 326.52 | H57: 734.67 | I57: 81.63 | J57: 435.36 | L57: =816.3-663.66 -> 152.64 | M57: 380.94 | N57: 489.78 | O57: 435.36 | AB57: 4234.14 | AC57: 4.6 | AD57: 19477.044 | AE57: 584.31132 | AF57: -292.15566 | AG57: =-envases!AC155*AB57 -> -224.44205
A58: 991260 | B58: ASADO C/H TRASERO GRAIN FED - HIND RIBS | D58: 4974.27 | E58: 4572.39 | F58: 4905.57 | G58: 5536.57 | H58: 4123.2 | I58: 1484.68 | J58: 5708.98 | L58: 6042.02 | M58: 1436.62 | N58: 2350.19 | O58: 3537.79 | AB58: 44672.28 | AC58: 4.7 | AD58: 209959.72 | AE58: 6298.7915 | AF58: -3149.3957 | AG58: =-envases!AC359*AB58 -> -3896.822
A59: 991190 | B59: Trozos de carne 10VL - BEEF PIECES 10VL Grain fed | D59: 1040 | E59: 920 | F59: 1220 | G59: 900 | H59: 1020 | I59: 40 | J59: 800 | L59: 1220 | M59: 420 | N59: 200 | O59: 560 | AB59: 8340 | AC59: 4.6 | AD59: 38364 | AE59: 1150.92 | AF59: -575.46 | AG59: =-envases!AC274*AB59 -> -601.45566
A60: 991290 | B60: Trozos de carne 55VL - BEEF PIECES 55VL GF ANGUS | D60: 571.41 | E60: 816.3 | F60: 1224.45 | G60: 81.63 | H60: 299.31 | I60: 81.63 | J60: 625.83 | L60: 1278.87 | M60: 489.78 | N60: 217.68 | O60: 571.41 | AB60: 6258.3 | AC60: 3.5 | AD60: 21904.05 | AE60: 657.1215 | AF60: -328.56075 | AG60: =-envases!AC376*AB60 -> -331.73813
A61: 991360 | B61: Asado c/h 3/c - fozen Beef bone in Ribs Angus (3 ribs) | AB61: =SUM(C61:AA61) -> 0 | AC61: 3.4 | AD61: =AB61*AC61 -> 0 | AE61: =+AD61*0.03 -> 0 | AF61: =-AD61*0.015 -> 0 | AG61: =-envases!AC444*AB61 -> 0
A62: 991390 | B62: Trozos de carne 65VL - BEEF PIECES 65VL GF ANGUS | D62: 408.15 | E62: 653.04 | F62: 625.83 | G62: 244.89 | H62: 435.36 | I62: 27.21 | J62: 625.83 | L62: 516.99 | M62: 353.73 | N62: 217.68 | O62: 272.1 | AB62: 4380.81 | AC62: 4.625 | AD62: 20261.246 | AE62: 607.83739 | AF62: -303.91869 | AG62: =-envases!AC461*AB62 -> -232.21669
A63: 991560 | B63: ASADO C/H 5/c (delantero) - Rib Plate | E63: 506.61 | F63: 113.56 | G63: 308.42 | H63: 101.62 | I63: 500.34 | J63: 1034.97 | L63: 19.62 | M63: 774.15 | N63: 300.62 | O63: 429.95 | AB63: 4089.86 | AC63: 4.925 | AD63: 20142.56 | AE63: 604.27681 | AF63: -302.13841 | AG63: =-envases!AC546*AB63 -> -324.22369
A64: 991590 | B64: Trozos de carne 75VL - BEEF PIECES 75VL GF ANGUS | D64: 408.15 | E64: 462.57 | F64: 408.15 | G64: 843.51 | H64: 843.51 | I64: 54.42 | J64: 897.93 | L64: 163.26 | M64: 680.25 | N64: 435.36 | O64: 516.99 | AB64: 5714.1 | AC64: 4.625 | AD64: 26427.712 | AE64: 792.83137 | AF64: -396.41569 | AG64: =-envases!AC563*AB64 -> -302.89134
A65: 991790 | B65: Trozos de carne 80VL - BEEF PIECES 80VL ANGUS | D65: 435.36 | E65: 190.47 | F65: 108.84 | G65: 380.94 | H65: 244.89 | J65: 408.15 | L65: 163.26 | M65: 571.41 | N65: 571.41 | O65: 108.84 | AB65: 3183.57 | AC65: 4.625 | AD65: 14724.011 | AE65: 441.72034 | AF65: -220.86017 | AG65: =-envases!AC648*AB65 -> -168.75375
A66: 991860 | B66: ASADO C/H 8/c (trasero) - Rib Plate | E66: 1252.89 | F66: 286.4 | G66: 808.56 | H66: 358.41 | I66: 1241.74 | J66: 2686.08 | L66: 22.41 | M66: 2082.68 | N66: 864.11 | O66: 1264.48 | AB66: 10867.76 | AC66: 4.925 | AD66: 53523.718 | AE66: 1605.7115 | AF66: -802.85577 | AG66: =-envases!AC682*AB66 -> -839.60668
A67: 993032 | B67: VACIO GRUESO (3 X paq.) - Flap meat | F67: 24.99 | H67: 24.96 | L67: 20.82 | M67: 40.75 | AB67: 111.52 | AC67: 11.1 | AD67: 1237.872 | AE67: 37.13616 | AF67: -18.56808 | AG67: =-envases!X34*AB67 -> -11.331957
A68: 993133 | B68: Bife de Vacio (Inter) - Flank steak | AB68: =SUM(C68:AA68) -> 0 | AC68: 9.7 | AD68: =AB68*AC68 -> 0 | AE68: =+AD68*0.03 -> 0 | AF68: =-AD68*0.015 -> 0 | AG68: =-envases!X82*AB68 -> 0
A69: 993290 | B69: TRIMMINGS ANGUS 75 CL | AB69: =SUM(C69:AA69) -> 0 | AC69: 5.116 | AD69: =AB69*AC69 -> 0 | AE69: =+AD69*0.03 -> 0 | AF69: =-AD69*0.015 -> 0 | AG69: =-envases!X99*AB69 -> 0
A70: 993590 | B70: TRIMMINGS ANGUS 85 CL | J70: 54.42 | L70: 54.42 | M70: 108.84 | N70: 27.21 | AB70: 244.89 | AC70: 5 | AD70: 1224.45 | AE70: 36.7335 | AF70: -18.36675 | AG70: =-envases!X116*AB70 -> -12.981057
A71: 993890 | B71: TRIMMINGS ANGUS 90 CL | D71: 27.21 | L71: 27.21 | N71: 54.42 | AB71: 108.84 | AC71: 5.74 | AD71: 624.7416 | AE71: =+AD71*0.03 -> 18.742248 | AF71: =-AD71*0.015 -> -9.371124 | AG71: =-envases!X133*AB71 -> -5.7693589
A72: 998136 | B72: PICADA ESPECIAL | AB72: =SUM(C72:AA72) -> 0 | AC72: 6.7 | AD72: =AB72*AC72 -> 0 | AG72: =-envases!S235*AB72 -> 0
A73: 998160 | B73: Asado Tiras | D73: 265.03 | E73: 218.68 | F73: 113.96 | G73: 137.81 | H73: 240.74 | I73: 280.08 | J73: 217.57 | K73: 28.26 | L73: 169.03 | M73: 59.62 | N73: 218.42 | O73: 89.23 | AB73: 2038.43 | AC73: 5.57 | AD73: 11354.055 | AG73: =-envases!N257*AB73 -> -735.22174
A74: 998560 | B74: Asado 10/c Manta GF (inter) | AB74: =SUM(C74:AA74) -> 0 | AC74: 7.31 | AD74: =AB74*AC74 -> 0 | AG74: =envases!S283*AB74 -> 0
A75: 998760 | B75: Asado 10/c Manta Abasto (grass) | AB75: =SUM(C75:AA75) -> 0 | AC75: 6.14 | AD75: =AB75*AC75 -> 0 | AE75: =+AD75*0.03 -> 0 | AF75: =-AD75*0.015 -> 0 | AG75: =-envases!S299*AB75 -> 0
A76: 1987039 | B76: FALDA c/h Vila - Bone in Beef Navel Plate Grain Fed Angus | D76: 2610.51 | E76: 2160.79 | F76: 1308 | H76: 996.79 | I76: 985.13 | J76: 386.78 | L76: 1625.17 | M76: 916.94 | N76: 908.14 | O76: 1766.56 | AB76: 13664.81 | AC76: 5.3 | AD76: 72423.493 | AE76: 2172.7048 | AF76: -1086.3524 | AG76: =-envases!AM35*AB76 -> -1465.3081
A77: 1987060 | B77: Asado c/h 4/c (Aguja) - Chuck Short Ribs Grain fed Angus | D77: 294.95 | E77: 131.02 | F77: 163.12 | G77: 598.39 | H77: 230.6 | J77: 211.91 | L77: 437.02 | M77: 188.7 | N77: 138.6 | O77: 328.63 | AB77: 2722.94 | AC77: 9.225 | AD77: 25119.122 | AE77: 753.57365 | AF77: -376.78682 | AG77: =-envases!AM53*AB77 -> -928.30897
A78: 1987139 | B78: Falda s/h - Brisket Navel End 120d GF Angus | D78: 1074.45 | E78: 2472.79 | F78: 2267.89 | G78: 2165.69 | H78: 2898.08 | I78: 6261.87 | J78: 2603.99 | K78: 3156.65 | L78: 2700.97 | M78: 1570.17 | N78: 3285.66 | O78: 2612.95 | AB78: 33071.16 | AC78: 7.325 | AD78: 242246.25 | AE78: 7267.3874 | AF78: -3633.6937 | AG78: =-envases!AM70*AB78 -> -6170.469
A79: 1987093 | B79: INTERCOSTALES CORTOS Vila - Rib fingers Grain Fed Angus | I79: 15.96 | AB79: 15.96 | AC79: 14.7 | AD79: 234.612 | AE79: 7.03836 | AF79: -3.51918 | AG79: =-envases!AM104*AB79 -> -4.3207773
A80: 1987160 | B80: Asado de Centro c/h 3/c - Short Ribs grain fed angus | D80: 1516.05 | E80: 1216.48 | F80: 564.35 | G80: 1675.46 | H80: 1550.79 | J80: 1119.56 | L80: 1323.25 | M80: 626.1 | N80: 488.67 | O80: 1054.94 | AB80: 11135.65 | AC80: 8.825 | AD80: 98272.111 | AE80: 2948.1633 | AF80: -1474.0817 | AG80: =-envases!AM122*AB80 -> -3887.1754
A81: 1987193 | B81: INTERCOSTALES DE ASADO Vila - Intercostal Meat Grain Fed Angus | AB81: =SUM(C81:AA81) -> 0 | AC81: 12.725 | AD81: =AB81*AC81 -> 0 | AE81: =+AD81*0.03 -> 0 | AF81: =-AD81*0.015 -> 0 | AG81: =-envases!AM87*AB81 -> 0
A82: 1987960 | B82: Trozos de Asado Vila - SHORT RIB PIECES GRAIN FED ANGUS | D82: 659.88 | E82: 641.65 | F82: 339.13 | G82: 768.48 | H82: 806.55 | I82: 125.41 | J82: 595.49 | L82: 609.19 | M82: 178.86 | N82: 253.57 | O82: 426.62 | AB82: 5404.83 | AC82: 2.925 | AD82: 15809.128 | AE82: =+AD82*0.03 -> 474.27383 | AF82: =-AD82*0.015 -> -237.13692 | AG82: =-envases!AM139*AB82 -> -683.60593
A83: 1992139 | B83: Falda s/h Vila - Brisket Navel End | D83: 764.44 | E83: 198.57 | AB83: 963.01 | AC83: 9 | AD83: =AB83*AC83 -> 8667.09 | AE83: =+AD83*0.03 -> 260.0127 | AF83: =-AD83*0.015 -> -130.00635
A84: 1994139 | B84: Falda s/h TG - Brisket Navel End M3+ | AB84: =SUM(C84:AA84) -> 0 | AC84: 9.4 | AD84: =AB84*AC84 -> 0 | AE84: =+AD84*0.03 -> 0 | AF84: =-AD84*0.015 -> 0
A85: 2000035 | B85: PUNTAS DE MATAMBRE LOGS | D85: 111.6 | E85: 352.89 | F85: 82.39 | G85: 80.57 | H85: 270.35 | I85: 108.65 | J85: 126.18 | K85: 261.33 | L85: 134.24 | N85: 591.4 | O85: 398.56 | AB85: 2518.16 | AC85: 4.5 | AD85: 11331.72
A86: 2000060 | B86: TAPA DE ASADO S/H LOGS | D86: 643.64 | E86: 704.13 | F86: 788.16 | G86: 1002.31 | H86: 966 | I86: 38.05 | J86: 1007.37 | L86: 1057.67 | M86: 620.89 | N86: 315.43 | O86: 708.57 | AB86: 7852.22 | AC86: 5.5 | AD86: 43187.21
A87: 3516139 | B87: Falda s/h - Brisket Navel Plate | AB87: =SUM(C87:AA87) -> 0 | AC87: 12.7 | AD87: =AB87*AC87 -> 0 | AE87: =+AD87*0.03 -> 0 | AF87: =-AD87*0.015 -> 0 | AG87: =-envases!BQ82*AB87 -> 0
A88: 3516193 | B88: Intercostales largos - Intercostal Meat | D88: 23.37 | G88: 61.99 | J88: 10.14 | AB88: 95.5 | AC88: 13.6 | AD88: 1298.8 | AE88: =+AD88*0.03 -> 38.964 | AF88: =-AD88*0.015 -> -19.482 | AG88: =-envases!BQ62*AB88 -> -41.895224
A89: 3516360 | B89: Asado s/h 3/c (centro) - Boneless Short Ribs | E89: 75.2 | F89: 36.96 | J89: 84.49 | L89: 78.25 | O89: 62.39 | AB89: 337.29 | AC89: 20.925 | AD89: 7057.7932 | AE89: 211.7338 | AF89: -105.8669 | AG89: =-envases!BQ22*AB89 -> -105.34295
A90: 3516460 | B90: Asado s/h 4/c (Aguja) - Boneless Chuck Short Ribs | J90: 82.25 | L90: 43.98 | AB90: 126.23 | AC90: 14.2 | AD90: 1792.466 | AE90: 53.77398 | AF90: -26.88699 | AG90: =-envases!BQ42*AB90 -> -34.95222
A91: 3673760 | B91: Asado 8/c en tiras GF Angus | E91: 689.98 | F91: 74.49 | G91: 17.2 | AB91: 781.67 | AC91: 12.725 | AD91: 9946.7508 | AE91: 298.40252 | AF91: -149.20126 | AG91: =-envases!AR59*AB91 -> -236.63649
A92: 4516060 | B92: Asado c/h 4/c (Aguja) TG - Chuck short ribs | D92: 25.12 | G92: 122.04 | L92: 38.12 | AB92: 185.28 | AC92: 12.925 | AD92: 2394.744 | AE92: 71.84232 | AF92: -35.92116 | AG92: =-envases!BV62*AB92 -> -62.993346
A93: 4516093 | B93: Intercostales cortos TG - Rib fingers | F93: 18.33 | I93: 19.26 | AB93: 37.59 | AC93: 15 | AD93: 563.85 | AE93: 16.9155 | AF93: -8.45775 | AG93: =-envases!BV22*AB93 -> -12.222172
A94: 4516139 | B94: Falda s/hueso TG - Brisket Navel | D94: 2034.43 | E94: 367.31 | F94: 280.79 | H94: 200.15 | I94: 638.41 | J94: 486.76 | K94: 6882.95 | L94: 193.8 | M94: 59.67 | N94: 717.16 | O94: 81.74 | AB94: 11943.17 | AC94: 8.8 | AD94: =AB94*AC94 -> 105099.9 | AE94: =+AD94*0.03 -> 3152.9969 | AF94: =-AD94*0.015 -> -1576.4984
A95: 4516160 | B95: Asado c/h 3/c (centro) TG - Short ribs | D95: 479.12 | E95: 176.14 | F95: 32.42 | G95: 216.38 | H95: 244.8 | J95: 184.44 | L95: 342.1 | M95: 12.65 | N95: 37.08 | O95: 99.45 | AB95: 1824.58 | AC95: 10.567568 | AD95: 19281.373 | AE95: =+AD95*0.03 -> 578.4412 | AF95: =-AD95*0.015 -> -289.2206 | AG95: =-envases!BV42*AB95 -> -620.33895
A96: 4543760 | B96: Asado 7C 2tiras VILA ANGUS - COSTELA DO DIANTEIRO (EM TIRAS) | AB96: =SUM(C96:AA96) -> 0 | AC96: 17 | AD96: =AB96*AC96 -> 0 | AE96: =+AD96*0.03 -> 0 | AF96: =-AD96*0.015 -> 0 | AG96: =-envases!CK22*AB96 -> 0
A97: 4543860 | B97: ASADO 4C TIRAS PREMIUM VILA ANGUS - COSTELA DO DIANTEIRO (EM TIRAS) | AB97: =SUM(C97:AA97) -> 0 | AC97: 17 | AD97: =AB97*AC97 -> 0 | AE97: =+AD97*0.03 -> 0 | AF97: =-AD97*0.015 -> 0 | AG97: =-envases!CA42*AB97 -> 0
A98: 4545160 | B98: ASADO 1C UMI - COSTELA DO TRASEIRO | AB98: =SUM(C98:AA98) -> 0 | AC98: 15 | AD98: =AB98*AC98 -> 0 | AE98: =+AD98*0.03 -> 0 | AF98: =-AD98*0.015 -> 0 | AG98: =-envases!CF21*AB98 -> 0
A99: 4545460 | B99: ASADO 4C (manta) UMI - COSTELA DO DIANTEIRO | AB99: =SUM(C99:AA99) -> 0 | AC99: 18 | AD99: =AB99*AC99 -> 0 | AE99: =+AD99*0.03 -> 0 | AF99: =-AD99*0.015 -> 0 | AG99: =-envases!CF41*AB99 -> 0
A100: 4545960 | B100: ASADO 4C EN TIRAS UMI - COSTELA DO DIANTEIRO (EM TIRAS) | F100: 88.38 | I100: 171.5 | K100: 89.6 | M100: 49.34 | N100: 182.24 | O100: 78.78 | AB100: 659.84 | AC100: 20.5 | AD100: 13526.72 | AE100: 405.8016 | AF100: -202.9008 | AG100: =-envases!CF61*AB100 -> -295.88712
A101: 4546960 | B101: ASADO S/hueso INK - COSTELA DO DIANTEIRO | AB101: =SUM(C101:AA101) -> 0 | AC101: 28 | AD101: =AB101*AC101 -> 0 | AE101: =+AD101*0.03 -> 0 | AF101: =-AD101*0.015 -> 0 | AG101: =-envases!CK22*AB101 -> 0
A102: 4858160 | B102: ASADO 1C VILA - COSTELA DO TRASEIRO | AB102: =SUM(C102:AA102) -> 0 | AC102: 14.5 | AD102: =AB102*AC102 -> 0 | AE102: =+AD102*0.03 -> 0 | AF102: =-AD102*0.015 -> 0 | AG102: =-envases!CP21*AB102 -> 0
...

Sheet logs
B2: entrada de Materia prima y aditivos | AB2: ACUMULADO | AC2: precio | AD2: Total
A3: código | B3: Producto | AB3: kls. | AC3: U$S | AD3: U$S
A4: 980006 | B4: Sobrante - Aguja | AB4: =SUM(C4:AA4) -> 0 | AC4: 7.6 | AD4: =AC4*AB4 -> 0
A5: 980024 | B5: Sobrante - Colita | AB5: 113.3 | AC5: =681/1.1391184/40.48 -> 14.768546 | AD5: 1673.2763
A6: 980026 | B6: Sobrante - Cuadrada | AB6: =SUM(C6:AA6) -> 0 | AC6: 6.01 | AD6: =AC6*AB6 -> 0
A7: 980090 | B7: Sobrante - Trimming | AB7: 1171.59 | AC7: 5.5 | AD7: 6443.745
A8: 980091 | B8: Sobrante - Manta 980091 | AB8: 63.88 | AC8: 5.5 | AD8: 351.34
A9: 991026 | B9: Cuadrada China | AB9: =SUM(C9:AA9) -> 0 | AC9: 6.01 | AD9: =AC9*AB9 -> 0
A10: 2000006 | B10: Aguja | AB10: =SUM(C10:AA10) -> 0 | AC10: 6.3 | AD10: =AC10*AB10 -> 0
A11: 2000008 | B11: Recorte (C.F) | AB11: 5034.05 | AC11: 4.5 | AD11: 22653.225
A12: 2000012 | B12: Paleta sin marucha Logs | AB12: 4856.19 | AC12: 7.4 | AD12: 35935.806
A13: 2000022 | B13: Nalga c/t logs | AB13: 21.48 | AC13: 6.5 | AD13: 139.62
A14: 2000023 | B14: Nalga s/t logs | AB14: =SUM(C14:AA14) -> 0 | AC14: 6.5 | AD14: =AC14*AB14 -> 0
A15: 2000026 | B15: Cuadrada Logs | AB15: 3861.29 | AC15: 6.5 | AD15: 25098.385
A16: 2000027 | B16: Bola de Lomo Logs | AB16: 16570.09 | AC16: 6.5 | AD16: 107705.59
A17: 2000028 | B17: Peceto Logs | AB17: =SUM(C17:AA17) -> 0 | AC17: 6.5 | AD17: =AC17*AB17 -> 0
A18: 2000031 | B18: Bife Angosto Pasto | AB18: =SUM(C18:AA18) -> 0 | AC18: 7.4 | AD18: =AC18*AB18 -> 0
A19: 2000032 | B19: Tapa de Vacio Logs | AB19: 3630.35 | AC19: 5.5 | AD19: 19966.925
A20: 2000035 | B20: Puntas de Matambre Logs | AB20: 910.9 | AC20: 5.5 | AD20: 5009.95
A21: 2000041 | B21: Arañita logs (grano) | AB21: =SUM(C21:AA21) -> 0 | AC21: 5.5 | AD21: =AC21*AB21 -> 0
A22: 2000060 | B22: Tapa de Asado s/h logs | AB22: 874.78 | AC22: 5.5 | AD22: 4811.29
A23: 2000090 | B23: Sobrante Mat. Prima preparada para logs | AB23: 2696.92 | AC23: 5.5 | AD23: 14833.06
A24: 2000091 | B24: Manta Logs | AB24: 12339.51 | AC24: 5.5 | AD24: 67867.305
A25: 2000123 | B25: Tapa de Nalga Logs | AB25: 11934.22 | AC25: 5.5 | AD25: 65638.21
A26: 2000141 | B26: Arañita logs (pasto) | AB26: =SUM(C26:AA26) -> 0 | AC26: 4.5 | AD26: =AC26*AB26 -> 0
A27: 2000117 | B27: Pecho s/h Congelado Logs | AB27: =SUM(C27:AA27) -> 0 | AC27: 5.5 | AD27: =AC27*AB27 -> 0
A28: 2000217 | B28: Solapa de Pecho logs | AB28: 10178.4 | AC28: 5.5 | AD28: 55981.2
A29: 2000516 | B29: Bife Ancho Logs | AB29: =SUM(C29:AA29) -> 0 | AC29: 14 | AD29: =AC29*AB29 -> 0
A30: 2000531 | B30: Bife Angosto para Logs | AB30: 15.13 | AC30: 7.4 | AD30: 111.962
A31: 2000590 | B31: Trimmings 85 CL Logs en caja | AB31: 28928.28 | AC31: 5.5 | AD31: 159105.54
A32: 2000593 | B32: Tejido conectivo Logs | AB32: =SUM(C32:AA32) -> 1992.87 | AC32: 4.5 | AD32: 8967.915
A33: 2000929 | B33: Corcho de Cuadril logs | AB33: 4850.69 | AC33: 5.5 | AD33: 26678.795
A34: 4001002 | B34: Logs #F3603B | AB34: 445.5 | AD34: =AC34*AB34 -> 0
A35: 981006 | B35: Aguja - Carne sin envasar logs (congelado)
A36: 981012 | B36: Paleta - Carne sin envasar logs (congelado) | AB36: 138.69 | AC36: 6.5 | AD36: 901.485
A37: 981027 | B37: Bola de Lomo Logs - Carne sin envasar | AB37: 5933.49 | AC37: 5.5 | AD37: 32634.195
A38: 981031 | B38: B. Angosto - para beef logs (congelado) | AB38: =SUM(C38:AA38) -> 0 | AC38: 7.4 | AD38: =AC38*AB38 -> 0
A39: 981035 | B39: Matambre Block - Carne sin envasar logs (congelado) | AB39: 6857.32 | AC39: 5.5 | AD39: 37715.26
A40: 981091 | B40: Manta - Carne sin envasar logs (congelado) | AB40: =SUM(C40:AA40) -> 0 | AC40: 5.5 | AD40: =AC40*AB40 -> 0
A41: 981123 | B41: Tapa de Nalga Manta (Logs) - Carne sin envasar | AB41: 151.05 | AC41: 5.5 | AD41: 830.775
A42: 981132 | B42: Tapa de Vacio - Carne sin envasar logs (congelado) | AB42: 314.09 | AC42: 5.5 | AD42: 1727.495
A43: 981217 | B43: Solapa de Pecho - Carne sin envasar logs (congelado) | AB43: 474.1 | AC43: 5.5 | AD43: 2607.55
A44: 981593 | B44: Tejido conectivo Logs - (congelado) | AB44: 218.35 | AC44: 4.5 | AD44: 982.575
A45: 981929 | B45: Corcho de Cuadril - Carne sin envasar logs (congelado) | AB45: 230.73 | AC45: 5.5 | AD45: 1269.015
A46: 22381810 | B46: Bola de lomo logs | AB46: =SUM(C46:AA46) -> 0 | AC46: 7.1 | AD46: =AC46*AB46 -> 0
A47: 22409810 | B47: Colita de Cuadril Logs | AB47: 68.51 | AC47: 7 | AD47: 479.57
A48: 22449820 | B48: Peceto LOGS | AB48: =SUM(C48:AA48) -> 0 | AC48: 6.9 | AD48: =AC48*AB48 -> 0
A49: 22449800 | B49: Peceto NIREA | AB49: =SUM(C49:AA49) -> 0 | AC49: 6.9 | AD49: =AC49*AB49 -> 0
A50: 22609810 | B50: Tapa de Nalga Logs | AB50: 2780.35 | AC50: 5.5 | AD50: 15291.925
A51: 23779810 | B51: Solapa de Pecho logs | AB51: 16687.68 | AC51: 5.5 | AD51: 91782.24
A52: 25199830 | B52: Trimming 50cl LOGS | AB52: 4681.07 | AC52: 3 | AD52: 14043.21
A53: 998009 | B53: Paleta | AB53: =SUM(C53:AA53) -> 0 | AC53: 6.1 | AD53: =AC53*AB53 -> 0
A54: 26559820 | B54: Cuadrada LOGS | AB54: 51753.15 | AC54: 6.5 | AD54: 336395.47
B55: Materia prima logs | AB55: 609.36 | AC55: 6.5 | AD55: 3960.84
A56: 998023 | B56: Nalga s/tapa | AB56: 140.1 | AC56: 6.5 | AD56: 910.65
A57: 998027 | B57: Bola de Lomo Abasto | AB57: 300.14 | AC57: 6.5 | AD57: 1950.91
A58: 998026 | B58: Cuadrada | AB58: =SUM(C58:AA58) -> 0 | AC58: 6.01 | AD58: =AC58*AB58 -> 0
B59: Total | AB59: 201827.6 | AD59: =SUM(AD4:AD58) -> 1172456.3
B61: Salida Producto Final | AB61: ACUMULADO | AC61: precio | AD61: Total
A62: código | B62: Producto | AB62: kls. | AC62: U$S | AD62: U$S
B63: Decomiso | AB63: =SUM(C63:AA63) -> 56.92 | AD63: =AB63*AC63 -> 0
B64: Grasa Logs | AB64: =SUM(C64:AA64) -> 422.3 | AC64: 0.4 | AD64: =AB64*AC64 -> 168.92
A65: 2000090 | B65: Sobrante Mat. Prima preparada para logs | AB65: =SUM(C65:AA65) -> 2449.8 | AC65: 6.5 | AD65: =AB65*AC65 -> 15923.7
A66: 981001 | B66: Logs Phillys Best - Sin envasar | AB66: =SUM(C66:AA66) -> 32530.87 | AC66: 5.248 | AD66: =AB66*AC66 -> 170722.01 | AE66: =AD66*0.03 -> 5121.6602 | AF66: =-AD66*0.015 -> -2560.8301
A67: 981002 | B67: Logs 93 Cl Molde Chico - sin envasar | AB67: =SUM(C67:AA67) -> 227898.68 | AC67: 7.34 | AD67: =AB67*AC67 -> 1672776.3 | AE67: =AD67*0.03 -> 50183.289 | AF67: =-AD67*0.015 -> -25091.645
B68: Total | AB68: 263358.57 | AD68: =SUM(AD63:AD67) -> 1859590.9 | AE68: =SUM(AE66:AE67) -> 55304.95 | AF68: =SUM(AF66:AF67) -> -27652.475
B69: Rendimiento | AB69: =(AB68/AB59)-1 -> 0.30486896
B70: Canchadas Philly's Best | AB70: =SUM(C70:AA70) -> 108
B71: Canchadas Comun | AB71: =SUM(C71:AA71) -> 696
B72: Horas Trabajadas | AB72: Hs. | AC72: Prec/U$S | AD72: Tot/U$S
B73: Personal Tercerizado - Producción | AB73: =SUM(C73:AA73) -> 3400 | AC73: ='mano de obra'!J17 -> 10.31003 | AD73: =AB73*AC73 -> 35054.101
B74: Pesonal Ontilcor SA - Producción | AB74: =SUM(C74:AA74) -> 800 | AC74: =+'mano de obra'!J14 -> 8.6202683 | AD74: =AB74*AC74 -> 6896.2147
B75: Personal Tercerizado - Desmolde | AB75: =SUM(C75:AA75) -> 1800 | AC75: =+AC73 -> 10.31003 | AD75: =AB75*AC75 -> 18558.053
B76: Pesonal Ontilcor SA - Desmolde | AB76: =SUM(C76:AA76) -> 200 | AC76: =+AC74 -> 8.6202683 | AD76: =AB76*AC76 -> 1724.0537
B77: Total Mano de Obra | AB77: 6200 | AD77: =SUM(AD73:AD76) -> 62232.422
B78: Aditivos
A79: Philly's Best | B79: Agua | AB79: =SUM(C79:AA79) -> 12108.96
A80: Philly's Best | B80: Especies | AB80: =SUM(C80:AA80) -> 857.52
B81: Agua | AB81: =SUM(C81:AA81) -> 41934
B82: Especies | AB82: =SUM(C82:AA82) -> 4698
A84: código | B84: Desmolde Entrada
A85: 980001 | B85: Sobrante - Logs Phillys Best | AB85: =SUM(C85:AA85) -> 69695.56
A86: 980002 | B86: Sobrante Logs - Molde chico | AB86: 781.95
A87: 981001 | B87: Logs Phillys Best - Sin envasar | AB87: 25849.35
A88: 981002 | B88: Logs 93 CL Molde Chico - sin envasar | AB88: 186000.14
B89: Total | AB89: 282327
A90: 980002 | B90: Sobrante - Logs Molde Chico | AB90: =SUM(C90:AA90) -> 833.55
A91: 980001 | B91: Sobrante - Logs Phillys Best | AB91: 28817.52
A92: 4000004 | B92: Logs Lean | AB92: 19934
A93: 4001002 | B93: Logs #F3603B | AB93: 938.17
A94: 6298014 | B94: Logs Philly's Best | AB94: 64346.27
A95: 4000014 | B95: Logs Lean Angus | AB95: 166438.5
B96: Total | AB96: 281308.01

Sheet mano de obra
H2: T. Cambio $ | I2: 40.48
E4: 46235
E5: aportes patronales | F5: bse | G5: ag.Lic. Sv y ap.patronal | H5: prev.despido
B6: por hora | D6: más prima | E6: y cargas sociales | I6: Costo
D7: 0.53 | E7: 0.1263 | F7: 0.08546 | G7: 0.23914 | H7: 0.0125 | I7: total | J7: U$S
B8: Ofic. Esp. | C8: 188.96 | D8: =C8*$D$7+C8 -> 289.1088 | E8: =D8*$E$7 -> 36.514441 | F8: =D8*$F$7 -> 24.707238 | G8: =D8*$G$7 -> 69.137478 | H8: =D8*$H$7 -> 3.61386 | I8: =SUM(D8:H8) -> 423.08182 | J8: =I8/$I$2 -> 10.451626
B9: Oficial A | C9: 166.2 | D9: 254.286 | E9: 32.116322 | F9: 21.731282 | G9: 60.809954 | H9: 3.178575 | I9: 372.12213 | J9: 9.1927404
B10: Oficial B | C10: 156.69 | D10: 239.7357 | E10: 30.278619 | F10: 20.487813 | G10: 57.330395 | H10: 2.9966963 | I10: 350.82922 | J10: 8.6667298
B11: Medio Oficial | C11: 149.34 | D11: 228.4902 | E11: 28.858312 | F11: 19.526772 | G11: 54.641146 | H11: 2.8561275 | I11: 334.37256 | J11: 8.2601917
B12: Peón Pr | C12: 144.64 | D12: 221.2992 | E12: 27.950089 | F12: 18.91223 | G12: 52.921491 | H12: 2.76624 | I12: 323.84925 | J12: 8.0002285
B13: Peón | C13: 129.27 | D13: 197.7831 | E13: 24.980006 | F13: 16.902544 | G13: 47.297851 | H13: 2.4722888 | I13: 289.43579 | J13: 7.1500936
B14: Promedio | C14: =AVERAGE(C8:C13) -> 155.85 | D14: 238.4505 | E14: 30.116298 | F14: 20.37798 | G14: 57.023053 | H14: 2.9806313 | I14: 348.94846 | J14: 8.6202683
B17: Nestor Larrosa | E17: valor hora | G17: 417.35 | J17: =G17/I2 -> 10.31003

Sheet VNR
A3: código | B3: Producto | C3: Prec/U$S | D3: M.obra | E3: envases | F3: servicios | G3: VNR
A4: 3001 | B4: Asado 13 costillas Pasto | C4: 4.965 | D4: =-asados!AE127 -> -0.57281723 | E4: =-envases!EH23 -> -0.077069105 | F4: -0.1 | G4: =SUM(C4:F4) -> 4.2151137
B5: Asado 13 costillas s/p Pasto | C5: 4.9 | D5: =+D4 -> -0.57281723 | E5: =+E4 -> -0.077069105 | F5: =+F4 -> -0.1 | G5: 4.1501137
A6: 4000 | B6: Falda con hueso Pasto | C6: 4.6 | D6: =+D4 -> -0.57281723 | E6: =+E4 -> -0.077069105 | F6: =+F4 -> -0.1 | G6: 3.8501137
A7: 4010 | B7: Falda con hueso Grano | C7: 5.3 | D7: =+D6 -> -0.57281723 | E7: =+E6 -> -0.077069105 | F7: =+F6 -> -0.1 | G7: 4.5501137
A8: 4403 | B8: Entraña Gruesa Fresca | C8: =255.36/40.48 -> 6.3083004 | D8: =porcionados!AE304 -> -0.66282927 | E8: =-envases!AM18 -> -0.29729653 | F8: -0.1 | G8: 5.2481746
A9: 4407 | B9: Quijada | C9: 6.92 | D9: =D8 -> -0.66282927 | E9: =-envases!AH23 -> -0.22292945 | F9: =F8 -> -0.1 | G9: 5.9342413
A10: 18001830 | B10: Falda con hueso SJ - Pasto | C10: =158.03/40.48 -> 3.9039032 | D10: =+D7 -> -0.57281723 | E10: =+E7 -> -0.077069105 | F10: =+F9 -> -0.1 | G10: 3.1540168
A11: 18003350 | B11: Falda con hueso SJ - El Rancho | C11: =206.25/40.48 -> 5.0951087 | D11: =+D10 -> -0.57281723 | E11: -0.077069105 | F11: =+F10 -> -0.1 | G11: 4.3452224
A12: 3911 | B12: Asado 13 costillas Grano s/p Nirea | C12: =238.39/40.48 -> 5.889081 | D12: -0.57281723 | E12: -0.077069105 | F12: =+F11 -> -0.1 | G12: 5.1391947
A13: 3101 | B13: Asado 13 costillas Pasto s/p Nirea | C13: =208.03/40.48 -> 5.139081 | D13: -0.57281723 | E13: -0.077069105 | F13: =+F12 -> -0.1 | G13: =SUM(C13:F13) -> 4.3891947
A14: 438031 | B14: Bife Angosto Vila Congelado | C14: =870/1.1391184/40.48 -> 18.867306 | D14: =+D9 -> -0.66282927 | E14: =-envases!D148 -> -0.65727622 | F14: =+F9 -> -0.1 | G14: 17.4472
A15: 439016 | B15: Bife Ancho Vila | C15: =1160/1.1391184/40.48 -> 25.156407 | D15: =+D14 -> -0.66282927 | E15: =-envases!D64 -> -0.55706309 | F15: =+F14 -> -0.1 | G15: 23.836515
A17: NIREA
A18: 16101790 | B18: ASADO | C18: 12.61 | D18: =+D15 -> -0.66282927 | E18: =E4 -> -0.077069105 | F18: =+F15 -> -0.1 | G18: =SUM(C18:F18) -> 11.770102
A19: 16103290 | B19: ASADO 3C | C19: 12.61 | D19: =+D18 -> -0.66282927 | E19: =E4 -> -0.077069105 | F19: =+F18 -> -0.1 | G19: 11.770102
A20: 16105240 | B20: Asado nirea | C20: 12.8 | D20: -0.66282927 | E20: =E4 -> -0.077069105 | F20: -0.1 | G20: 11.960102
A21: 16601910 | B21: ASADO 5C | C21: 4.47 | D21: -0.66282927 | E21: =E4 -> -0.077069105 | F21: -0.1 | G21: 3.6301016
A22: 17001910 | B22: Asado con hueso | C22: 3.95 | D22: -0.66282927 | E22: =E4 -> -0.077069105 | F22: -0.1 | G22: 3.1101016
A23: 17071910 | B23: ASADO C/H TRASERO | C23: 4.5 | D23: -0.66282927 | E23: =E4 -> -0.077069105 | F23: -0.1 | G23: 3.6601016 | I23: =3/1.1391184/40.48 -> 0.065059674
A24: 21769820 | B24: Falda nirea ( caja) | C24: 8.2 | D24: -0.66282927 | E24: =E4 -> -0.077069105 | F24: -0.1 | G24: 7.3601016
A25: 21765230 | B25: Falda nirea Taurus | C25: 8.1 | D25: -0.66282927 | E25: =E5 -> -0.077069105 | F25: -0.1 | G25: =SUM(C25:F25) -> 7.2601016
A26: 25169820 | B26: ASADO SIN HUESO (INTERCOSTALES) | C26: 14.230015 | D26: =+D24 -> -0.66282927 | E26: =E4 -> -0.077069105 | F26: =+F24 -> -0.1 | G26: 13.390117
A27: 18961511 | B27: Pecho Nirea (bins) | C27: =193.75/40.48 -> 4.7863142 | D27: -0.66282927 | E27: =E5 -> -0.077069105 | F27: -0.1 | G27: 3.9464159

Sheet envases
D1: 46216 | E1: dólar 13/07/26 | J1: =E1 -> dólar 13/07/26 | O1: =J1 -> dólar 13/07/26 | T1: =O1 -> dólar 13/07/26 | Y1: =T1 -> dólar 13/07/26 | AD1: =Y1 -> dólar 13/07/26 | AI1: =AD1 -> dólar 13/07/26
B2: 438/439 | E2: 40.26 | G2: 437 | J2: =E2 -> 40.26 | L2: 436 | O2: =J2 -> 40.26 | Q2: 998 | T2: =O2 -> 40.26 | V2: 993 | Y2: =T2 -> 40.26 | AA2: 991 | AD2: =Y2 -> 40.26 | AF2: 884 | AI2: =AD2 -> 40.26 | AK2: 1987 | AP2: 3673 | AU2: 5687036 | AZ2: 4410 UMI | BE2: 442 / 443 RANCHO | BJ2: 13390 | BO2: 3516 | BT2: 4516 | BY2: 4543 | CD2: 4545 | CI2: 4546 | CN2: 4858 | CS2: 6172 / 6173 | CX2: 3193 | DC2: 4841 | DH2: 5516 | DM2: 1993 | DR2: 6112 | DW2: 2366
D3: Precio UYU | E3: Precio U$S | I3: Precio UYU | J3: Precio U$S | N3: Precio UYU | O3: Precio U$S
B4: 439010 | C4: Envase Chuck | D4: 490 | E4: =D4/E2 -> 12.170889 | G4: 437016 | H4: Envase Bife Ancho | I4: 1105 | J4: =I4/E2 -> 27.446597 | L4: 436031 | M4: Envase Bife Angosto 3,5 - 4 kg | N4: 447 | O4: =N4/E2 -> 11.102832 | Q4: 998001 | R4: Envase Delantero C/H | V4: 993170 | W4: Envase Entraña fina (6x paquete) | AA4: 991072 | AB4: Envase Entraña gruesa (2x paquete) | AF4: 884507 | AG4: Quijada CC - (Maseteros) / Cheek Meat | AK4: 1987072 | AL4: Envase Entraña gruesa (2x paquete) GF | AP4: 3673916 | AQ4: Envase Bife Ancho Porcionado | AU4: 5687036 | AV4: Envase Carne Picada | AZ4: 441024 | BA4: Envasado Colita de Cuadril | BE4: 442024 | BF4: Envasado Colita de Cuadril EL RANCHO | BJ4: 13390 | BK4: Envase Trimming Angus 80CL | BO4: 3516360 | BP4: Envasado Asado s/h 3c UMI | BT4: 4516093 | BU4: Envasado Intercostales Cortos Taurus | BY4: 4543760 | BZ4: Envasado Asado 7c 2 tiras Vila | CD4: 4545160 | CE4: Envase Asado 1/C UMI | CI4: 4546960 | CJ4: Envasado Asado S/H Ink | CN4: 4858160 | CO4: Envase Asado 1/C Vila Brasil | CS4: 4865160 | CT4: Envase Asado 1/C Vila Brasil | CX4: 3193072 | CY4: Envase Entraña gruesa (grass) | DC4: 4841024 | DD4: Envase Colita de Cuadril - Maminha | DH4: 5516193 | DI4: Envase Intercostales Largos INK | DM4: 1993916 | DN4: Envasado Bife Ancho TG Porcionado | DR4: 6112716 | DS4: Envase Bife Ancho | DW4: 2366095 | DX4: Envase Cubos | EF4: Envase Logs | EI4: Código | EJ4: Asado Pasto a 5 y 8 costillas China | EK4: Cantidad | EL4: Precio U$S
B5: Código | C5: Insumos | D5: Precio U$S | G5: Código | H5: Insumos | I5: Precio U$S | L5: Código | M5: Insumos | N5: Precio U$S | Q5: Código | R5: Insumos | S5: Precio U$S | V5: Código | W5: Insumos | X5: Precio U$S | AA5: Código | AB5: Insumos | AC5: Precio U$S | AF5: Código | AG5: Insumos | AH5: Precio U$S | AK5: Código | AL5: Insumos | AM5: Precio U$S | AP5: Código | AQ5: Insumos | AR5: Precio U$S | AU5: Código | AV5: Insumos | AW5: Precio U$S | AZ5: Código | BA5: Insumos | BB5: Precio U$S | BE5: Código | BF5: Insumos | BG5: Precio U$S | BJ5: Código | BK5: Insumos | BL5: Precio U$S | BO5: Código | BP5: Insumos | BQ5: Precio U$S | BT5: Código | BU5: Insumos | BV5: Precio U$S | BY5: Código | BZ5: Insumos | CA5: Precio U$S | CD5: Código | CE5: Insumos | CF5: Precio U$S | CI5: Código | CJ5: Insumos | CK5: Precio U$S | CN5: Código | CO5: Insumos | CP5: Precio U$S | CS5: Código | CT5: Insumos | CU5: Precio U$S | CX5: Código | CY5: Insumos | CZ5: Precio U$S | DC5: Código | DD5: Insumos | DE5: Precio U$S | DH5: Código | DI5: Insumos | DJ5: Precio U$S | DM5: Código | DN5: Insumos | DO5: Precio U$S | DR5: Código | DS5: Insumos | DT5: Precio U$S | DW5: Código | DX5: Insumos | DY5: Precio U$S | EE5: Código | EF5: Insumo | EG5: Precio U$S | EI5: 2037 | EJ5: Tapa | EK5: 1 | EL5: =insumos!H268 -> 0.65
C6: Envasado | H6: Envasado | M6: Envasado | R6: Envasado | W6: Envasado | AB6: Envasado | AG6: Envasado | AL6: Envasado | AQ6: Envasado | AV6: Envasado | BA6: Envasado | BF6: Envasado | BK6: Envasado | BP6: Envasado | BU6: Envasado | BZ6: Envasado | CE6: Envasado | CJ6: Envasado | CO6: Envasado | CT6: Envasado | CY6: Envasado | DD6: Envasado | DI6: Envasado | DN6: Envasado | DS6: Envasado | DX6: Envasado | EF6: 1 pallets fumigado | EG6: =512.4/40.48 -> 12.658103 | EI6: 6184 | EJ6: Fondo | EK6: 1 | EL6: =insumos!H215 -> 0.6
B7: 3741 | C7: Fondo Cofre | D7: =insumos!$G$213 -> 0.83558719 | G7: 5524 | H7: FONDO ENFRIADO (nueva medida) 505x380x155 cm - MERCOPACK | I7: =insumos!$H$217 -> 0.895 | L7: 3741 | M7: Fondo Cofre | N7: =insumos!$G$213 -> 0.83558719 | Q7: 6184 | R7: Fondo Congelado | S7: =insumos!$H$215 -> 0.6 | V7: 6184 | W7: Fondo Congelado | X7: =insumos!$H$215 -> 0.6 | AA7: 3741 | AB7: Fondo Cofre | AC7: =insumos!$G$213 -> 0.83558719 | AF7: 2055 | AG7: Tapa blanca enfriado | AH7: =insumos!$H$266 -> 1.15 | AK7: 3741 | AL7: Fondo cofre | AM7: =insumos!$G$213 -> 0.83558719 | AP7: 5524 | AQ7: FONDO ENFRIADO (nueva medida) 505x380x155 cm - MERCOPACK | AR7: =insumos!$H$217 -> 0.895 | AU7: 6184 | AV7: Fondo Congelado | AW7: =insumos!$H$215 -> 0.6 | AZ7: 3741 | BA7: Fondo Cofre | BB7: =insumos!$G$213 -> 0.83558719 | BE7: 3741 | BF7: Fondo Cofre | BG7: =insumos!$G$213 -> 0.83558719 | BJ7: 6184 | BK7: Fondo Congelado | BL7: =insumos!$H$215 -> 0.6 | BO7: 3741 | BP7: Fondo Cofre | BQ7: =insumos!$G$213 -> 0.83558719 | BT7: 3741 | BU7: Fondo Cofre | BV7: =insumos!$G$213 -> 0.83558719 | BY7: 6184 | BZ7: Fondo Congelado | CA7: =insumos!$H$215 -> 0.6 | CD7: 3741 | CE7: Fondo Cofre | CF7: =insumos!$G$213 -> 0.83558719 | CI7: 3741 | CJ7: Fondo Cofre | CK7: =insumos!$G$213 -> 0.83558719 | CN7: 3741 | CO7: Fondo Cofre | CP7: =insumos!$G$213 -> 0.83558719 | CS7: 3741 | CT7: Fondo Cofre | CU7: =insumos!$G$213 -> 0.83558719 | CX7: 3741 | CY7: Fondo Cofre | CZ7: =insumos!$G$213 -> 0.83558719 | DC7: 3741 | DD7: Fondo Cofre | DE7: =insumos!$G$213 -> 0.83558719 | DH7: 3741 | DI7: Fondo Cofre | DJ7: =insumos!$G$213 -> 0.83558719 | DM7: 3741 | DN7: Fondo Cofre | DO7: =insumos!$G$213 -> 0.83558719 | DR7: 5524 | DS7: FONDO ENFRIADO (nueva medida) 505x380x155 cm - MERCOPACK | DT7: =insumos!$H$217 -> 0.895 | DW7: 5524 | DX7: FONDO ENFRIADO (nueva medida) 505x380x155 cm - MERCOPACK | DY7: =insumos!$H$217 -> 0.895 | EE7: 6261 | EF7: 1 caja octogonal | EG7: =insumos!H99 -> 12.25 | EI7: 4542 | EJ7: Bolsa 95 x 60 | EK7: 1 | EL7: =insumos!I35 -> 0.022058824
B8: 3759 | C8: TAPA VILA COFRE 156 (135)(gris) - Mpack | D8: =+insumos!$G$284 -> 1.1352417 | G8: 5523 | H8: TAPA VILA gris - 50x38x15.5 cm (nueva medida) - Mercopack | I8: =+insumos!$H$285 -> 1.1829611 | L8: 3806 | M8: TAPA BLANCA COFRE 135 - doble micro - MERCOPACK | N8: =+insumos!$H$267 -> 1.2 | Q8: 2037 | R8: Tapa blanca congelado | S8: =+insumos!$H$268 -> 0.65 | V8: 2037 | W8: Tapa blanca congelado | X8: =+insumos!$H$268 -> 0.65 | AA8: 3806 | AB8: TAPA BLANCA COFRE 135 - doble micro - MERCOPACK | AC8: =+insumos!$H$267 -> 1.2 | AF8: 5524 | AG8: Fondo enfriado (nueva medida) 505x380x155 cm – MERCOPACK | AH8: =insumos!$H$217 -> 0.895 | AK8: 3759 | AL8: TAPA VILA COFRE 156 (135)(gris) - Mpack | AM8: =+insumos!$G$284 -> 1.1352417 | AP8: 5523 | AQ8: TAPA VILA gris - 50x38x15.5 cm (nueva medida) - Mercopack | AR8: =+insumos!$H$285 -> 1.1829611 | AU8: 2055 | AV8: TAPA BLANCA 136 (cartulina)- Mpack | AW8: =+insumos!$H$266 -> 1.15 | AZ8: 5653 | BA8: TAPA UMi CONGELADO (136) - IMPRIMEX | BB8: =+insumos!$G$283 -> 1.1 | BE8: 6287 | BF8: TAPA 135 COFRE EL RANCHO - IMPRIMEX | BG8: =+insumos!$H$263 -> 1.6 | BJ8: 2037 | BK8: Tapa blanca congelado | BL8: =+insumos!$H$268 -> 0.65 | BO8: 5653 | BP8: TAPA UMi CONGELADO (136) - IMPRIMEX | BQ8: =+insumos!$G$283 -> 1.1 | BT8: 6265 | BU8: TAPA TAURUS BIFE ONTILCOR - MERCOPACK | BV8: =+insumos!$H$279 -> 1.25 | BY8: 5523 | BZ8: TAPA VILA gris - 50x38x15.5 cm (nueva medida) - Mercopack | CA8: =+insumos!$H$285 -> 1.1829611 | CD8: 5653 | CE8: TAPA UMi CONGELADO (136) - IMPRIMEX | CF8: =+insumos!$G$283 -> 1.1 | CI8: 5251 | CJ8: TAPA INK COFRE - IMPRIMEX | CK8: =+insumos!$H$274 -> 1.6 | CN8: 3759 | CO8: TAPA VILA COFRE 156 (135)(gris) - Mpack | CP8: =+insumos!$G$284 -> 1.1352417 | CS8: 3759 | CT8: TAPA VILA COFRE 156 (135)(gris) - Mpack | CU8: =+insumos!$G$284 -> 1.1352417 | CX8: 3806 | CY8: TAPA BLANCA COFRE 135 - doble micro - MERCOPACK | CZ8: =+insumos!$H$267 -> 1.2 | DC8: 3759 | DD8: TAPA VILA gris - 50x38x15.5 cm (nueva medida) - Mercopack | DE8: =+insumos!$G$284 -> 1.1352417 | DH8: 5251 | DI8: TAPA INK COFRE - IMPRIMEX | DJ8: =+insumos!$H$274 -> 1.6 | DM8: 6265 | DN8: TAPA TAURUS BIFE ONTILCOR - MERCOPACK | DO8: =+insumos!$H$279 -> 1.25 | DR8: 2055 | DS8: TAPA BLANCA 136 (cartulina)- Mpack | DT8: =+insumos!$H$266 -> 1.15 | DW8: 2055 | DX8: TAPA BLANCA 136 (cartulina)- Mpack | DY8: =+insumos!$H$266 -> 1.15 | EE8: 6286 | EF8: 1 sobre tapa | EG8: =+insumos!H256 -> 1.24 | EI8: 3817 | EJ8: Cinta adhesiva ( metros) | EK8: 1.8 | EL8: =insumos!I103*1.8 -> 0.02088
B9: 4653 | C9: SEPARADORES 530X290 – MERCOPACK | D9: =insumos!$H$254*3 -> 0.55921788 | E9: 3 unid. X caja | G9: 4542 | H9: Bolsa 95X60 | I9: =insumos!$I$35 -> 0.022058824 | L9: 4541 | M9: Bolsa 85x60 | N9: =insumos!$H$43 -> 0.022058824 | Q9: 4542 | R9: Bolsa 95X60 | S9: =insumos!$I$35 -> 0.022058824 | V9: 4542 | W9: Bolsa 95X60 | X9: =insumos!$I$35 -> 0.022058824 | AA9: 4541 | AB9: Bolsa 85x60 | AC9: =insumos!$H$43 -> 0.022058824 | AF9: 4542 | AG9: Bolsa 95X60 | AH9: =insumos!$I$35 -> 0.022058824 | AK9: 4541 | AL9: Bolsa 85X60 | AM9: =insumos!$H$43 -> 0.022058824 | AP9: 4986 | AQ9: SEPARADORES 570x230 mm - MERCOPACK | AR9: =insumos!$H$255*3 -> 0.56999964 | AS9: 3 unid. X caja | AU9: 4986 | AV9: SEPARADORES 570x230 mm - MERCOPACK | AW9: =insumos!$H$255*4 -> 0.75999952 | AX9: 4 unid. X caja | AZ9: 4653 | BA9: SEPARADORES 530X290 – MERCOPACK | BB9: =insumos!$H$254*2 -> 0.37281192 | BC9: 2 unid. X caja | BE9: 4653 | BF9: SEPARADORES 530X290 – MERCOPACK | BG9: =insumos!$H$254*2 -> 0.37281192 | BH9: 2 unid. X caja | BJ9: 2105 | BK9: BOLSA 80 (60) x 75 /ø80 AZUL, impresa EN ROLLO - STRONG | BL9: =insumos!$I$33 -> 0.049999554 | BO9: 4653 | BP9: SEPARADORES 530X290 – MERCOPACK | BQ9: =insumos!$H$254 -> 0.18640596 | BY9: 4542 | BZ9: Bolsa 95X60 | CA9: =insumos!$I$35 -> 0.022058824 | CD9: 4653 | CE9: SEPARADORES 530X290 – MERCOPACK | CF9: =insumos!$H$254 -> 0.18640596 | CI9: 4653 | CJ9: SEPARADORES 530X290 – MERCOPACK | CK9: =insumos!$H$254*3 -> 0.55921788 | CL9: 3 unid. X caja | CN9: 4653 | CO9: SEPARADORES 530X290 – MERCOPACK | CP9: =insumos!$H$254 -> 0.18640596 | CS9: 4653 | CT9: SEPARADORES 530X290 – MERCOPACK | CU9: =insumos!$H$254 -> 0.18640596 | CX9: 4541 | CY9: Bolsa 85x60 | CZ9: =insumos!$H$43 -> 0.022058824 | DC9: 4653 | DD9: SEPARADORES 530X290 – MERCOPACK | DE9: =insumos!$H$254*3 -> 0.55921788 | DF9: 3 unid. X caja | DH9: 4541 | DI9: Bolsa 85x60 | DJ9: =insumos!$H$43 -> 0.022058824 | DM9: 4653 | DN9: SEPARADORES 530X290 – MERCOPACK | DO9: =insumos!$H$254*3 -> 0.55921788 | DP9: 3 unid. X caja | DR9: 4542 | DS9: Bolsa 95X60 | DT9: =insumos!$I$35 -> 0.022058824 | DW9: 4542 | DX9: Bolsa 95X60 | DY9: =insumos!$I$35 -> 0.022058824 | EE9: 6262 | EF9: 1 tapa | EG9: 2.18 | EI9: 2173 | EJ9: Fajas | EK9: 2 | EL9: =+insumos!H149*2 -> 0.034950266
B10: 4541 | C10: Bolsa 85x60 | D10: =insumos!$H$43 -> 0.022058824 | G10: 3817 | H10: Cinta adhesiva ( metros) | I10: =insumos!$I$103*1.8 -> 0.02088 | J10: 1,8 metros | L10: 3817 | M10: Cinta adhesiva ( metros) | N10: =insumos!$I$103*1.8 -> 0.02088 | O10: 1,8 metros | Q10: 3817 | R10: Cinta adhesiva ( metros) | S10: =insumos!$I$103*1.8 -> 0.02088 | T10: 1.8 metros | V10: 3817 | W10: Cinta adhesiva ( metros) | X10: =insumos!$I$103*1.8 -> 0.02088 | Y10: 1.8 metros | AA10: 3817 | AB10: Cinta adhesiva ( metros) | AC10: =insumos!$I$103*1.8 -> 0.02088 | AD10: 1.8 metros | AF10: 3817 | AG10: Cinta adhesiva ( metros) | AH10: =insumos!I103*1.8 -> 0.02088 | AI10: 1,8 metros | AK10: 3817 | AL10: Cinta adhesiva ( metros) | AM10: =insumos!$I$103*1.8 -> 0.02088 | AN10: 1.8 metros | AP10: 4542 | AQ10: Bolsa 95X60 | AR10: =insumos!$I$35 -> 0.022058824 | AU10: 4542 | AV10: Bolsa 95X60 | AW10: =insumos!$I$35 -> 0.022058824 | AZ10: 5315 | BA10: BOLSA COFRE 85(60)X46/ø40, impr. en rollo, ROSADA - STRONG | BB10: =insumos!$H$45 -> 0.028 | BE10: 6280 | BF10: BOLSA NARANJA 85(60)X46/40 - STRONG | BG10: =insumos!$H$50 -> 0.027941176 | BJ10: 3817 | BK10: Cinta adhesiva ( metros) | BL10: =insumos!$I$103*1.8 -> 0.02088 | BM10: 1.8 metros | BO10: 5315 | BP10: BOLSA COFRE 85(60)X46/ø40, impr. en rollo, ROSADA - STRONG | BQ10: =insumos!$H$45 -> 0.028 | BT10: 5353 | BU10: BOLSA COFRE 85(60)X46/ø40, impr. en rollo, AMARILLA - STRONG | BV10: =insumos!$H$44 -> 0.028 | BY10: 4986 | BZ10: SEPARADORES 570x230 mm - MERCOPACK | CA10: =insumos!$H$255*4 -> 0.75999952 | CB10: 4 unid. X caja | CD10: 5315 | CE10: BOLSA COFRE 85(60)X46/ø40, impr. en rollo, ROSADA - STRONG | CF10: =insumos!$H$45 -> 0.028 | CI10: 4541 | CJ10: Bolsa 85X60 | CK10: =insumos!$H$43 -> 0.022058824 | CN10: 4541 | CO10: Bolsa 85X60 | CP10: =insumos!$H$43 -> 0.022058824 | CS10: 4541 | CT10: Bolsa 85X60 | CU10: =insumos!$H$43 -> 0.022058824 | CX10: 3817 | CY10: Cinta adhesiva ( metros) | CZ10: =insumos!$I$103*1.8 -> 0.02088 | DA10: 1,8 metros | DC10: 4541 | DD10: Bolsa 85X60 | DE10: =insumos!$H$43 -> 0.022058824 | DH10: 3817 | DI10: Cinta adhesiva ( metros) | DJ10: =insumos!$I$103*1.8 -> 0.02088 | DK10: 1.8 metros | DM10: 5353 | DN10: BOLSA COFRE 85(60)X46/ø40, impr. en rollo, AMARILLA - STRONG | DO10: =insumos!$H$44 -> 0.028 | DR10: 3817 | DS10: Cinta adhesiva ( metros) | DT10: =insumos!$I$103*1.8 -> 0.02088 | DU10: 1,8 metros | DW10: 3817 | DX10: Cinta adhesiva ( metros) | DY10: =insumos!$I$103*1.8 -> 0.02088 | DZ10: 1,8 metros | EE10: 5383 | EF10: 1 bolsa de huesos china | EG10: 0.0168 | EI10: 2923 | EJ10: Film Strechs (0,160 kls.p/pallets) | EL10: =+insumos!I202*0.16 -> 0.09
B11: 3817 | C11: Cinta adhesiva ( metros) | D11: =insumos!$I$103*1.8 -> 0.02088 | E11: 1,8 metros | G11: 2173 | H11: Fajas | I11: =+insumos!$H$149*2 -> 0.034950266 | J11: 2 unidades | L11: 2173 | M11: Fajas | N11: =+insumos!$H$149*2 -> 0.034950266 | O11: 2 unidades | Q11: 2173 | R11: Fajas | S11: =+insumos!$H$149*2 -> 0.034950266 | T11: 2 unidades | V11: 2173 | W11: Fajas | X11: =+insumos!$H$149*2 -> 0.034950266 | Y11: 2 unidades | AA11: 2173 | AB11: Fajas | AC11: =+insumos!$H$149*2 -> 0.034950266 | AD11: 2 unidades | AF11: 2173 | AG11: Fajas | AH11: =+insumos!H149*2 -> 0.034950266 | AI11: 2 unidades | AK11: 2173 | AL11: Fajas | AM11: =+insumos!$H$149*2 -> 0.034950266 | AN11: 2 unidades | AP11: 3817 | AQ11: Cinta adhesiva ( metros) | AR11: =insumos!$I$103*1.8 -> 0.02088 | AS11: 1,8 metros | AU11: 3817 | AV11: Cinta adhesiva ( metros) | AW11: =insumos!$I$103*1.8 -> 0.02088 | AX11: 1,8 metros | AZ11: 3817 | BA11: Cinta adhesiva ( metros) | BB11: =insumos!$I$103*1.8 -> 0.02088 | BC11: 1,8 metros | BE11: 3817 | BF11: Cinta adhesiva ( metros) | BG11: =insumos!$I$103*1.8 -> 0.02088 | BH11: 1,8 metros | BJ11: 2173 | BK11: Fajas | BL11: =+insumos!$H$149*2 -> 0.034950266 | BM11: 2 unidades | BO11: 3817 | BP11: Cinta adhesiva ( metros) | BQ11: =insumos!$I$103*1.8 -> 0.02088 | BR11: 1,8 metros | BT11: 3817 | BU11: Cinta adhesiva ( metros) | BV11: =insumos!$I$103*1.8 -> 0.02088 | BW11: 1,8 metros | BY11: 3817 | BZ11: Cinta adhesiva ( metros) | CA11: =insumos!$I$103*1.8 -> 0.02088 | CB11: 1.8 metros | CD11: 3817 | CE11: Cinta adhesiva ( metros) | CF11: =insumos!$I$103*1.8 -> 0.02088 | CG11: 1.8 metros | CI11: 3817 | CJ11: Cinta adhesiva ( metros) | CK11: =insumos!$I$103*1.8 -> 0.02088 | CL11: 1.8 metros | CN11: 3817 | CO11: Cinta adhesiva ( metros) | CP11: =insumos!$I$103*1.8 -> 0.02088 | CQ11: 1.8 metros | CS11: 3817 | CT11: Cinta adhesiva ( metros) | CU11: =insumos!$I$103*1.8 -> 0.02088 | CV11: 1.8 metros | CX11: 2173 | CY11: Fajas | CZ11: =+insumos!$H$149*2 -> 0.034950266 | DA11: 2 unidades | DC11: 3817 | DD11: Cinta adhesiva ( metros) | DE11: =insumos!$I$103*1.8 -> 0.02088 | DF11: 1.8 metros | DH11: 2173 | DI11: Fajas | DJ11: =+insumos!$H$149*2 -> 0.034950266 | DK11: 2 unidades | DM11: 3817 | DN11: Cinta adhesiva ( metros) | DO11: =insumos!$I$103*1.8 -> 0.02088 | DP11: 1,8 metros | DR11: 2173 | DS11: Fajas | DT11: =+insumos!$H$149*2 -> 0.034950266 | DU11: 2 unidades | DW11: 2173 | DX11: Fajas | DY11: =+insumos!$H$149*2 -> 0.034950266 | DZ11: 2 unidades | EE11: 2173 | EF11: Faja Numerada | EG11: 0.0167 | EI11: 2445 | EJ11: Pallets ( 30 cajas de 20 kls) | EK11: 1 | EL11: =(440/40.48)/(30*20) -> 0.018115942
B12: 2173 | C12: Fajas | D12: =+insumos!$H$149*2 -> 0.034950266 | E12: 2 unidades | G12: 3636 | H12: Etiqueta Caja | I12: =+insumos!$H$121 -> 0.0445 | L12: 3636 | M12: Etiqueta Caja | N12: =+insumos!$H$121 -> 0.0445 | Q12: 3636 | R12: Etiqueta Caja | S12: =+insumos!$H$121 -> 0.0445 | V12: 3636 | W12: Etiqueta Caja | X12: =+insumos!$H$121 -> 0.0445 | AA12: 3636 | AB12: Etiqueta Caja | AC12: =+insumos!$H$121 -> 0.0445 | AF12: 3636 | AG12: Etiqueta Caja | AH12: =+insumos!H121 -> 0.0445 | AK12: 3636 | AL12: Etiqueta Caja | AM12: =+insumos!$H$121 -> 0.0445 | AP12: 2173 | AQ12: Fajas | AR12: =+insumos!$H$149*2 -> 0.034950266 | AS12: 2 unidades | AU12: 2173 | AV12: Fajas | AW12: =+insumos!$H$149*2 -> 0.034950266 | AX12: 2 unidades | AZ12: 2173 | BA12: Fajas | BB12: =+insumos!$H$149*2 -> 0.034950266 | BC12: 2 unidades | BE12: 2173 | BF12: Fajas | BG12: =+insumos!$H$149*2 -> 0.034950266 | BH12: 2 unidades | BJ12: 3636 | BK12: Etiqueta Caja | BL12: =+insumos!$H$121 -> 0.0445 | BO12: 2173 | BP12: Fajas | BQ12: =+insumos!$H$149*2 -> 0.034950266 | BR12: 2 unidades | BT12: 2173 | BU12: Fajas | BV12: =+insumos!$H$149*2 -> 0.034950266 | BW12: 2 unidades | BY12: 2173 | BZ12: Fajas | CA12: =+insumos!$H$149*2 -> 0.034950266 | CB12: 2 unidades | CD12: 2173 | CE12: Fajas | CF12: =+insumos!$H$149*2 -> 0.034950266 | CG12: 2 unidades | CI12: 2173 | CJ12: Fajas | CK12: =+insumos!$H$149*2 -> 0.034950266 | CL12: 2 unidades | CN12: 2173 | CO12: Fajas | CP12: =+insumos!$H$149*2 -> 0.034950266 | CQ12: 2 unidades | CS12: 2173 | CT12: Fajas | CU12: =+insumos!$H$149*2 -> 0.034950266 | CV12: 2 unidades | CX12: 3636 | CY12: Etiqueta Caja | CZ12: =+insumos!$H$121 -> 0.0445 | DC12: 2173 | DD12: Fajas | DE12: =+insumos!$H$149*2 -> 0.034950266 | DF12: 2 unidades | DH12: 3636 | DI12: Etiqueta Caja | DJ12: =+insumos!$H$121 -> 0.0445 | DM12: 2173 | DN12: Fajas | DO12: =+insumos!$H$149*2 -> 0.034950266 | DP12: 2 unidades | DR12: 3636 | DS12: Etiqueta Caja | DT12: =+insumos!$H$121 -> 0.0445 | DW12: 3636 | DX12: Etiqueta Caja | DY12: =+insumos!$H$121 -> 0.0445 | EE12: 6268 | EF12: 35 mts. Fleje | EG12: =0.0245*35 -> 0.8575 | EI12: 2119 | EJ12: Hoja separador | EK12: 2 | EL12: =insumos!I224*2 -> 0
B13: 3636 | C13: Etiqueta Caja | D13: =+insumos!$H$121 -> 0.0445 | H13: Paquete | M13: Paquete | R13: Paquete | W13: Paquete | AB13: Paquete | AG13: Paquete | AL13: Paquete | AP13: 3636 | AQ13: Etiqueta Caja | AR13: =+insumos!$H$121 -> 0.0445 | AU13: 3636 | AV13: Etiqueta Caja | AW13: =+insumos!$H$121 -> 0.0445 | AZ13: 3636 | BA13: Etiqueta Caja | BB13: =+insumos!$H$121 -> 0.0445 | BE13: 3636 | BF13: Etiqueta Caja | BG13: =+insumos!$H$121 -> 0.0445 | BK13: Paquete | BO13: 3636 | BP13: Etiqueta Caja | BQ13: =+insumos!$H$121 -> 0.0445 | BT13: 3636 | BU13: Etiqueta Caja | BV13: =+insumos!$H$121 -> 0.0445 | BY13: 3636 | BZ13: Etiqueta Caja | CA13: =+insumos!$H$121 -> 0.0445 | CD13: 3636 | CE13: Etiqueta Caja | CF13: =+insumos!$H$121 -> 0.0445 | CI13: 3636 | CJ13: Etiqueta Caja | CK13: =+insumos!$H$121 -> 0.0445 | CN13: 3636 | CO13: Etiqueta Caja | CP13: =+insumos!$H$121 -> 0.0445 | CS13: 3636 | CT13: Etiqueta Caja | CU13: =+insumos!$H$121 -> 0.0445 | CY13: Paquete | DC13: 3636 | DD13: Etiqueta Caja | DE13: =+insumos!$H$121 -> 0.0445 | DI13: Paquete | DM13: 3636 | DN13: Etiqueta Caja | DO13: =+insumos!$H$121 -> 0.0445 | DS13: Paquete | DX13: Paquete | EE13: 3108 | EF13: 160 grms film | EG13: 0.24 | EI13: 2157 | EJ13: Rotulo bopp term 50 x 40 | EK13: 1 | EL13: =insumos!H249 -> 0.0085
C14: Paquete | G14: 6259 | H14: BOBINA 280x650 MM IMP VILA - MERCOPACK | I14: =insumos!$H$23*4 -> 1.1519995 | J14: 4 unid. X caja | L14: 5214 | M14: BOLSA VACIO 18X67 SOLDA V SB15- MERCOPACK | N14: =insumos!$H$65*3 -> 0.41399939 | O14: 3 unid. X caja | V14: 4745 | W14: Bolsa 31x40 | X14: =insumos!H93*8 -> 0.912 | Y14: 8 unid. X caja | AA14: 4741 | AB14: Bolsa 20x50 | AC14: =insumos!$H$90*10 -> 3.08 | AD14: 10 unid. X caja | AF14: 5138 | AG14: Etiqueta 102x78 Bopp Term | AH14: =insumos!H113*4 -> 0.10803782 | AI14: 4 unid. X caja | AK14: 6293 | AL14: Bolsa 20x50 Vila | AM14: =insumos!$H$55*10 -> 1.61 | AN14: 10 unid. X caja | AQ14: Paquete | AV14: Paquete | BA14: Paquete | BF14: Paquete | BP14: Paquete | BU14: Paquete | BZ14: Paquete | CE14: Paquete | CJ14: Paquete | CO14: Paquete | CT14: Paquete | CX14: 4741 | CY14: Bolsa 20x50 | CZ14: =insumos!$H$90*10 -> 3.08 | DA14: 10 unid. X caja | DD14: Paquete | DH14: 5138 | DI14: ET. BOPP TERM. 102X78 - RR | DJ14: =insumos!$H$113*12 -> 0.32411345 | DK14: 12 unid. X caja | DN14: Paquete | DR14: 5214 | DS14: BOLSA VACIO 18X67 SOLDA V SB15- MERCOPACK | DT14: =insumos!$H$65*4 -> 0.55199919 | DU14: 4 unid. X caja | DW14: 4741 | DX14: BOLSA VACIO IMP. 20X50 - MERCOPACK | DY14: =insumos!$H$90*12 -> 3.696 | DZ14: 12 unid. X caja | EE14: 2122 | EF14: bolsa celeste | EG14: =0.0583333333333333*45 -> 2.625 | EI14: 3636 | EJ14: Etqiueta bopp termico 100 x 154 lisa RR | EK14: 1 | EL14: =insumos!H121 -> 0.0445
B15: 6269 | C15: Etiqueta delantera | D15: =insumos!H150*12 -> 1.1319 | E15: 12 unid. X caja | G15: 5138 | H15: ET. BOPP TERM. 102X78 - RR | I15: =insumos!$H$113*4 -> 0.10803782 | J15: 4 unid. X caja | L15: 5138 | M15: ET. BOPP TERM. 102X78 - RR | N15: =insumos!$H$113*3 -> 0.081028362 | O15: 3 unid. X caja | R15: Total | S15: =SUM(S7:S14) -> 1.3723891 | W15: Total | X15: =SUM(X7:X14) -> 2.2843891 | AA15: 3887 | AB15: ET. BOPP TERMICO 100x050 LISA - RR | AC15: =insumos!$H$120*10 -> 0.199 | AD15: 10 unid. X caja | AF15: 4745 | AG15: Bolsa 31x40 | AH15: =insumos!H93*4 -> 0.456 | AI15: 4 unid. X caja | AL15: Total | AM15: =SUM(AM7:AM14) -> 3.7032179 | AP15: 4102 | AQ15: Etiqueta Trasera 100x100 | AR15: =insumos!$H$115*28 -> 0.924 | AS15: 28 unid. X caja | AU15: 6290 | AV15: Etiqueta delantera | AW15: =insumos!H190*35 -> 1.82 | AX15: 35 unid. X caja | AZ15: 4102 | BA15: Etiqueta Trasera 100x100 | BB15: =insumos!$H$115*9 -> 0.297 | BC15: 9 unid. X caja | BE15: 5138 | BF15: ET. BOPP TERM. 102X78 - RR | BG15: =insumos!$H$113*12 -> 0.32411345 | BH15: 12 unid. X caja | BO15: 4102 | BP15: Etiqueta Trasera 100x100 | BQ15: =insumos!$H$115*4 -> 0.132 | BR15: 4 unid. X caja | BT15: 5138 | BU15: ET. BOPP TERM. 102X78 - RR | BV15: =insumos!$H$113*12 -> 0.32411345 | BW15: 12 unid. X caja | CD15: 5138 | CE15: ET. BOPP TERM. 102X78 - RR | CF15: =insumos!$H$113*16 -> 0.43215126 | CG15: 16 unid. X caja | CI15: 5214 | CJ15: BOLSA VACIO 18X67 SOLDA V SB15- MERCOPACK | CK15: =insumos!$H$65*8 -> 1.1039984 | CN15: 6216 | CO15: ETIQUETAS BOPP MET.DOBLE CAPA 084X081 - ASADO 1 COSTILLA CONGELADO | CP15: =insumos!$H$181*16 -> 1.568 | CQ15: 16 unid. X caja | CS15: 6216 | CT15: ETIQUETAS BOPP MET.DOBLE CAPA 084X081 - ASADO 1 COSTILLA CONGELADO | CU15: =insumos!$H$181*16 -> 1.568 | CV15: 16 unid. X caja | DC15: 6206 | DD15: Etiqueta delantera | DE15: =insumos!$H$186*12 -> 1.1007317 | DF15: 12 unid. X caja | DH15: 5250 | DI15: Et. INK OPP - 7.2X14 - IMPRIMEX | DJ15: =insumos!H131*12 -> 0.9 | DK15: 12 unid. X caja | DW15: 5138 | DX15: ET. BOPP TERM. 102X78 - RR | DY15: =insumos!$H$113*12 -> 0.32411345 | DZ15: 12 unid. X caja | EF15: Total | EG15: =SUM(EG6:EG14) -> 32.084103 | EJ15: Total por Caja | EL15: =SUM(EL5:EL14) -> 1.489005
B16: 5202 | C16: Etiqueta Trasera | D16: =insumos!$H$114*16 -> 0.42151619 | E16: 12 unid. X caja | H16: Total | I16: =SUM(I7:I15) -> 3.4603875 | M16: Total | N16: =SUM(N7:N15) -> 2.653004 | R16: peso prom. Caja | S16: =1558.78/83 -> 18.780482 | W16: peso prom. Caja | X16: 20.39 | AB16: Total | AC16: =SUM(AC7:AC15) -> 5.4369763 | AL16: peso prom. Caja | AM16: 12.83 | AP16: 6229 | AQ16: TAPA BARRERA NEGRA 250 C (FILM PARA TERMOFORMADORA) - MULTIPACK DIAMALER | AR16: =insumos!$I$265*28 -> 0.60259547 | AS16: 28 unid. X caja | AZ16: 6229 | BA16: TAPA BARRERA NEGRA 250 C (FILM PARA TERMOFORMADORA) - MULTIPACK DIAMALER | BB16: =insumos!$I$265*9 -> 0.1936914 | BC16: 9 unid. X caja | BE16: 6229 | BF16: TAPA BARRERA NEGRA 250 C (FILM PARA TERMOFORMADORA) - MULTIPACK DIAMALER | BG16: =insumos!$I$265*12 -> 0.2582552 | BH16: 12 unid. X caja | BK16: Total | BL16: =SUM(BL7:BL15) -> 1.4003298 | BO16: 5403 | BP16: BOLSA VACIO 31X45 UMI - MERCOPACK | BQ16: =insumos!$H$80*4 -> 0.884 | BR16: 4 unid. X caja | BT16: 4972 | BU16: BOLSA VACIO 24x40 impr. TAURUS GOLD - MERCOPACK | BV16: =insumos!$H$71*12 -> 1.452 | BW16: 12 unid. X caja | BY16: 5202 | BZ16: Etiqueta Trasera | CA16: =insumos!$H$114*15 -> 0.39517143 | CB16: 15 unid. X caja | CD16: 5462 | CE16: BOLSA VACIO 30x65/ø45 UMi - BEMIS | CF16: =insumos!$H$76*16 -> 3.3024111 | CG16: 16 unid. X caja | CI16: 6216 | CJ16: ETIQUETAS BOPP MET.DOBLE CAPA 084X081 - ASADO 1 COSTILLA CONGELADO | CK16: =insumos!$H$181*8 -> 0.784 | CN16: 5202 | CO16: Etiqueta Trasera | CP16: =insumos!$H$114*16 -> 0.42151619 | CQ16: 16 unid. X caja | CS16: 5138 | CT16: ET. BOPP TERM. 102X78 - RR | CU16: =insumos!$H$113*16 -> 0.43215126 | CV16: 16 unid. X caja | CY16: Total | CZ16: =SUM(CZ7:CZ15) -> 5.2379763 | DC16: 5202 | DD16: Etiqueta Trasera | DE16: =insumos!$H$114*12 -> 0.31613714 | DF16: 12 unid. X caja | DH16: 6297 | DI16: BOLSA PARA VACIO 18X45 | DJ16: =insumos!$H$53*12 -> 1.872 | DK16: 12 unid. X caja | DM16: 6229 | DN16: TAPA BARRERA NEGRA 250 C (FILM PARA TERMOFORMADORA) - MULTIPACK DIAMALER | DO16: =insumos!$I$265*12 -> 0.2582552 | DP16: 12 unid. X caja | DS16: Total | DT16: =SUM(DT7:DT15) -> 2.7193883 | DX16: Total | DY16: =SUM(DY7:DY15) -> 6.1875025 | EF16: 45 moldes x 12,2 kls | EG16: =45*12.2 -> 549 | EJ16: Costo x kls | EL16: =EL15/EL17 -> 0.074824373
B17: 6229 | C17: TAPA BARRERA NEGRA 250 C (FILM PARA TERMOFORMADORA) - MULTIPACK DIAMALER | D17: =insumos!$I$265*12 -> 0.2582552 | E17: 12 unid. X caja | H17: peso prom. Caja | I17: 19.5 | M17: peso prom. Caja | N17: =29253.79/2456 -> 11.911152 | R17: Costo x kls | S17: =+S15/S16 -> 0.073075286 | W17: Costo x kls | X17: =+X15/X16 -> 0.11203478 | AB17: peso prom. Caja | AC17: 12.38 | AL17: Costo x kls | AM17: =+AM15/AM16 -> 0.28863741 | AP17: 6254 | AQ17: FONDO BARRERA TERMOFORMADORA TR NI 180 - MULTIPACK DIAMALER | AR17: =+insumos!$I$208*28 -> 1.2448086 | AS17: 28 unid. X caja | AU17: 6229 | AV17: TAPA BARRERA NEGRA 250 C (FILM PARA TERMOFORMADORA) - MULTIPACK DIAMALER | AW17: =insumos!$I$265*35 -> 0.75324433 | AZ17: 6254 | BA17: FONDO BARRERA TERMOFORMADORA TR NI 180 - MULTIPACK DIAMALER | BB17: =+insumos!$I$208*9 -> 0.40011705 | BC17: 9 unid. X caja | BE17: 6254 | BF17: FONDO BARRERA TERMOFORMADORA TR NI 180 - MULTIPACK DIAMALER | BG17: =+insumos!$I$208*12 -> 0.5334894 | BH17: 12 unid. X caja | BK17: peso prom. Caja | BL17: =146362.59/5379 -> 27.21 | BY17: 4741 | BZ17: BOLSA VACIO IMP. 20X50 - MERCOPACK | CA17: =insumos!$H$90*15 -> 4.62 | CB17: 15 unid. X caja | CN17: 5214 | CO17: BOLSA VACIO 18X67 SOLDA V SB15- MERCOPACK | CP17: =insumos!$H$65*16 -> 2.2079968 | CQ17: 16 unid. X caja | CS17: 5214 | CT17: BOLSA VACIO 18X67 SOLDA V SB15- MERCOPACK | CU17: =insumos!$H$65*16 -> 2.2079968 | CV17: 16 unid. X caja | CY17: peso prom. Caja | CZ17: 12.64 | DC17: 6229 | DD17: TAPA BARRERA NEGRA 250 C (FILM PARA TERMOFORMADORA) - MULTIPACK DIAMALER | DE17: =insumos!$I$265*12 -> 0.2582552 | DF17: 12 unid. X caja | DI17: Total | DJ17: =SUM(DJ7:DJ16) -> 5.6540897 | DM17: 6254 | DN17: FONDO BARRERA TERMOFORMADORA TR NI 180 - MULTIPACK DIAMALER | DO17: =+insumos!$I$208*12 -> 0.5334894 | DP17: 12 unid. X caja | DS17: peso prom. Caja | DT17: 18.09 | DX17: peso prom. Caja | DY17: =125974.25/7458 -> 16.891157 | EF17: Costo por tons. | EG17: =(+EG15/EG16)*1000 -> 58.440989 | EJ17: Peso Prom. Caja | EK17: ASADO 5 C | EL17: 19.9
B18: 6254 | C18: FONDO BARRERA TERMOFORMADORA TR NI 180 - MULTIPACK DIAMALER | D18: =+insumos!$I$208*12 -> 0.5334894 | E18: 12 unid. X caja | H18: Costo x kls | I18: =+I16/I17 -> 0.17745577 | M18: Costo x kls | N18: =+N16/N17 -> 0.22273278 | R18: porcentaje cobertura ( fallas, roturas) + 3 % | S18: =S17*1.03 -> 0.075267545 | W18: porcentaje cobertura ( fallas, roturas) + 3 % | X18: =X17*1.03 -> 0.11539582 | AB18: Costo x kls | AC18: =+AC16/AC17 -> 0.43917417 | AL18: porcentaje cobertura ( fallas, roturas) + 3 % | AM18: =AM17*1.03 -> 0.29729653 | AP18: 5868 | AQ18: PADS BLANCOS 4.5" x 7" - TITE DRI | AR18: =insumos!$I$243*28 -> 0.53088 | AS18: 28 unid. X caja | AU18: 6254 | AV18: FONDO BARRERA TERMOFORMADORA TR NI 180 - MULTIPACK DIAMALER | AW18: =+insumos!$I$208*35 -> 1.5560107 | AZ18: 6138 | BA18: FAJAS UMI - 8x19.5cm - IMPRIMEX | BB18: =insumos!$H$197*9 -> 1.3087059 | BC18: 9 unid. X caja | BE18: 6288 | BF18: ETIQUETAS BOPP MET. ADC 6000 60X110 LAMINADO MATE - EL RANCHO PASSION - RR | BG18: =insumos!$H$176*12 -> 0.648 | BH18: 12 unid. X caja | BK18: Costo x kls | BL18: =+BL16/BL17 -> 0.051463793 | CE18: Total | CF18: =SUM(CF7:CF17) -> 5.9848858 | CO18: Total | CP18: =SUM(CP7:CP17) -> 6.4771368 | CT18: Total | CU18: =SUM(CU7:CU17) -> 6.4877719 | CY18: Costo x kls | CZ18: =+CZ16/CZ17 -> 0.41439686 | DC18: 6254 | DD18: FONDO BARRERA TERMOFORMADORA TR NI 180 - MULTIPACK DIAMALER | DE18: =+insumos!$I$208*12 -> 0.5334894 | DF18: 12 unid. X caja | DI18: peso prom. Caja | DJ18: 12.14 | DM18: 5868 | DN18: PADS BLANCOS 4.5" x 7" - TITE DRI | DO18: =insumos!$I$243*12 -> 0.22752 | DP18: 12 unid. X caja | DS18: Costo x kls | DT18: =+DT16/DT17 -> 0.1503255 | DX18: Costo x kls | DY18: =+DY16/DY17 -> 0.36631608 | EF18: 3 % cobertura | EG18: =+EG17*1.03 -> 60.194218 | EK18: ASADO 8 C | EL18: 20.24
C19: Total | D19: =SUM(D7:D18) -> 4.9975966 | H19: porcentaje cobertura ( fallas, roturas) + 3 % | I19: =I18*1.03 -> 0.18277944 | M19: porcentaje cobertura ( fallas, roturas) + 3 % | N19: =N18*1.03 -> 0.22941476 | AB19: porcentaje cobertura ( fallas, roturas) + 3 % | AC19: =AC18*1.03 -> 0.4523494 | AQ19: Total | AR19: =SUM(AR7:AR18) -> 6.0726339 | BA19: Total | BB19: =SUM(BB7:BB18) -> 4.6362437 | BF19: Total | BG19: =SUM(BG7:BG18) -> 4.7005286 | BK19: porcentaje cobertura ( fallas, roturas) + 3 % | BL19: =BL18*1.03 -> 0.053007707 | BP19: Total | BQ19: =SUM(BQ7:BQ18) -> 3.2663234 | BU19: Total | BV19: =SUM(BV7:BV18) -> 3.9900309 | BZ19: Total | CA19: =SUM(CA7:CA18) -> 7.6805212 | CE19: peso prom. Caja | CF19: =1900.61/143 -> 13.290979 | CJ19: Total | CK19: =SUM(CK7:CK18) -> 5.0051925 | CO19: peso prom. Caja | CP19: =1992.58/164 -> 12.149878 | CT19: peso prom. Caja | CU19: =309.64/26 -> 11.909231 | CY19: porcentaje cobertura ( fallas, roturas) + 3 % | CZ19: =CZ18*1.03 -> 0.42682876 | DC19: 5868 | DD19: PADS BLANCOS 4.5" x 7" - TITE DRI | DE19: =+insumos!$I$243*12 -> 0.22752 | DF19: 12 unid. X caja | DI19: Costo x kls | DJ19: =+DJ17/DJ18 -> 0.4657405 | DN19: Total | DO19: =SUM(DO7:DO18) -> 3.7923999 | DS19: porcentaje cobertura ( fallas, roturas) + 3 % | DT19: =DT18*1.03 -> 0.15483526 | DX19: porcentaje cobertura ( fallas, roturas) + 3 % | DY19: =DY18*1.03 -> 0.37730557 | EF19: Cantidad Cajas x pallets | EG19: 30
C20: peso prom. Caja | D20: 12.89 | Q20: 998006 | R20: Envase Aguja | V20: 993032 | W20: Envase Vacio grueso (3x paquete) | AG20: Total | AH20: =SUM(AH7:AH15) -> 2.7314269 | AK20: 1987039 | AL20: Envase Falda c/h Vila | AQ20: peso prom. Caja | AR20: 10.5 | AV20: Total | AW20: =SUM(AW7:AW19) -> 6.7616437 | BA20: peso prom. Caja | BB20: =3178.57/286 -> 11.113881 | BF20: peso prom. Caja | BG20: =1659.9/151 -> 10.992715 | BP20: peso prom. Caja | BQ20: =1766.6/164 -> 10.771951 | BU20: peso prom. Caja | BV20: =16204.12/1282 -> 12.639719 | BZ20: peso prom. Caja | CA20: 13.25 | CE20: Costo x kls | CF20: =+CF18/CF19 -> 0.45029684 | CJ20: peso prom. Caja | CK20: =1042.85/124 -> 8.4100806 | CO20: Costo x kls | CP20: =+CP18/CP19 -> 0.53310303 | CT20: Costo x kls | CU20: =+CU18/CU19 -> 0.54476834 | DD20: Total | DE20: =SUM(DE7:DE19) -> 5.0885692 | DI20: porcentaje cobertura ( fallas, roturas) + 3 % | DJ20: =DJ19*1.03 -> 0.47971272 | DN20: peso prom. Caja | DO20: 5.1 | EF20: Costo $ por kls
C21: Costo x kls | D21: =+D19/D20 -> 0.38771114 | G21: 437024 | H21: Envase Colita de Cuadril | I21: 538 | J21: =I21/E2 -> 13.36314 | L21: 436035 | M21: Envase Matambre | N21: 240 | O21: =N21/E2 -> 5.9612519 | Q21: Código | R21: Insumos | S21: Precio U$S | V21: Código | W21: Insumos | X21: Precio U$S | AA21: 991420 | AB21: Envase Brazuelo s/h c/conical | AG21: peso prom. Caja | AH21: 12.62 | AK21: Código | AL21: Insumos | AM21: Precio U$S | AQ21: Costo x kls | AR21: =+AR19/AR20 -> 0.57834609 | AV21: peso prom. Caja | AW21: 11.3 | BA21: Costo x kls | BB21: =+BB19/BB20 -> 0.41715794 | BF21: Costo x kls | BG21: =+BG19/BG20 -> 0.42760396 | BP21: Costo x kls | BQ21: =+BQ19/BQ20 -> 0.30322486 | BU21: Costo x kls | BV21: =+BV19/BV20 -> 0.31567401 | BZ21: Costo x kls | CA21: =+CA19/CA20 -> 0.57966197 | CE21: porcentaje cobertura ( fallas, roturas) + 3 % | CF21: =CF20*1.03 -> 0.46380574 | CJ21: Costo x kls | CK21: =+CK19/CK20 -> 0.59514204 | CO21: porcentaje cobertura ( fallas, roturas) + 3 % | CP21: =CP20*1.03 -> 0.54909612 | CT21: porcentaje cobertura ( fallas, roturas) + 3 % | CU21: =CU20*1.03 -> 0.56111139 | CX21: 3193572 | CY21: Envase Entraña gruesa (GF) | DD21: peso prom. Caja | DE21: =4724.26/388 -> 12.175928 | DN21: Costo x kls | DO21: =+DO19/DO20 -> 0.74360783 | DR21: 6112731 | DS21: Envase Bife Angosto | DW21: 2366136 | DX21: Envase Picada | EF21: Unidades x caja. | EG21: 5 c = 5 o 6u
C22: porcentaje cobertura ( fallas, roturas) + 3 % | D22: =D21*1.03 -> 0.39934248 | G22: Código | H22: Insumos | I22: Precio U$S | L22: Código | M22: Insumos | N22: Precio U$S | R22: Envasado | W22: Envasado | AA22: Código | AB22: Insumos | AC22: Precio U$S | AG22: Costo x kls | AH22: =+AH20/AH21 -> 0.21643636 | AL22: Envasado | AQ22: porcentaje cobertura ( fallas, roturas) + 3 % | AR22: =AR21*1.03 -> 0.59569647 | AV22: Costo x kls | AW22: =+AW20/AW21 -> 0.59837555 | BA22: porcentaje cobertura ( fallas, roturas) + 3 % | BB22: =BB21*1.03 -> 0.42967267 | BF22: porcentaje cobertura ( fallas, roturas) + 3 % | BG22: =BG21*1.03 -> 0.44043208 | BP22: porcentaje cobertura ( fallas, roturas) + 3 % | BQ22: =BQ21*1.03 -> 0.31232161 | BU22: porcentaje cobertura ( fallas, roturas) + 3 % | BV22: =BV21*1.03 -> 0.32514424 | BZ22: porcentaje cobertura ( fallas, roturas) + 3 % | CA22: =CA21*1.03 -> 0.59705183 | CJ22: porcentaje cobertura ( fallas, roturas) + 3 % | CK22: =CK21*1.03 -> 0.6129963 | CX22: Código | CY22: Insumos | CZ22: Precio U$S | DD22: Costo x kls | DE22: =+DE20/DE21 -> 0.41792045 | DH22: 5516072 | DI22: Envase Entraña gruesa INK | DN22: porcentaje cobertura ( fallas, roturas) + 3 % | DO22: =DO21*1.03 -> 0.76591607 | DR22: Código | DS22: Insumos | DT22: Precio U$S | DW22: Código | DX22: Insumos | DY22: Precio U$S | EG22: 8c = 2 u
H23: Envasado | M23: Envasado | Q23: 6184 | R23: Fondo Congelado | S23: =insumos!$H$215 -> 0.6 | V23: 6184 | W23: Fondo Congelado | X23: =insumos!$H$215 -> 0.6 | AB23: Envasado | AG23: porcentaje cobertura ( fallas, roturas) + 3 % | AH23: =AH22*1.03 -> 0.22292945 | AK23: 6184 | AL23: Fondo Congelado | AM23: =insumos!$H$215 -> 0.6 | AV23: porcentaje cobertura ( fallas, roturas) + 3 % | AW23: =AW22*1.03 -> 0.61632681 | CD23: 4545460 | CE23: Envasado Asado c/h 4c UMI | CN23: 4858460 | CO23: Envase Asado 4/C en Tira Brasil | CS23: 6173460 | CT23: Envase Asado c/h 4c UMI | CY23: Envasado | DD23: porcentaje cobertura ( fallas, roturas) + 3 % | DE23: =DE22*1.03 -> 0.43045806 | DH23: Código | DI23: Insumos | DJ23: Precio U$S | DS23: Envasado | DX23: Envasado | EF23: porcentaje cobertura ( fallas, roturas) + 3 % | EH23: =EL16*1.03 -> 0.077069105
B24: 439011 | C24: Envase Tapa de Aguja | D24: =595 -> 595 | E24: =D24/E2 -> 14.778937 | G24: 5524 | H24: FONDO ENFRIADO (nueva medida) 505x380x155 cm - MERCOPACK | I24: =insumos!$H$217 -> 0.895 | L24: 5524 | M24: FONDO ENFRIADO (nueva medida) 505x380x155 cm - MERCOPACK | N24: =insumos!$H$217 -> 0.895 | Q24: 2037 | R24: Tapa blanca congelado | S24: =+insumos!$H$268 -> 0.65 | V24: 2037 | W24: Tapa blanca congelado | X24: =+insumos!H268 -> 0.65 | AA24: 6184 | AB24: Fondo Congelado | AC24: =insumos!$H$215 -> 0.6 | AK24: 5523 | AL24: TAPA VILA gris - 50x38x15.5 cm (nueva medida) - Mercopack | AM24: =+insumos!$H$285 -> 1.1829611 | AP24: 3673931 | AQ24: Envase Bife Angosto Porcionado | AZ24: 441033 | BA24: Envasado Bife de Vacio | BE24: 442070 | BF24: Envasado Entraña Fina EL RANCHO | BO24: 3516460 | BP24: Envasado Asado s/h 4c UMI | BT24: 4516160 | BU24: Envasado Asado c/h 3c Taurus | BY24: 4543860 | BZ24: Envasado Asado 4c tiras Vila | CD24: Código | CE24: Insumos | CF24: Precio U$S | CI24: 4546931 | CJ24: Envasado B.Angosto INK 300g | CN24: Código | CO24: Insumos | CP24: Precio U$S | CS24: Código | CT24: Insumos | CU24: Precio U$S | CX24: 3741 | CY24: Fondo cofre | CZ24: =insumos!$G$213 -> 0.83558719 | DI24: Envasado | DM24: 1993929 | DN24: Envasado Cuadril TG Porcionado | DR24: 5524 | DS24: FONDO ENFRIADO (nueva medida) 505x380x155 cm - MERCOPACK | DT24: =insumos!$H$217 -> 0.895 | DW24: 5524 | DX24: FONDO ENFRIADO (nueva medida) 505x380x155 cm - MERCOPACK | DY24: =insumos!$H$217 -> 0.895
B25: Código | C25: Insumos | D25: Precio U$S | G25: 5523 | H25: TAPA VILA gris - 50x38x15.5 cm (nueva medida) - Mercopack | I25: =+insumos!$H$285 -> 1.1829611 | L25: 2055 | M25: TAPA BLANCA 136 (cartulina)- Mpack | N25: =+insumos!$H$266 -> 1.15 | Q25: 4542 | R25: Bolsa 95X60 | S25: =insumos!$I$35 -> 0.022058824 | V25: 4542 | W25: Bolsa 95X60 | X25: =insumos!I35 -> 0.022058824 | AA25: 2037 | AB25: Tapa blanca congelado | AC25: =+insumos!$H$268 -> 0.65 | AF25: 885407 | AG25: Quijada Angus | AK25: 4542 | AL25: Bolsa 95X60 | AM25: =insumos!$I$35 -> 0.022058824 | AP25: Código | AQ25: Insumos | AR25: Precio U$S | AZ25: Código | BA25: Insumos | BB25: Precio U$S | BE25: Código | BF25: Insumos | BG25: Precio U$S | BO25: Código | BP25: Insumos | BQ25: Precio U$S | BT25: Código | BU25: Insumos | BV25: Precio U$S | BY25: Código | BZ25: Insumos | CA25: Precio U$S | CE25: Envasado | CI25: Código | CJ25: Insumos | CK25: Precio U$S | CO25: Envasado | CT25: Envasado | CX25: 3759 | CY25: TAPA VILA COFRE 156 (135)(gris) - Mpack | CZ25: =+insumos!$G$284 -> 1.1352417 | DC25: 4861032 | DD25: Envase Vacio Grueso (rojo) - Fralda | DH25: 3741 | DI25: Fondo Cofre | DJ25: =insumos!$G$213 -> 0.83558719 | DM25: Código | DN25: Insumos | DO25: Precio U$S | DR25: 2055 | DS25: TAPA BLANCA 136 (cartulina)- Mpack | DT25: =+insumos!$H$266 -> 1.15 | DW25: 2055 | DX25: TAPA BLANCA 136 (cartulina)- Mpack | DY25: =+insumos!$H$266 -> 1.15
C26: Envasado | G26: 4542 | H26: Bolsa 95X60 | I26: =insumos!$I$35 -> 0.022058824 | L26: 4542 | M26: Bolsa 95X60 | N26: =insumos!$I$35 -> 0.022058824 | Q26: 3817 | R26: Cinta adhesiva ( metros) | S26: =insumos!$I$103*1.8 -> 0.02088 | T26: 1.8 metros | V26: 3817 | W26: Cinta adhesiva ( metros) | X26: =insumos!I103*1.8 -> 0.02088 | Y26: 1.8 metros | AA26: 4542 | AB26: Bolsa 95X60 | AC26: =insumos!$I$35 -> 0.022058824 | AF26: Código | AG26: Insumos | AH26: Precio U$S | AK26: 3817 | AL26: Cinta adhesiva ( metros) | AM26: =insumos!$I$103*1.8 -> 0.02088 | AN26: 1.8 metros | AQ26: Envasado | BA26: Envasado | BF26: Envasado | BP26: Envasado | BU26: Envasado | BZ26: Envasado | CD26: 3741 | CE26: Fondo Cofre | CF26: =insumos!$G$213 -> 0.83558719 | CJ26: Envasado | CN26: 3741 | CO26: Fondo Cofre | CP26: =insumos!$G$213 -> 0.83558719 | CS26: 3741 | CT26: Fondo Cofre | CU26: =insumos!$G$213 -> 0.83558719 | CX26: 4541 | CY26: Bolsa 85X60 | CZ26: =insumos!$H$43 -> 0.022058824 | DC26: Código | DD26: Insumos | DE26: Precio U$S | DH26: 5251 | DI26: TAPA INK COFRE - IMPRIMEX | DJ26: =+insumos!$H$274 -> 1.6 | DN26: Envasado | DR26: 4542 | DS26: Bolsa 95X60 | DT26: =insumos!$I$35 -> 0.022058824 | DW26: 4542 | DX26: Bolsa 95X60 | DY26: =insumos!$I$35 -> 0.022058824 | EF26: Especies para Logs | EG26: Kls. | EH26: Prec/U$S
B27: 3741 | C27: Fondo Cofre | D27: =insumos!$G$213 -> 0.83558719 | G27: 3817 | H27: Cinta adhesiva ( metros) | I27: =insumos!$I$103*1.8 -> 0.02088 | J27: 1,8 metros | L27: 3817 | M27: Cinta adhesiva ( metros) | N27: =insumos!$I$103*1.8 -> 0.02088 | O27: 1,8 metros | Q27: 2173 | R27: Fajas | S27: =+insumos!$H$149*2 -> 0.034950266 | T27: 2 unidades | V27: 2173 | W27: Fajas | X27: =+insumos!H149*2 -> 0.034950266 | Y27: 2 unidades | AA27: 3817 | AB27: Cinta adhesiva ( metros) | AC27: =insumos!$I$103*1.8 -> 0.02088 | AD27: 1.8 metros | AG27: Envasado | AK27: 2173 | AL27: Fajas | AM27: =+insumos!$H$149*2 -> 0.034950266 | AN27: 2 unidades | AP27: 5524 | AQ27: FONDO ENFRIADO (nueva medida) 505x380x155 cm - MERCOPACK | AR27: =insumos!$H$217 -> 0.895 | AZ27: 3741 | BA27: Fondo Cofre | BB27: =insumos!$G$213 -> 0.83558719 | BE27: 3741 | BF27: Fondo Cofre | BG27: =insumos!$G$213 -> 0.83558719 | BO27: 3741 | BP27: Fondo Cofre | BQ27: =insumos!$G$213 -> 0.83558719 | BT27: 3741 | BU27: Fondo Cofre | BV27: =insumos!$G$213 -> 0.83558719 | BY27: 3741 | BZ27: Fondo Cofre | CA27: =insumos!$G$213 -> 0.83558719 | CD27: 5653 | CE27: TAPA UMi CONGELADO (136) - IMPRIMEX | CF27: =+insumos!$G$283 -> 1.1 | CI27: 3741 | CJ27: Fondo Cofre | CK27: =insumos!$G$213 -> 0.83558719 | CN27: 3759 | CO27: TAPA VILA COFRE 156 (135)(gris) - Mpack | CP27: =+insumos!$G$284 -> 1.1352417 | CS27: 5653 | CT27: TAPA UMi CONGELADO (136) - IMPRIMEX | CU27: =+insumos!$G$283 -> 1.1 | CX27: 3817 | CY27: Cinta adhesiva ( metros) | CZ27: =insumos!$I$103*1.8 -> 0.02088 | DA27: 1.8 metros | DD27: Envasado | DH27: 4541 | DI27: Bolsa 85x60 | DJ27: =insumos!$H$43 -> 0.022058824 | DM27: 3741 | DN27: Fondo Cofre | DO27: =insumos!$G$213 -> 0.83558719 | DR27: 3817 | DS27: Cinta adhesiva ( metros) | DT27: =insumos!$I$103*1.8 -> 0.02088 | DU27: 1,8 metros | DW27: 3817 | DX27: Cinta adhesiva ( metros) | DY27: =insumos!$I$103*1.8 -> 0.02088 | DZ27: 1,8 metros | EE27: F06895 | EF27: Wow Meat Flavor Enhancer | EG27: =24750/0.4536 -> 54563.492 | EH27: =2.39/0.4536 -> 5.2689594 | EI27: =+EG27*EH27 -> 287492.83
B28: 3759 | C28: TAPA VILA COFRE 156 (135)(gris) - Mpack | D28: =+insumos!$G$284 -> 1.1352417 | G28: 2173 | H28: Fajas | I28: =+insumos!$H$149*2 -> 0.034950266 | J28: 2 unidades | L28: 2173 | M28: Fajas | N28: =+insumos!$H$149*2 -> 0.034950266 | O28: 2 unidades | Q28: 3636 | R28: Etiqueta Caja | S28: =+insumos!$H$121 -> 0.0445 | V28: 3636 | W28: Etiqueta Caja | X28: =+insumos!H121 -> 0.0445 | AA28: 2173 | AB28: Fajas | AC28: =+insumos!$H$149*2 -> 0.034950266 | AD28: 2 unidades | AF28: 3741 | AG28: Fondo cofre | AH28: =insumos!$G$213 -> 0.83558719 | AK28: 3636 | AL28: Etiqueta Caja | AM28: =+insumos!$H$121 -> 0.0445 | AP28: 5523 | AQ28: TAPA VILA gris - 50x38x15.5 cm (nueva medida) - Mercopack | AR28: =+insumos!$H$285 -> 1.1829611 | AZ28: 5653 | BA28: TAPA UMi CONGELADO (136) - IMPRIMEX | BB28: =+insumos!$G$283 -> 1.1 | BE28: 6287 | BF28: TAPA 135 COFRE EL RANCHO - IMPRIMEX | BG28: =+insumos!$H$263 -> 1.6 | BO28: 5653 | BP28: TAPA UMi CONGELADO (136) - IMPRIMEX | BQ28: =+insumos!$G$283 -> 1.1 | BT28: 6265 | BU28: TAPA TAURUS BIFE ONTILCOR - MERCOPACK | BV28: =+insumos!$H$279 -> 1.25 | BY28: 3759 | BZ28: TAPA VILA COFRE 156 (135)(gris) - Mpack | CA28: =+insumos!$G$284 -> 1.1352417 | CD28: 4653 | CE28: SEPARADORES 530X290 – MERCOPACK | CF28: =insumos!$H$254*2 -> 0.37281192 | CG28: 2 unidades | CI28: 5251 | CJ28: TAPA INK COFRE - IMPRIMEX | CK28: =+insumos!$H$274 -> 1.6 | CN28: 4653 | CO28: SEPARADORES 530X290 – MERCOPACK | CP28: =insumos!$H$254*4 -> 0.74562384 | CQ28: 4 unid. X caja | CS28: 4653 | CT28: SEPARADORES 530X290 – MERCOPACK | CU28: =insumos!$H$254*2 -> 0.37281192 | CV28: 2 unidades | CX28: 2173 | CY28: Fajas | CZ28: =+insumos!$H$149*2 -> 0.034950266 | DA28: 2 unidades | DC28: 3741 | DD28: Fondo Cofre | DE28: =insumos!$G$213 -> 0.83558719 | DH28: 3817 | DI28: Cinta adhesiva ( metros) | DJ28: =insumos!$I$103*1.8 -> 0.02088 | DK28: 1.8 metros | DM28: 6265 | DN28: TAPA TAURUS BIFE ONTILCOR - MERCOPACK | DO28: =+insumos!$H$279 -> 1.25 | DR28: 2173 | DS28: Fajas | DT28: =+insumos!$H$149*2 -> 0.034950266 | DU28: 2 unidades | DW28: 2173 | DX28: Fajas | DY28: =+insumos!$H$149*2 -> 0.034950266 | DZ28: 2 unidades | EE28: F06897 | EF28: Wow Phosphate Blend | EG28: =5500/0.4536 -> 12125.22 | EH28: =3.8/0.4536 -> 8.377425 | EI28: =+EG28*EH28 -> 101578.13
B29: 4653 | C29: SEPARADORES 530X290 – MERCOPACK | D29: =insumos!$H$254*2 -> 0.37281192 | E29: 2 unid. X caja | G29: 3636 | H29: Etiqueta Caja | I29: =+insumos!$H$121 -> 0.0445 | L29: 3636 | M29: Etiqueta Caja | N29: =+insumos!$H$121 -> 0.0445 | R29: Paquete | W29: Paquete | AA29: 3636 | AB29: Etiqueta Caja | AC29: =+insumos!$H$121 -> 0.0445 | AF29: 4784 | AG29: TAPA THE BLACK ANGUS - GRAIN FED (grano) cofre - IMPRIMEX | AH29: =insumos!$H$281 -> 1.6000018 | AL29: Paquete | AP29: 4986 | AQ29: SEPARADORES 570x230 mm - MERCOPACK | AR29: =insumos!$H$255*3 -> 0.56999964 | AS29: 3 unid. X caja | AZ29: 4986 | BA29: SEPARADORES 570x230 mm - MERCOPACK | BB29: =insumos!$H$255*2 -> 0.37999976 | BC29: 2 unid. X caja | BE29: 4653 | BF29: SEPARADORES 530X290 – MERCOPACK | BG29: =insumos!$H$254*2 -> 0.37281192 | BH29: 2 unid. X caja | BO29: 4653 | BP29: SEPARADORES 530X290 – MERCOPACK | BQ29: =insumos!$H$254 -> 0.18640596 | BT29: 4653 | BU29: SEPARADORES 530X290 – MERCOPACK | BV29: =insumos!$H$254*2 -> 0.37281192 | BY29: 4653 | BZ29: SEPARADORES 530X290 – MERCOPACK | CA29: =insumos!$H$254*4 -> 0.74562384 | CB29: 4 unid. X caja | CD29: 5315 | CE29: BOLSA COFRE 85(60)X46/ø40, impr. en rollo, ROSADA - STRONG | CF29: =insumos!$H$45 -> 0.028 | CI29: 4653 | CJ29: SEPARADORES 530X290 – MERCOPACK | CK29: =insumos!$H$254*3 -> 0.55921788 | CL29: 3 unid. X caja | CN29: 4541 | CO29: Bolsa 85X60 | CP29: =insumos!$H$43 -> 0.022058824 | CS29: 3817 | CT29: Cinta adhesiva ( metros) | CU29: =insumos!$I$103*1.8 -> 0.02088 | CV29: 1.8 metros | CX29: 3636 | CY29: Etiqueta Caja | CZ29: =+insumos!$H$121 -> 0.0445 | DC29: 3806 | DD29: TAPA BLANCA COFRE 135 - doble micro - MERCOPACK | DE29: =+insumos!$H$267 -> 1.2 | DH29: 2173 | DI29: Fajas | DJ29: =+insumos!$H$149*2 -> 0.034950266 | DK29: 2 unidades | DM29: 4653 | DN29: SEPARADORES 530X290 – MERCOPACK | DO29: =insumos!$H$254*3 -> 0.55921788 | DP29: 3 unid. X caja | DR29: 3636 | DS29: Etiqueta Caja | DT29: =+insumos!$H$121 -> 0.0445 | DW29: 3636 | DX29: Etiqueta Caja | DY29: =+insumos!$H$121 -> 0.0445 | EF29: Freight Ocean And Export Fees | EG29: 1 | EH29: 3379.95 | EI29: =+EH29 -> 3379.95
B30: 4541 | C30: Bolsa 85x60 | D30: =insumos!$H$43 -> 0.022058824 | H30: Paquete | M30: Paquete | Q30: 2021 | R30: BOLSA VACIO 30x65 - impr. en rollo - BEMIS | S30: =insumos!$H$75*5 -> 0.975 | T30: 5 unid. X caja | V30: 4745 | W30: Bolsa 31x40 | X30: =insumos!H93*7 -> 0.798 | Y30: 8 unid. X caja | AB30: Paquete | AF30: 4541 | AG30: Bolsa 85X60 | AH30: =insumos!$H$43 -> 0.022058824 | AK30: 2119 | AL30: HOJA 70 x 70 /30ø impr. - STRONG | AM30: =insumos!$H$224 -> 0.1 | AP30: 4542 | AQ30: Bolsa 95X60 | AR30: =insumos!$I$35 -> 0.022058824 | AZ30: 5315 | BA30: BOLSA COFRE 85(60)X46/ø40, impr. en rollo, ROSADA - STRONG | BB30: =insumos!$H$45 -> 0.028 | BE30: 6280 | BF30: BOLSA NARANJA 85(60)X46/40 - STRONG | BG30: =insumos!$H$50 -> 0.027941176 | BO30: 5315 | BP30: BOLSA COFRE 85(60)X46/ø40, impr. en rollo, ROSADA - STRONG | BQ30: =insumos!$H$45 -> 0.028 | BT30: 5353 | BU30: BOLSA COFRE 85(60)X46/ø40, impr. en rollo, AMARILLA - STRONG | BV30: =insumos!$H$44 -> 0.028 | BY30: 4541 | BZ30: Bolsa 85X60 | CA30: =insumos!$H$43 -> 0.022058824 | CD30: 3817 | CE30: Cinta adhesiva ( metros) | CF30: =insumos!$I$103*1.8 -> 0.02088 | CG30: 1,8 metros | CI30: 4541 | CJ30: Bolsa 85X60 | CK30: =insumos!$H$43 -> 0.022058824 | CN30: 3817 | CO30: Cinta adhesiva ( metros) | CP30: =insumos!$I$103*1.8 -> 0.02088 | CQ30: 1.8 metros | CS30: 5315 | CT30: BOLSA COFRE 85(60)X46/ø40, impr. en rollo, ROSADA - STRONG | CU30: =insumos!$H$45 -> 0.028 | CY30: Paquete | DC30: 4542 | DD30: Bolsa 95X60 | DE30: =insumos!$I$35 -> 0.022058824 | DH30: 3636 | DI30: Etiqueta Caja | DJ30: =+insumos!$H$121 -> 0.0445 | DM30: 5353 | DN30: BOLSA COFRE 85(60)X46/ø40, impr. en rollo, AMARILLA - STRONG | DO30: =insumos!$H$44 -> 0.028 | DS30: Paquete | DX30: Paquete | EG30: =SUM(EG27:EG29) -> 66689.713 | EI30: =SUM(EI27:EI29) -> 392450.9 | EJ30: =+EI30/EG30 -> 5.8847292
B31: 3817 | C31: Cinta adhesiva ( metros) | D31: =insumos!$I$103*1.8 -> 0.02088 | E31: 1,8 metros | G31: 6294 | H31: BOLSA PARA VACIO 24X45 (PICANHA) IMP VILA - MERCOPACK | I31: =insumos!$H$56*14 -> 2.688 | J31: 14 unid. X Caja | Q31: 3382 | R31: ET. PAI 102X78 LISA - RR | S31: =insumos!$H$135*5 -> 0.1025 | T31: 5 unid. X caja | W31: Total | X31: =SUM(X23:X30) -> 2.1703891 | AA31: 2119 | AB31: HOJA 70 x 70 /30ø impr. - STRONG | AC31: =insumos!$H$224*10 -> 1 | AD31: 10 unid. X caja | AF31: 3817 | AG31: Cinta adhesiva ( metros) | AH31: =insumos!I124*1.8 -> 0 | AI31: 1,8 metros | AP31: 3817 | AQ31: Cinta adhesiva ( metros) | AR31: =insumos!$I$103*1.8 -> 0.02088 | AS31: 1,8 metros | AZ31: 3817 | BA31: Cinta adhesiva ( metros) | BB31: =insumos!$I$103*1.8 -> 0.02088 | BC31: 1,8 metros | BE31: 3817 | BF31: Cinta adhesiva ( metros) | BG31: =insumos!$I$103*1.8 -> 0.02088 | BH31: 1,8 metros | BO31: 3817 | BP31: Cinta adhesiva ( metros) | BQ31: =insumos!$I$103*1.8 -> 0.02088 | BR31: 1,8 metros | BT31: 3817 | BU31: Cinta adhesiva ( metros) | BV31: =insumos!$I$103*1.8 -> 0.02088 | BW31: 1,8 metros | BY31: 3817 | BZ31: Cinta adhesiva ( metros) | CA31: =insumos!$I$103*1.8 -> 0.02088 | CB31: 1.8 metros | CD31: 2173 | CE31: Fajas | CF31: =+insumos!$H$149*2 -> 0.034950266 | CG31: 2 unidades | CI31: 3817 | CJ31: Cinta adhesiva ( metros) | CK31: =insumos!$I$103*1.8 -> 0.02088 | CL31: 1.8 metros | CN31: 2173 | CO31: Fajas | CP31: =+insumos!$H$149*2 -> 0.034950266 | CQ31: 2 unidades | CS31: 2173 | CT31: Fajas | CU31: =+insumos!$H$149*2 -> 0.034950266 | CV31: 2 unidades | CX31: 6293 | CY31: Bolsa 20x50 Vila | CZ31: =insumos!$H$55*10 -> 1.61 | DA31: 10 unid. X caja | DC31: 3817 | DD31: Cinta adhesiva ( metros) | DE31: =insumos!$I$103*1.8 -> 0.02088 | DI31: Paquete | DM31: 3817 | DN31: Cinta adhesiva ( metros) | DO31: =insumos!$I$103*1.8 -> 0.02088 | DP31: 1,8 metros | DR31: 5214 | DS31: BOLSA VACIO 18X67 SOLDA V SB15- MERCOPACK | DT31: =insumos!$H$65*4 -> 0.55199919 | DU31: 4 unid. X caja | DW31: 5138 | DX31: ET. BOPP TERM. 102X78 - RR | DY31: =insumos!$H$113*21 -> 0.56719853 | DZ31: 21 unid. X caja
B32: 2173 | C32: Fajas | D32: =+insumos!$H$149*2 -> 0.034950266 | E32: 2 unidades | G32: 5138 | H32: ET. BOPP TERM. 102X78 - RR | I32: =insumos!$H$113*14 -> 0.37813235 | J32: 14 unid. X Caja | L32: 5138 | M32: ET. BOPP TERM. 102X78 - RR | N32: =insumos!$H$113*7 -> 0.18906618 | O32: 7 unid. X caja | R32: Total | S32: =SUM(S23:S31) -> 2.4498891 | W32: peso prom. Caja | X32: 22 | AA32: 3887 | AB32: ET. BOPP TERMICO 100x050 LISA - RR | AC32: =insumos!$H$120*10 -> 0.199 | AD32: 10 unid. X caja | AF32: 2173 | AG32: Fajas | AH32: =+insumos!H170*2 -> 0 | AI32: 2 unidades | AL32: Total | AM32: =SUM(AM23:AM31) -> 2.0053502 | AP32: 2173 | AQ32: Fajas | AR32: =+insumos!$H$149*2 -> 0.034950266 | AS32: 2 unidades | AZ32: 2173 | BA32: Fajas | BB32: =+insumos!$H$149*2 -> 0.034950266 | BC32: 2 unidades | BE32: 2173 | BF32: Fajas | BG32: =+insumos!$H$149*2 -> 0.034950266 | BH32: 2 unidades | BO32: 2173 | BP32: Fajas | BQ32: =+insumos!$H$149*2 -> 0.034950266 | BR32: 2 unidades | BT32: 2173 | BU32: Fajas | BV32: =+insumos!$H$149*2 -> 0.034950266 | BW32: 2 unidades | BY32: 2173 | BZ32: Fajas | CA32: =+insumos!$H$149*2 -> 0.034950266 | CB32: 2 unidades | CD32: 3636 | CE32: Etiqueta Caja | CF32: =+insumos!$H$121 -> 0.0445 | CI32: 2173 | CJ32: Fajas | CK32: =+insumos!$H$149*2 -> 0.034950266 | CL32: 2 unidades | CN32: 3636 | CO32: Etiqueta Caja | CP32: =+insumos!$H$121 -> 0.0445 | CS32: 3636 | CT32: Etiqueta Caja | CU32: =+insumos!$H$121 -> 0.0445 | CY32: Total | CZ32: =SUM(CZ24:CZ31) -> 3.7032179 | DC32: 2173 | DD32: Fajas | DE32: =+insumos!$H$149*2 -> 0.034950266 | DH32: 5138 | DI32: ET. BOPP TERM. 102X78 - RR | DJ32: =insumos!$H$113*8 -> 0.21607563 | DK32: 8 unid. X caja | DM32: 2173 | DN32: Fajas | DO32: =+insumos!$H$149*2 -> 0.034950266 | DP32: 2 unidades | DW32: 6229 | DX32: TAPA BARRERA NEGRA 250 C (FILM PARA TERMOFORMADORA) - MULTIPACK DIAMALER | DY32: =insumos!$I$265*21 -> 0.4519466 | DZ32: 21 unid. X caja
B33: 3636 | C33: Etiqueta Caja | D33: =+insumos!$H$121 -> 0.0445 | H33: Total | I33: =SUM(I24:I32) -> 5.2664826 | M33: Total | N33: =SUM(N24:N32) -> 2.3564553 | R33: peso prom. Caja | S33: =11124.76/613 -> 18.148059 | W33: Costo x kls | X33: =+X31/X32 -> 0.09865405 | AB33: Total | AC33: =SUM(AC24:AC32) -> 2.5713891 | AF33: 3636 | AG33: Etiqueta Caja | AH33: =+insumos!H142 -> 0.052272727 | AL33: peso prom. Caja | AM33: =55840.63/2899 -> 19.262032 | AP33: 3636 | AQ33: Etiqueta Caja | AR33: =+insumos!$H$121 -> 0.0445 | AZ33: 3636 | BA33: Etiqueta Caja | BB33: =+insumos!$H$121 -> 0.0445 | BE33: 3636 | BF33: Etiqueta Caja | BG33: =+insumos!$H$121 -> 0.0445 | BO33: 3636 | BP33: Etiqueta Caja | BQ33: =+insumos!$H$121 -> 0.0445 | BT33: 3636 | BU33: Etiqueta Caja | BV33: =+insumos!$H$121 -> 0.0445 | BY33: 3636 | BZ33: Etiqueta Caja | CA33: =+insumos!$H$121 -> 0.0445 | CE33: Paquete | CI33: 3636 | CJ33: Etiqueta Caja | CK33: =+insumos!$H$121 -> 0.0445 | CO33: Paquete | CT33: Paquete | CY33: peso prom. Caja | CZ33: 12.83 | DC33: 3636 | DD33: Etiqueta Caja | DE33: =+insumos!$H$121 -> 0.0445 | DH33: 5250 | DI33: Et. INK OPP - 7.2X14 - IMPRIMEX | DJ33: =insumos!H149*8 -> 0.13980107 | DK33: 8 unid. X caja | DM33: 3636 | DN33: Etiqueta Caja | DO33: =+insumos!$H$121 -> 0.0445 | DS33: Total | DT33: =SUM(DT24:DT32) -> 2.7193883 | DW33: 6254 | DX33: FONDO BARRERA TERMOFORMADORA TR NI 180 - MULTIPACK DIAMALER | DY33: =+insumos!$I$208*21 -> 0.93360645 | DZ33: 21 unid. X caja
C34: Paquete | H34: peso prom. Caja | I34: 16.6 | M34: peso prom. Caja | N34: =125974.25/7458 -> 16.891157 | R34: Costo x kls | S34: =+S32/S33 -> 0.13499455 | W34: porcentaje cobertura ( fallas, roturas) + 3 % | X34: =X33*1.03 -> 0.10161367 | AB34: peso prom. Caja | AC34: =745.27/38 -> 19.612368 | AG34: Paquete | AL34: Costo x kls | AM34: =+AM32/AM33 -> 0.10410897 | AQ34: Paquete | BA34: Paquete | BF34: Paquete | BP34: Paquete | BU34: Paquete | BZ34: Paquete | CD34: 5138 | CE34: ET. BOPP TERM. 102X78 - RR | CF34: =insumos!$H$113*6 -> 0.16205672 | CG34: 6 unid. X caja | CJ34: Paquete | CN34: 6211 | CO34: ETIQUETAS BOPP MET.DOBLE CAPA 084X081 LAM. MATE VILA - ASADO 4 COSTILLAS CONGELADA - RR | CP34: =insumos!$H$183*12 -> 1.1270554 | CQ34: 12 unid. X caja | CS34: 5138 | CT34: ET. BOPP TERM. 102X78 - RR | CU34: =insumos!$H$113*6 -> 0.16205672 | CV34: 6 unid. X caja | CY34: Costo x kls | CZ34: =+CZ32/CZ33 -> 0.28863741 | DD34: Paquete | DH34: 6297 | DI34: BOLSA PARA VACIO 18X45 | DJ34: =insumos!$H$53*8 -> 1.248 | DK34: 8 unid. X caja | DN34: Paquete | DS34: peso prom. Caja | DT34: 16.13 | DW34: 2094 | DX34: etiq. VIANDE HACHEE 22x9,7cm IMPRIMEX | DY34: =insumos!H142*21 -> 1.0977273 | DZ34: 21 unid. X caja
B35: 6290 | C35: Etiqueta delantera | D35: =insumos!H154*12 -> 1.176 | E35: 12 unid. X caja | H35: Costo x kls | I35: =+I33/I34 -> 0.31725799 | M35: Costo x kls | N35: =+N33/N34 -> 0.13950822 | R35: porcentaje cobertura ( fallas, roturas) + 3 % | S35: =S34*1.03 -> 0.13904439 | AB35: Costo x kls | AC35: =+AC33/AC34 -> 0.13111058 | AF35: 5138 | AG35: Etiqueta 102x78 Bopp Term | AH35: =insumos!H113*12 -> 0.32411345 | AI35: 12 unid. X caja | AL35: porcentaje cobertura ( fallas, roturas) + 3 % | AM35: =AM34*1.03 -> 0.10723224 | AP35: 4102 | AQ35: Etiqueta Trasera 100x100 | AR35: =insumos!$H$115*28 -> 0.924 | AS35: 28 unid. X caja | AZ35: 4102 | BA35: Etiqueta Trasera 100x100 | BB35: =insumos!$H$115*9 -> 0.297 | BC35: 9 unid. X caja | BE35: 5138 | BF35: ET. BOPP TERM. 102X78 - RR | BG35: =insumos!$H$113*12 -> 0.32411345 | BH35: 12 unid. X caja | BO35: 4102 | BP35: Etiqueta Trasera 100x100 | BQ35: =insumos!$H$115*4 -> 0.132 | BR35: 4 unid. X caja | BT35: 5138 | BU35: ET. BOPP TERM. 102X78 - RR | BV35: =insumos!$H$113*5 -> 0.13504727 | BW35: 5 unid. X caja | BY35: 6211 | BZ35: ETIQUETAS BOPP MET.DOBLE CAPA 084X081 LAM. MATE VILA - ASADO 4 COSTILLAS CONGELADA - RR | CA35: =insumos!$H$183*12 -> 1.1270554 | CB35: 12 unid. X caja | CD35: 5403 | CE35: BOLSA VACIO 31X45 UMI - MERCOPACK | CF35: =insumos!$H$80*6 -> 1.326 | CG35: 6 unid. X caja | CI35: 5138 | CJ35: ET. BOPP TERM. 102X78 - RR | CK35: =insumos!$H$113*12 -> 0.32411345 | CL35: 12 unid. X caja | CN35: 5202 | CO35: Etiqueta Trasera | CP35: =insumos!$H$114*12 -> 0.31613714 | CQ35: 12 unid. X caja | CS35: 5403 | CT35: BOLSA VACIO 31X45 UMI - MERCOPACK | CU35: =insumos!$H$80*6 -> 1.326 | CV35: 6 unid. X caja | CY35: porcentaje cobertura ( fallas, roturas) + 3 % | CZ35: =CZ34*1.03 -> 0.29729653 | DC35: 5214 | DD35: BOLSA VACIO 18X67 SOLDA V SB15- MERCOPACK | DE35: =insumos!$H$65*10 -> 1.379998 | DI35: Total | DJ35: =SUM(DJ25:DJ34) -> 4.161853 | DS35: Costo x kls | DT35: =+DT33/DT34 -> 0.16859196 | DX35: Total | DY35: =SUM(DY24:DY34) -> 5.2178679
B36: 5202 | C36: Etiqueta Trasera | D36: =insumos!$H$114*12 -> 0.31613714 | E36: 12 unid. X caja | H36: porcentaje cobertura ( fallas, roturas) + 3 % | I36: =I35*1.03 -> 0.32677573 | M36: porcentaje cobertura ( fallas, roturas) + 3 % | N36: =N35*1.03 -> 0.14369347 | V36: 993271 | W36: Envase Entraña Interna Black Angus (4x paq.) | AB36: porcentaje cobertura ( fallas, roturas) + 3 % | AC36: =AC35*1.03 -> 0.1350439 | AF36: 4741 | AG36: Bolsa 20x50 | AH36: =insumos!$H$90*12 -> 3.696 | AI36: 12 unid. X caja | AP36: 6229 | AQ36: TAPA BARRERA NEGRA 250 C (FILM PARA TERMOFORMADORA) - MULTIPACK DIAMALER | AR36: =insumos!$I$265*28 -> 0.60259547 | AS36: 28 unid. X caja | AZ36: 6229 | BA36: TAPA BARRERA NEGRA 250 C (FILM PARA TERMOFORMADORA) - MULTIPACK DIAMALER | BB36: =insumos!$I$265*9 -> 0.1936914 | BC36: 9 unid. X caja | BE36: 6229 | BF36: TAPA BARRERA NEGRA 250 C (FILM PARA TERMOFORMADORA) - MULTIPACK DIAMALER | BG36: =insumos!$I$265*12 -> 0.2582552 | BH36: 12 unid. X caja | BO36: 5403 | BP36: BOLSA VACIO 31X45 UMI - MERCOPACK | BQ36: =insumos!$H$80*4 -> 0.884 | BR36: 4 unid. X caja | BT36: 4973 | BU36: BOLSA VACIO 31X40 impr. TAURUS GOLD - MERCOPACK | BV36: =insumos!$H$79*5 -> 1.07 | BW36: 5 unid. X caja | BY36: 5202 | BZ36: Etiqueta Trasera | CA36: =insumos!$H$114*12 -> 0.31613714 | CB36: 12 unid. X caja | CI36: 6229 | CJ36: TAPA BARRERA NEGRA 250 C (FILM PARA TERMOFORMADORA) - MULTIPACK DIAMALER | CK36: =insumos!$I$265*12 -> 0.2582552 | CL36: 12 unid. X caja | CN36: 6229 | CO36: TAPA BARRERA NEGRA 250 C (FILM PARA TERMOFORMADORA) - MULTIPACK DIAMALER | CP36: =insumos!$I$265*12 -> 0.2582552 | CQ36: 12 unid. X caja | CT36: Total | CU36: =SUM(CU26:CU35) -> 3.9247861 | DC36: 5138 | DD36: ET. BOPP TERM. 102X78 - RR | DE36: =insumos!$H$113*10 -> 0.27009454 | DI36: peso prom. Caja | DJ36: 12.74 | DM36: 6229 | DN36: TAPA BARRERA NEGRA 250 C (FILM PARA TERMOFORMADORA) - MULTIPACK DIAMALER | DO36: =insumos!$I$265*12 -> 0.2582552 | DP36: 12 unid. X caja | DS36: porcentaje cobertura ( fallas, roturas) + 3 % | DT36: =DT35*1.03 -> 0.17364972 | DX36: peso prom. Caja | DY36: 20.9
B37: 6229 | C37: TAPA BARRERA NEGRA 250 C (FILM PARA TERMOFORMADORA) - MULTIPACK DIAMALER | D37: =insumos!$I$265*12 -> 0.2582552 | E37: 12 unid. X caja | Q37: 998009 | R37: Envase Paleta | V37: Código | W37: Insumos | X37: Precio U$S | AK37: 1987060 | AL37: Envase Asado c/h 4c Vila | AP37: 6254 | AQ37: FONDO BARRERA TERMOFORMADORA TR NI 180 - MULTIPACK DIAMALER | AR37: =+insumos!$I$208*28 -> 1.2448086 | AS37: 28 unid. X caja | AZ37: 6254 | BA37: FONDO BARRERA TERMOFORMADORA TR NI 180 - MULTIPACK DIAMALER | BB37: =+insumos!$I$208*9 -> 0.40011705 | BC37: 9 unid. X caja | BE37: 6254 | BF37: FONDO BARRERA TERMOFORMADORA TR NI 180 - MULTIPACK DIAMALER | BG37: =+insumos!$I$208*12 -> 0.5334894 | BH37: 12 unid. X caja | BY37: 6229 | BZ37: TAPA BARRERA NEGRA 250 C (FILM PARA TERMOFORMADORA) - MULTIPACK DIAMALER | CA37: =insumos!$I$265*12 -> 0.2582552 | CB37: 12 unid. X caja | CI37: 6254 | CJ37: FONDO BARRERA TERMOFORMADORA TR NI 180 - MULTIPACK DIAMALER | CK37: =+insumos!$I$208*12 -> 0.5334894 | CL37: 12 unid. X caja | CN37: 6254 | CO37: FONDO BARRERA TERMOFORMADORA TR NI 180 - MULTIPACK DIAMALER | CP37: =+insumos!$I$208*12 -> 0.5334894 | CQ37: 12 unid. X caja | CT37: peso prom. Caja | CU37: =331.56/26 -> 12.752308 | DD37: Total | DE37: =SUM(DE28:DE36) -> 3.8080688 | DI37: Costo x kls | DJ37: =+DJ35/DJ36 -> 0.32667606 | DM37: 6254 | DN37: FONDO BARRERA TERMOFORMADORA TR NI 180 - MULTIPACK DIAMALER | DO37: =+insumos!$I$208*12 -> 0.5334894 | DP37: 12 unid. X caja | DX37: Costo x kls | DY37: =+DY35/DY36 -> 0.24965875
B38: 6254 | C38: FONDO BARRERA TERMOFORMADORA TR NI 180 - MULTIPACK DIAMALER | D38: =+insumos!$I$208*12 -> 0.5334894 | E38: 12 unid. X caja | G38: 437025 | H38: Envase Picaña | I38: 720 | J38: =I38/E2 -> 17.883756 | L38: 436051 | M38: Envase Cabeza de Lomo | N38: 553 | O38: =N38/E2 -> 13.735718 | Q38: Código | R38: Insumos | S38: Precio U$S | W38: Envasado | AA38: 991022 | AB38: Envase Nalga C/tapa | AK38: Código | AL38: Insumos | AM38: Precio U$S | AP38: 5868 | AQ38: PADS BLANCOS 4.5" x 7" - TITE DRI | AR38: =insumos!$I$243*28 -> 0.53088 | AS38: 28 unid. X caja | AZ38: 6138 | BA38: FAJAS UMI - 8x19.5cm - IMPRIMEX | BB38: =insumos!$H$197*9 -> 1.3087059 | BC38: 9 unid. X caja | BE38: 6288 | BF38: ETIQUETAS BOPP MET. ADC 6000 60X110 LAMINADO MATE - EL RANCHO PASSION - RR | BG38: =insumos!$H$176*12 -> 0.648 | BH38: 12 unid. X caja | BY38: 6254 | BZ38: FONDO BARRERA TERMOFORMADORA TR NI 180 - MULTIPACK DIAMALER | CA38: =+insumos!$I$208*12 -> 0.5334894 | CB38: 12 unid. X caja | CE38: Total | CF38: =SUM(CF26:CF37) -> 3.9247861 | CI38: 6142 | CJ38: Faja iNK - 8x19.5 - IMPRIMEX | CK38: =insumos!$H$194*12 -> 2.4 | CL38: 12 unid. X caja | CO38: Total | CP38: =SUM(CP26:CP37) -> 5.0737789 | CT38: Costo x kls | CU38: =+CU36/CU37 -> 0.30777066 | DD38: peso prom. Caja | DE38: 11.61 | DI38: porcentaje cobertura ( fallas, roturas) + 3 % | DJ38: =DJ37*1.03 -> 0.33647634 | DM38: 5868 | DN38: PADS BLANCOS 4.5" x 7" - TITE DRI | DO38: =insumos!$I$243*12 -> 0.22752 | DP38: 12 unid. X caja | DX38: porcentaje cobertura ( fallas, roturas) + 3 % | DY38: =DY37*1.03 -> 0.25714852
B39: 5868 | C39: PADS BLANCOS 4.5" x 7" - TITE DRI | D39: =insumos!$I$243*12 -> 0.22752 | E39: 12 unid. X caja | G39: Código | H39: Insumos | I39: Precio U$S | L39: Código | M39: Insumos | N39: Precio U$S | R39: Envasado | V39: 6184 | W39: Fondo Congelado | X39: =insumos!$H$215 -> 0.6 | AA39: Código | AB39: Insumos | AC39: Precio U$S | AL39: Envasado | AQ39: Total | AR39: =SUM(AR27:AR38) -> 6.0726339 | BA39: Total | BB39: =SUM(BB27:BB38) -> 4.6434315 | BF39: Total | BG39: =SUM(BG27:BG38) -> 4.7005286 | BP39: Total | BQ39: =SUM(BQ27:BQ38) -> 3.2663234 | BU39: Total | BV39: =SUM(BV27:BV38) -> 3.7917766 | BZ39: Total | CA39: =SUM(CA27:CA38) -> 5.0737789 | CE39: peso prom. Caja | CF39: =286.51/22 -> 13.023182 | CJ39: Total | CK39: =SUM(CK27:CK38) -> 6.6330522 | CO39: peso prom. Caja | CP39: =1990.15/268 -> 7.4259328 | CT39: porcentaje cobertura ( fallas, roturas) + 3 % | CU39: =CU38*1.03 -> 0.31700378 | DD39: Costo x kls | DE39: =+DE37/DE38 -> 0.32799903 | DN39: Total | DO39: =SUM(DO27:DO38) -> 3.7923999
C40: Total | D40: =SUM(D27:D39) -> 4.9774316 | H40: Envasado | M40: Envasado | Q40: 6184 | R40: Fondo Congelado | S40: =insumos!$H$215 -> 0.6 | V40: 5523 | W40: TAPA VILA gris - 50x38x15.5 cm (nueva medida) - Mercopack | X40: =+insumos!$H$285 -> 1.1829611 | AB40: Envasado | AK40: 3741 | AL40: Fondo Cofre | AM40: =insumos!$G$213 -> 0.83558719 | AQ40: peso prom. Caja | AR40: 8.8 | BA40: peso prom. Caja | BB40: =1024.81/146 -> 7.0192466 | BF40: peso prom. Caja | BG40: =4072.11/406 -> 10.029828 | BP40: peso prom. Caja | BQ40: =1093.52/90 -> 12.150222 | BU40: peso prom. Caja | BV40: =24984.64/2175 -> 11.487191 | BZ40: peso prom. Caja | CA40: =494.96/51 -> 9.705098 | CE40: Costo x kls | CF40: =+CF38/CF39 -> 0.30136922 | CJ40: peso prom. Caja | CK40: =904.53/182 -> 4.9699451 | CO40: Costo x kls | CP40: =+CP38/CP39 -> 0.68325138 | DD40: porcentaje cobertura ( fallas, roturas) + 3 % | DE40: =DE39*1.03 -> 0.33783901 | DH40: 5516560 | DI40: Envase Asado s/h 4c INK | DN40: peso prom. Caja | DO40: 4.85
C41: peso prom. Caja | D41: 11.3 | G41: 5524 | H41: FONDO ENFRIADO (nueva medida) 505x380x155 cm - MERCOPACK | I41: =insumos!$H$217 -> 0.895 | L41: 3741 | M41: Fondo Cofre | N41: =insumos!$G$213 -> 0.83558719 | Q41: 2037 | R41: Tapa blanca congelado | S41: =+insumos!$H$268 -> 0.65 | V41: 4542 | W41: Bolsa 95X60 | X41: =insumos!$I$35 -> 0.022058824 | AA41: 6184 | AB41: Fondo Congelado | AC41: =insumos!$H$215 -> 0.6 | AG41: Total | AH41: =SUM(AH28:AH36) -> 6.5300339 | AK41: 3759 | AL41: TAPA VILA COFRE 156 (135)(gris) - Mpack | AM41: =+insumos!$G$284 -> 1.1352417 | AQ41: Costo x kls | AR41: =+AR39/AR40 -> 0.69007204 | BA41: Costo x kls | BB41: =+BB39/BB40 -> 0.66152848 | BF41: Costo x kls | BG41: =+BG39/BG40 -> 0.46865498 | BP41: Costo x kls | BQ41: =+BQ39/BQ40 -> 0.26882829 | BU41: Costo x kls | BV41: =+BV39/BV40 -> 0.33008737 | BZ41: Costo x kls | CA41: =+CA39/CA40 -> 0.52279522 | CE41: porcentaje cobertura ( fallas, roturas) + 3 % | CF41: =CF40*1.03 -> 0.31041029 | CJ41: Costo x kls | CK41: =+CK39/CK40 -> 1.3346329 | CO41: porcentaje cobertura ( fallas, roturas) + 3 % | CP41: =CP40*1.03 -> 0.70374893 | CS41: 6173916 | CT41: Envasado Bife Ancho Porcionado UMI | DH41: Código | DI41: Insumos | DJ41: Precio U$S | DN41: Costo x kls | DO41: =+DO39/DO40 -> 0.78193813
C42: Costo x kls | D42: =+D40/D41 -> 0.44048067 | G42: 5523 | H42: TAPA VILA gris - 50x38x15.5 cm (nueva medida) - Mercopack | I42: =+insumos!$H$285 -> 1.1829611 | L42: 3806 | M42: TAPA BLANCA COFRE 135 - doble micro - MERCOPACK | N42: =+insumos!$H$267 -> 1.2 | Q42: 4542 | R42: Bolsa 95X60 | S42: =insumos!$I$35 -> 0.022058824 | V42: 3817 | W42: Cinta adhesiva ( metros) | X42: =insumos!$I$103*1.8 -> 0.02088 | Y42: 1.8 metros | AA42: 2037 | AB42: Tapa blanca congelado | AC42: =+insumos!$H$268 -> 0.65 | AG42: peso prom. Caja | AH42: 14.4 | AK42: 4653 | AL42: SEPARADORES 530X290 – MERCOPACK | AM42: =insumos!$H$254*2 -> 0.37281192 | AN42: 2 unidades | AQ42: porcentaje cobertura ( fallas, roturas) + 3 % | AR42: =AR41*1.03 -> 0.7107742 | BA42: porcentaje cobertura ( fallas, roturas) + 3 % | BB42: =BB41*1.03 -> 0.68137434 | BF42: porcentaje cobertura ( fallas, roturas) + 3 % | BG42: =BG41*1.03 -> 0.48271462 | BP42: porcentaje cobertura ( fallas, roturas) + 3 % | BQ42: =BQ41*1.03 -> 0.27689313 | BU42: porcentaje cobertura ( fallas, roturas) + 3 % | BV42: =BV41*1.03 -> 0.33999 | BZ42: porcentaje cobertura ( fallas, roturas) + 3 % | CA42: =CA41*1.03 -> 0.53847908 | CJ42: porcentaje cobertura ( fallas, roturas) + 3 % | CK42: =CK41*1.03 -> 1.3746719 | CS42: Código | CT42: Insumos | CU42: Precio U$S | DI42: Envasado | DN42: porcentaje cobertura ( fallas, roturas) + 3 % | DO42: =DO41*1.03 -> 0.80539628
C43: porcentaje cobertura ( fallas, roturas) + 3 % | D43: =D42*1.03 -> 0.45369509 | G43: 4542 | H43: Bolsa 95X60 | I43: =insumos!$I$35 -> 0.022058824 | L43: 4541 | M43: Bolsa 85x60 | N43: =insumos!$H$43 -> 0.022058824 | Q43: 3817 | R43: Cinta adhesiva ( metros) | S43: =insumos!$I$103*1.8 -> 0.02088 | T43: 1.8 metros | V43: 2173 | W43: Fajas | X43: =+insumos!$H$149*2 -> 0.034950266 | Y43: 2 unidades | AA43: 4542 | AB43: Bolsa 95X60 | AC43: =insumos!$I$35 -> 0.022058824 | AG43: Costo x kls | AH43: =+AH41/AH42 -> 0.45347458 | AK43: 3817 | AL43: Cinta adhesiva ( metros) | AM43: =insumos!$I$103*1.8 -> 0.02088 | AN43: 1.8 metros | CD43: 4545960 | CE43: Envase Asado 4/C en tiras UMI | CN43: 4858560 | CO43: Envase Asado c/h 5c Manta Vila | CT43: Envasado | DH43: 3741 | DI43: Fondo Cofre | DJ43: =insumos!$G$213 -> 0.83558719
G44: 3817 | H44: Cinta adhesiva ( metros) | I44: =insumos!$I$103*1.8 -> 0.02088 | J44: 1,8 metros | L44: 3817 | M44: Cinta adhesiva ( metros) | N44: =insumos!$I$103*1.8 -> 0.02088 | O44: 1,8 metros | Q44: 2173 | R44: Fajas | S44: =+insumos!$H$149*2 -> 0.034950266 | T44: 2 unidades | V44: 3636 | W44: Etiqueta Caja | X44: =+insumos!$H$121 -> 0.0445 | AA44: 3817 | AB44: Cinta adhesiva ( metros) | AC44: =insumos!$I$103*1.8 -> 0.02088 | AD44: 1.8 metros | AG44: porcentaje cobertura ( fallas, roturas) + 3 % | AH44: =AH43*1.03 -> 0.46707882 | AK44: 4541 | AL44: Bolsa 85x60 | AM44: =insumos!$H$43 -> 0.022058824 | AP44: 3673760 | AQ44: Envase Asado 8/C en Tira | AZ44: 441916 | BA44: Envasado Bife Ancho Porcionado | BE44: 442033 | BF44: Envasado Bife de Vacio EL RANCHO | BO44: 3516193 | BP44: Envasado Intercostales Largos UMI | BT44: 4516060 | BU44: Envasado Asado c/h 4c Taurus | BY44: 4543132 | BZ44: Envasado Flap Vila - Fralda | CD44: Código | CE44: Insumos | CF44: Precio U$S | CI44: 4546010 | CJ44: Envasado Aguja INK | CN44: Código | CO44: Insumos | CP44: Precio U$S | CS44: 3741 | CT44: Fondo Cofre | CU44: =insumos!$G$213 -> 0.83558719 | DH44: 5251 | DI44: TAPA INK COFRE - IMPRIMEX | DJ44: =+insumos!$H$274 -> 1.6 | DM44: 1993930 | DN44: Envasado Lomo TG Porcionado
B45: 439016 | C45: Envase Bife Ancho | D45: =1160 -> 1160 | E45: =D45/E2 -> 28.812717 | G45: 2173 | H45: Fajas | I45: =+insumos!$H$149*2 -> 0.034950266 | J45: 2 unidades | L45: 2173 | M45: Fajas | N45: =+insumos!$H$149*2 -> 0.034950266 | O45: 2 unidades | Q45: 3636 | R45: Etiqueta Caja | S45: =+insumos!$H$121 -> 0.0445 | W45: Paquete | AA45: 2173 | AB45: Fajas | AC45: =+insumos!$H$149*2 -> 0.034950266 | AD45: 2 unidades | AK45: 2173 | AL45: Fajas | AM45: =+insumos!$H$149*2 -> 0.034950266 | AN45: 2 unidades | AP45: Código | AQ45: Insumos | AR45: Precio U$S | AZ45: Código | BA45: Insumos | BB45: Precio U$S | BE45: Código | BF45: Insumos | BG45: Precio U$S | BO45: Código | BP45: Insumos | BQ45: Precio U$S | BT45: Código | BU45: Insumos | BV45: Precio U$S | BY45: Código | BZ45: Insumos | CA45: Precio U$S | CE45: Envasado | CI45: Código | CJ45: Insumos | CK45: Precio U$S | CO45: Envasado | CS45: 5653 | CT45: TAPA UMi CONGELADO (136) - IMPRIMEX | CU45: =+insumos!$G$283 -> 1.1 | DH45: 4986 | DI45: SEPARADORES 570x230 mm - MERCOPACK | DJ45: =insumos!$H$255*2 -> 0.37999976 | DK45: 2 unid. X caja | DM45: Código | DN45: Insumos | DO45: Precio U$S
B46: Código | C46: Insumos | D46: Precio U$S | G46: 3636 | H46: Etiqueta Caja | I46: =+insumos!$H$121 -> 0.0445 | L46: 3636 | M46: Etiqueta Caja | N46: =+insumos!$H$121 -> 0.0445 | R46: Paquete | V46: 5450 | W46: Bolsa 22x55 | X46: =insumos!H91*5 -> 0.58996599 | Y46: 5 unid. X caja | AA46: 3636 | AB46: Etiqueta Caja | AC46: =+insumos!$H$121 -> 0.0445 | AF46: 886407 | AG46: Envase Quijada Grain Fed | AK46: 3636 | AL46: Etiqueta Caja | AM46: =+insumos!$H$121 -> 0.0445 | AQ46: Envasado | BA46: Envasado | BF46: Envasado | BP46: Envasado | BU46: Envasado | BZ46: Envasado | CD46: 3741 | CE46: Fondo Cofre | CF46: =insumos!$G$213 -> 0.83558719 | CJ46: Envasado | CN46: 3741 | CO46: Fondo Cofre | CP46: =insumos!$G$213 -> 0.83558719 | CS46: 4986 | CT46: SEPARADORES 570x230 mm - MERCOPACK | CU46: =insumos!$H$255*4 -> 0.75999952 | CV46: 4 unid. X caja | DH46: 4541 | DI46: Bolsa 85x60 | DJ46: =insumos!$H$43 -> 0.022058824 | DK46: 1.8 metros | DN46: Envasado
C47: Envasado | H47: Paquete | M47: Paquete | Q47: 4745 | R47: BOLSA VACIO IMP. 31X40 (30X40) - MERCOPACK | S47: =insumos!$H$93*6 -> 0.684 | T47: 6 unid. X caja | W47: Total | X47: =SUM(X39:X46) -> 2.4953162 | AB47: Paquete | AF47: Código | AG47: Insumos | AH47: Precio U$S | AL47: Paquete | AP47: 5524 | AQ47: FONDO ENFRIADO (nueva medida) 505x380x155 cm - MERCOPACK | AR47: =insumos!$H$217 -> 0.895 | AZ47: 3741 | BA47: Fondo Cofre | BB47: =insumos!$G$213 -> 0.83558719 | BE47: 3741 | BF47: Fondo Cofre | BG47: =insumos!$G$213 -> 0.83558719 | BO47: 3741 | BP47: Fondo Cofre | BQ47: =insumos!$G$213 -> 0.83558719 | BT47: 3741 | BU47: Fondo Cofre | BV47: =insumos!$G$213 -> 0.83558719 | BY47: 5524 | BZ47: FONDO ENFRIADO (nueva medida) 505x380x155 cm - MERCOPACK | CA47: =insumos!$H$217 -> 0.895 | CD47: 5653 | CE47: TAPA UMi CONGELADO (136) - IMPRIMEX | CF47: =+insumos!$G$283 -> 1.1 | CI47: 3741 | CJ47: Fondo Cofre | CK47: =insumos!$G$213 -> 0.83558719 | CN47: 3759 | CO47: TAPA VILA COFRE 156 (135)(gris) - Mpack | CP47: =+insumos!$G$284 -> 1.1352417 | CS47: 5315 | CT47: BOLSA COFRE 85(60)X46/ø40, impr. en rollo, ROSADA - STRONG | CU47: =insumos!$H$45 -> 0.028 | DH47: 3817 | DI47: Cinta adhesiva ( metros) | DJ47: =insumos!$I$103*1.8 -> 0.02088 | DK47: 2 unidades | DM47: 3741 | DN47: Fondo Cofre | DO47: =insumos!$G$213 -> 0.83558719
B48: 3741 | C48: Fondo Cofre | D48: =insumos!$G$213 -> 0.83558719 | G48: 6294 | H48: BOLSA PARA VACIO 24X45 (PICANHA) IMP VILA - MERCOPACK | I48: =insumos!$H$56*12 -> 2.304 | L48: 2012 | M48: BOLSA VACIO 20x30 - impr. en rollo - BEMIS | N48: =insumos!$H$67*12 -> 0.73201116 | O48: 12 unid. X caja | Q48: 3382 | R48: ET. PAI 102X78 LISA - RR | S48: =insumos!$H$135*6 -> 0.123 | T48: 6 unid. X caja | W48: peso prom. Caja | X48: 19.8 | AA48: 2120 | AB48: HOJA 90 x 90 (45 abierta) /30ø impr. - STRONG | AC48: =insumos!$H$225*4 -> 0.4 | AD48: 4 unid. X caja | AG48: Envasado | AK48: 5138 | AL48: ET. BOPP TERM. 102X78 - RR | AM48: =insumos!$H$113*6 -> 0.16205672 | AN48: 6 unid. X caja | AP48: 5523 | AQ48: TAPA VILA gris - 50x38x15.5 cm (nueva medida) - Mercopack | AR48: =+insumos!$H$285 -> 1.1829611 | AZ48: 5653 | BA48: TAPA UMi CONGELADO (136) - IMPRIMEX | BB48: =+insumos!$G$283 -> 1.1 | BE48: 6287 | BF48: TAPA 135 COFRE EL RANCHO - IMPRIMEX | BG48: =+insumos!$H$263 -> 1.6 | BO48: 5653 | BP48: TAPA UMi CONGELADO (136) - IMPRIMEX | BQ48: =+insumos!$G$283 -> 1.1 | BT48: 6265 | BU48: TAPA TAURUS BIFE ONTILCOR - MERCOPACK | BV48: =+insumos!$H$279 -> 1.25 | BY48: 5523 | BZ48: TAPA VILA gris - 50x38x15.5 cm (nueva medida) - Mercopack | CA48: =+insumos!$H$285 -> 1.1829611 | CD48: 4653 | CE48: SEPARADORES 530X290 – MERCOPACK | CF48: =insumos!$H$254*5 -> 0.93202981 | CG48: 5 unid. X caja | CI48: 5251 | CJ48: TAPA INK COFRE - IMPRIMEX | CK48: =+insumos!$H$274 -> 1.6 | CN48: 4653 | CO48: SEPARADORES 530X290 – MERCOPACK | CP48: =insumos!$H$254*2 -> 0.37281192 | CQ48: 2 unidades | CS48: 3817 | CT48: Cinta adhesiva ( metros) | CU48: =insumos!$I$103*1.8 -> 0.02088 | CV48: 1,8 metros | DH48: 2173 | DI48: Fajas | DJ48: =+insumos!$H$149*2 -> 0.034950266 | DM48: 6265 | DN48: TAPA TAURUS BIFE ONTILCOR - MERCOPACK | DO48: =+insumos!$H$279 -> 1.25
B49: 3759 | C49: TAPA VILA COFRE 156 (135)(gris) - Mpack | D49: =+insumos!$G$284 -> 1.1352417 | G49: 5138 | H49: ET. BOPP TERM. 102X78 - RR | I49: =insumos!$H$113*12 -> 0.32411345 | L49: 5138 | M49: ET. BOPP TERM. 102X78 - RR | N49: =insumos!$H$113*12 -> 0.32411345 | O49: 12 unid. X caja | R49: Total | S49: =SUM(S40:S48) -> 2.1793891 | W49: Costo x kls | X49: =+X47/X48 -> 0.12602607 | AA49: 3887 | AB49: ET. BOPP TERMICO 100x050 LISA - RR | AC49: =insumos!$H$120*4 -> 0.0796 | AD49: 4 unid. X caja | AF49: 3741 | AG49: Fondo Cofre | AH49: =insumos!$G$213 -> 0.83558719 | AK49: 6260 | AL49: BOBINA 310x450 MM IMP VILA - MERCOPACK | AM49: =insumos!$H$24*6 -> 1.326 | AN49: 6 unid. X caja | AP49: 4542 | AQ49: Bolsa 95X60 | AR49: =insumos!$I$35 -> 0.022058824 | AZ49: 4986 | BA49: SEPARADORES 570x230 mm - MERCOPACK | BB49: =insumos!$H$255*3 -> 0.56999964 | BC49: 3 unid. X caja | BE49: 4653 | BF49: SEPARADORES 530X290 – MERCOPACK | BG49: =insumos!$H$254*4 -> 0.74562384 | BH49: 4 unid. X caja | BT49: 4653 | BU49: SEPARADORES 530X290 – MERCOPACK | BV49: =insumos!$H$254*2 -> 0.37281192 | BY49: 4986 | BZ49: SEPARADORES 570x230 mm - MERCOPACK | CA49: =insumos!$H$255*3 -> 0.56999964 | CB49: 3 unid. X caja | CD49: 5315 | CE49: BOLSA COFRE 85(60)X46/ø40, impr. en rollo, ROSADA - STRONG | CF49: =insumos!$H$45 -> 0.028 | CI49: 4653 | CJ49: SEPARADORES 530X290 – MERCOPACK | CK49: =insumos!$H$254*3 -> 0.55921788 | CL49: 3 unid. X caja | CN49: 3817 | CO49: Cinta adhesiva ( metros) | CP49: =insumos!$I$103*1.8 -> 0.02088 | CQ49: 1.8 metros | CS49: 2173 | CT49: Fajas | CU49: =+insumos!$H$149*2 -> 0.034950266 | CV49: 2 unidades | DH49: 3636 | DI49: Etiqueta Caja | DJ49: =+insumos!$H$121 -> 0.0445 | DM49: 4653 | DN49: SEPARADORES 530X290 – MERCOPACK | DO49: =insumos!$H$254*3 -> 0.55921788 | DP49: 3 unid. X caja
B50: 4653 | C50: SEPARADORES 530X290 – MERCOPACK | D50: =insumos!$H$254*3 -> 0.55921788 | E50: 3 unid. X caja | H50: Total | I50: =SUM(I41:I49) -> 4.8284637 | M50: Total | N50: =SUM(N41:N49) -> 3.2141009 | R50: peso prom. Caja | S50: =70763.24/3806 -> 18.592549 | W50: porcentaje cobertura ( fallas, roturas) + 3 % | X50: =X49*1.03 -> 0.12980685 | AB50: Total | AC50: =SUM(AC41:AC49) -> 1.8519891 | AF50: 3759 | AG50: TAPA VILA COFRE 156 (135)(gris) - Mpack | AH50: =+insumos!$G$284 -> 1.1352417 | AL50: Total | AM50: =SUM(AM40:AM49) -> 3.9540866 | AP50: 3817 | AQ50: Cinta adhesiva ( metros) | AR50: =insumos!$I$103*1.8 -> 0.02088 | AS50: 1,8 metros | AZ50: 5315 | BA50: BOLSA COFRE 85(60)X46/ø40, impr. en rollo, ROSADA - STRONG | BB50: =insumos!$H$45 -> 0.028 | BE50: 6280 | BF50: BOLSA NARANJA 85(60)X46/40 - STRONG | BG50: =insumos!$H$50 -> 0.027941176 | BO50: 5315 | BP50: BOLSA COFRE 85(60)X46/ø40, impr. en rollo, ROSADA - STRONG | BQ50: =insumos!$H$45 -> 0.028 | BT50: 5353 | BU50: BOLSA COFRE 85(60)X46/ø40, impr. en rollo, AMARILLA - STRONG | BV50: =insumos!$H$44 -> 0.028 | BY50: 4542 | BZ50: Bolsa 95X60 | CA50: =insumos!$I$35 -> 0.022058824 | CD50: 3817 | CE50: Cinta adhesiva ( metros) | CF50: =insumos!$I$103*1.8 -> 0.02088 | CG50: 1.8 metros | CI50: 4541 | CJ50: Bolsa 85X60 | CK50: =insumos!$H$43 -> 0.022058824 | CN50: 4541 | CO50: Bolsa 85x60 | CP50: =insumos!$H$43 -> 0.022058824 | CS50: 3636 | CT50: Etiqueta Caja | CU50: =+insumos!$H$121 -> 0.0445 | DI50: Paquete | DM50: 5353 | DN50: BOLSA COFRE 85(60)X46/ø40, impr. en rollo, AMARILLA - STRONG | DO50: =insumos!$H$44 -> 0.028
B51: 4541 | C51: Bolsa 85x60 | D51: =insumos!$H$43 -> 0.022058824 | H51: peso prom. Caja | I51: 19.3 | M51: peso prom. Caja | N51: =3017.41/242 -> 12.468636 | R51: Costo x kls | S51: =+S49/S50 -> 0.11721842 | AB51: peso prom. Caja | AC51: =745.27/38 -> 19.612368 | AL51: peso prom. Caja | AM51: =406.17/34 -> 11.946176 | AP51: 2173 | AQ51: Fajas | AR51: =+insumos!$H$149*2 -> 0.034950266 | AS51: 2 unidades | AZ51: 3817 | BA51: Cinta adhesiva ( metros) | BB51: =insumos!$I$103*1.8 -> 0.02088 | BC51: 1,8 metros | BE51: 3817 | BF51: Cinta adhesiva ( metros) | BG51: =insumos!$I$103*1.8 -> 0.02088 | BH51: 1,8 metros | BO51: 3817 | BP51: Cinta adhesiva ( metros) | BQ51: =insumos!$I$103*1.8 -> 0.02088 | BR51: 1,8 metros | BT51: 3817 | BU51: Cinta adhesiva ( metros) | BV51: =insumos!$I$103*1.8 -> 0.02088 | BW51: 1,8 metros | BY51: 3817 | BZ51: Cinta adhesiva ( metros) | CA51: =insumos!$I$103*1.8 -> 0.02088 | CB51: 1,8 metros | CD51: 2173 | CE51: Fajas | CF51: =+insumos!$H$149*2 -> 0.034950266 | CG51: 2 unidades | CI51: 3817 | CJ51: Cinta adhesiva ( metros) | CK51: =insumos!$I$103*1.8 -> 0.02088 | CL51: 1.8 metros | CN51: 2173 | CO51: Fajas | CP51: =+insumos!$H$149*2 -> 0.034950266 | CQ51: 2 unidades | CT51: Paquete | DH51: 5138 | DI51: ET. BOPP TERM. 102X78 - RR | DJ51: =insumos!$H$113*6 -> 0.16205672 | DK51: 6 unid. X caja | DM51: 3817 | DN51: Cinta adhesiva ( metros) | DO51: =insumos!$I$103*1.8 -> 0.02088 | DP51: 1,8 metros
B52: 3817 | C52: Cinta adhesiva ( metros) | D52: =insumos!$I$103*1.8 -> 0.02088 | E52: 1,8 metros | H52: Costo x kls | I52: =+I50/I51 -> 0.25017946 | M52: Costo x kls | N52: =+N50/N51 -> 0.25777485 | R52: porcentaje cobertura ( fallas, roturas) + 3 % | S52: =S51*1.03 -> 0.12073497 | V52: 993171 | W52: Envase Entraña Interna Angus (4x paq.) | AB52: Costo x kls | AC52: =+AC50/AC51 -> 0.09442965 | AF52: 4541 | AG52: Bolsa 85X60 | AH52: =insumos!$H$43 -> 0.022058824 | AL52: Costo x kls | AM52: =+AM50/AM51 -> 0.33099181 | AP52: 3636 | AQ52: Etiqueta Caja | AR52: =+insumos!$H$121 -> 0.0445 | AZ52: 2173 | BA52: Fajas | BB52: =+insumos!$H$149*2 -> 0.034950266 | BC52: 2 unidades | BE52: 2173 | BF52: Fajas | BG52: =+insumos!$H$149*2 -> 0.034950266 | BH52: 2 unidades | BO52: 2173 | BP52: Fajas | BQ52: =+insumos!$H$149*2 -> 0.034950266 | BR52: 2 unidades | BT52: 2173 | BU52: Fajas | BV52: =+insumos!$H$149*2 -> 0.034950266 | BW52: 2 unidades | BY52: 2173 | BZ52: Fajas | CA52: =+insumos!$H$149*2 -> 0.034950266 | CB52: 2 unidades | CD52: 3636 | CE52: Etiqueta Caja | CF52: =+insumos!$H$121 -> 0.0445 | CI52: 2173 | CJ52: Fajas | CK52: =+insumos!$H$149*2 -> 0.034950266 | CL52: 2 unidades | CN52: 3636 | CO52: Etiqueta Caja | CP52: =+insumos!$H$121 -> 0.0445 | CS52: 5138 | CT52: ET. BOPP TERM. 102X78 - RR | CU52: =insumos!$H$113*15 -> 0.40514181 | CV52: 15 unid. X caja | DH52: 5250 | DI52: Et. INK OPP - 7.2X14 - IMPRIMEX | DJ52: =insumos!H167*6 -> 0.25458278 | DK52: 6 unid. X caja | DM52: 2173 | DN52: Fajas | DO52: =+insumos!$H$149*2 -> 0.034950266 | DP52: 2 unidades
B53: 2173 | C53: Fajas | D53: =+insumos!$H$149*2 -> 0.034950266 | E53: 2 unidades | H53: porcentaje cobertura ( fallas, roturas) + 3 % | I53: =I52*1.03 -> 0.25768485 | M53: porcentaje cobertura ( fallas, roturas) + 3 % | N53: =N52*1.03 -> 0.2655081 | V53: Código | W53: Insumos | X53: Precio U$S | AB53: porcentaje cobertura ( fallas, roturas) + 3 % | AC53: =AC52*1.03 -> 0.09726254 | AF53: 3817 | AG53: Cinta adhesiva ( metros) | AH53: =insumos!$I$103*1.8 -> 0.02088 | AI53: 1.8 metros | AL53: porcentaje cobertura ( fallas, roturas) + 3 % | AM53: =AM52*1.03 -> 0.34092157 | AQ53: Paquete | AZ53: 3636 | BA53: Etiqueta Caja | BB53: =+insumos!$H$121 -> 0.0445 | BE53: 3636 | BF53: Etiqueta Caja | BG53: =+insumos!$H$121 -> 0.0445 | BO53: 3636 | BP53: Etiqueta Caja | BQ53: =+insumos!$H$121 -> 0.0445 | BT53: 3636 | BU53: Etiqueta Caja | BV53: =+insumos!$H$121 -> 0.0445 | BY53: 3636 | BZ53: Etiqueta Caja | CA53: =+insumos!$H$121 -> 0.0445 | CE53: Paquete | CI53: 3636 | CJ53: Etiqueta Caja | CK53: =+insumos!$H$121 -> 0.0445 | CO53: Paquete | CS53: 6229 | CT53: TAPA BARRERA NEGRA 250 C (FILM PARA TERMOFORMADORA) - MULTIPACK DIAMALER | CU53: =insumos!$I$265*15 -> 0.322819 | CV53: 15 unid. X caja | DH53: 6297 | DI53: BOLSA PARA VACIO 18X45 | DJ53: =insumos!$H$53*6 -> 0.936 | DK53: 6 unid. X caja | DM53: 3636 | DN53: Etiqueta Caja | DO53: =+insumos!$H$121 -> 0.0445
B54: 3636 | C54: Etiqueta Caja | D54: =+insumos!$H$121 -> 0.0445 | Q54: 998012 | R54: Envase Carnaza de Paleta | W54: Envasado | AF54: 2173 | AG54: Fajas | AH54: =+insumos!$H$149*2 -> 0.034950266 | AI54: 2 unidades | AP54: 4651 | AQ54: BOLSA VACIO HP15- p/carne c/ hueso 40x80/ø120 - MERCOPACK | AR54: =insumos!$H$88*2 -> 1.978 | AS54: 2 unid. X caja | BA54: Paquete | BF54: Paquete | BP54: Paquete | BU54: Paquete | BZ54: Paquete | CD54: 5138 | CE54: ET. BOPP TERM. 102X78 - RR | CF54: =insumos!$H$113*10 -> 0.27009454 | CG54: 10 unid. X caja | CJ54: Paquete | CN54: 5138 | CO54: ET. BOPP TERM. 102X78 - RR | CP54: =insumos!$H$113*6 -> 0.16205672 | CQ54: 6 unid. X caja | CS54: 6254 | CT54: FONDO BARRERA TERMOFORMADORA TR NI 180 - MULTIPACK DIAMALER | CU54: =+insumos!$I$208*15 -> 0.66686175 | CV54: 15 unid. X caja | DI54: Total | DJ54: =SUM(DJ43:DJ53) -> 4.2906155 | DN54: Paquete
C55: Paquete | G55: 437030 | H55: Envase Lomo S/Cordon 3-4lb | L55: 436070 | M55: Envase Entraña Fina (2x Paq.) | Q55: Código | R55: Insumos | S55: Precio U$S | V55: 6184 | W55: Fondo Congelado | X55: =insumos!$H$215 -> 0.6 | AA55: 991026 | AB55: Envase Cuadrada | AF55: 3636 | AG55: Etiqueta Caja | AH55: =+insumos!$H$121 -> 0.0445 | AK55: 1987139 | AL55: Envase Falda S/h Vila | AP55: 5138 | AQ55: ET. BOPP TERM. 102X78 - RR | AR55: =insumos!$H$113*2 -> 0.054018908 | AS55: 2 unid. X caja | AZ55: 4102 | BA55: Etiqueta Trasera 100x100 | BB55: =insumos!$H$115*12 -> 0.396 | BC55: 12 unid. X caja | BE55: 5138 | BF55: ET. BOPP TERM. 102X78 - RR | BG55: =insumos!$H$113*20 -> 0.54018908 | BH55: 20 unid. X caja | BO55: 4102 | BP55: Etiqueta Trasera 100x100 | BQ55: =insumos!$H$115*12 -> 0.396 | BR55: 12 unid. X caja | BT55: 5138 | BU55: ET. BOPP TERM. 102X78 - RR | BV55: =insumos!$H$113*5 -> 0.13504727 | BW55: 5 unid. X caja | BY55: 6208 | BZ55: Etiqueta delantera | CA55: =insumos!$H$188*12 -> 1.0929882 | CB55: 12 unid. X caja | CI55: 5138 | CJ55: ET. BOPP TERM. 102X78 - RR | CK55: =insumos!$H$113*12 -> 0.32411345 | CL55: 12 unid. X caja | CN55: 6260 | CO55: BOBINA 310x450 MM IMP VILA - MERCOPACK | CP55: =insumos!$H$24*6 -> 1.326 | CQ55: 6 unid. X caja | CS55: 6138 | CT55: FAJAS UMI - 8x19.5cm - IMPRIMEX | CU55: =insumos!$H$197*15 -> 2.1811765 | CV55: 15 unid. X caja | DI55: peso prom. Caja | DJ55: 14.4
B56: 6252 | C56: Etiqueta delantera | D56: =insumos!H153*8 -> 0.784 | E56: 8 unid. X caja | G56: Código | H56: Insumos | I56: Precio U$S | L56: Código | M56: Insumos | N56: Precio U$S | R56: Envasado | V56: 2037 | W56: Tapa blanca congelado | X56: =+insumos!$H$268 -> 0.65 | AA56: Código | AB56: Insumos | AC56: Precio U$S | AG56: Paquete | AK56: Código | AL56: Insumos | AM56: Precio U$S | AQ56: Total | AR56: =SUM(AR47:AR55) -> 4.2323691 | AZ56: 6229 | BA56: TAPA BARRERA NEGRA 250 C (FILM PARA TERMOFORMADORA) - MULTIPACK DIAMALER | BB56: =insumos!$I$265*12 -> 0.2582552 | BC56: 12 unid. X caja | BE56: 6229 | BF56: TAPA BARRERA NEGRA 250 C (FILM PARA TERMOFORMADORA) - MULTIPACK DIAMALER | BG56: =insumos!$I$265*20 -> 0.43042533 | BH56: 20 unid. X caja | BO56: 5403 | BP56: BOLSA VACIO 31X45 UMI - MERCOPACK | BQ56: =insumos!$H$80*12 -> 2.652 | BR56: 12 unid. X caja | BT56: 4973 | BU56: BOLSA VACIO 31X40 impr. TAURUS GOLD - MERCOPACK | BV56: =insumos!$H$79*5 -> 1.07 | BW56: 5 unid. X caja | BY56: 5202 | BZ56: Etiqueta Trasera | CA56: =insumos!$H$114*12 -> 0.31613714 | CB56: 12 unid. X caja | CD56: 6229 | CE56: TAPA BARRERA NEGRA 250 C (FILM PARA TERMOFORMADORA) - MULTIPACK DIAMALER | CF56: =insumos!$I$265*12 -> 0.2582552 | CG56: 12 unid. X caja | CI56: 6229 | CJ56: TAPA BARRERA NEGRA 250 C (FILM PARA TERMOFORMADORA) - MULTIPACK DIAMALER | CK56: =insumos!$I$265*12 -> 0.2582552 | CL56: 12 unid. X caja | CN56: 6209 | CO56: ETIQUETAS BOPP MET.DOBLE CAPA 100X095 LAM. MATE VILA - ASADO 5 COSTILLAS CONGELADO - RR | CP56: =insumos!$H$189*6 -> 0.48130909 | CQ56: 6 unid. X caja | CT56: Total | CU56: =SUM(CU44:CU55) -> 6.399916 | DI56: Costo x kls | DJ56: =+DJ54/DJ55 -> 0.29795941 | DM56: 6229 | DN56: TAPA BARRERA NEGRA 250 C (FILM PARA TERMOFORMADORA) - MULTIPACK DIAMALER | DO56: =insumos!$I$265*12 -> 0.2582552 | DP56: 12 unid. X caja
B57: 5202 | C57: Etiqueta Trasera | D57: =insumos!$H$114*8 -> 0.2107581 | E57: 8 unid. X caja | H57: Envasado | M57: Envasado | Q57: 6184 | R57: Fondo Congelado | S57: =insumos!$H$215 -> 0.6 | V57: 4542 | W57: Bolsa 95X60 | X57: =insumos!$I$35 -> 0.022058824 | AB57: Envasado | AF57: 6222 | AG57: ETIQUETA BOPP MET.DOBLE CAPA 084X081 LAM.MATE VILA- BOCHECHA -RR | AH57: =insumos!$H$162*10 -> 0.87259259 | AI57: 10 unid. X caja | AL57: Envasado | AQ57: peso prom. Caja | AR57: 14.4 | AZ57: 6254 | BA57: FONDO BARRERA TERMOFORMADORA TR NI 180 - MULTIPACK DIAMALER | BB57: =+insumos!$I$208*12 -> 0.5334894 | BC57: 12 unid. X caja | BE57: 6254 | BF57: FONDO BARRERA TERMOFORMADORA TR NI 180 - MULTIPACK DIAMALER | BG57: =+insumos!$I$208*20 -> 0.889149 | BH57: 20 unid. X caja | BY57: 6229 | BZ57: TAPA BARRERA NEGRA 250 C (FILM PARA TERMOFORMADORA) - MULTIPACK DIAMALER | CA57: =insumos!$I$265*12 -> 0.2582552 | CB57: 12 unid. X caja | CD57: 6254 | CE57: FONDO BARRERA TERMOFORMADORA TR NI 180 - MULTIPACK DIAMALER | CF57: =+insumos!$I$208*12 -> 0.5334894 | CG57: 12 unid. X caja | CI57: 6254 | CJ57: FONDO BARRERA TERMOFORMADORA TR NI 180 - MULTIPACK DIAMALER | CK57: =+insumos!$I$208*12 -> 0.5334894 | CL57: 12 unid. X caja | CN57: 5202 | CO57: Etiqueta Trasera | CP57: =insumos!$H$114*6 -> 0.15806857 | CQ57: 6 unid. X caja | CT57: peso prom. Caja | CU57: =214.82/39 -> 5.5082051 | DI57: porcentaje cobertura ( fallas, roturas) + 3 % | DJ57: =DJ56*1.03 -> 0.30689819 | DM57: 6254 | DN57: FONDO BARRERA TERMOFORMADORA TR NI 180 - MULTIPACK DIAMALER | DO57: =+insumos!$I$208*12 -> 0.5334894 | DP57: 12 unid. X caja
B58: 6229 | C58: TAPA BARRERA NEGRA 250 C (FILM PARA TERMOFORMADORA) - MULTIPACK DIAMALER | D58: =insumos!$I$265*8 -> 0.17217013 | E58: 8 unid. X caja | G58: 5524 | H58: FONDO ENFRIADO (nueva medida) 505x380x155 cm - MERCOPACK | I58: =insumos!$H$217 -> 0.895 | L58: 5524 | M58: FONDO ENFRIADO (nueva medida) 505x380x155 cm - MERCOPACK | N58: =insumos!$H$217 -> 0.895 | Q58: 2037 | R58: Tapa blanca congelado | S58: =+insumos!$H$268 -> 0.65 | V58: 3817 | W58: Cinta adhesiva ( metros) | X58: =insumos!$I$103*1.8 -> 0.02088 | Y58: 1.8 metros | AA58: 6184 | AB58: Fondo Congelado | AC58: =insumos!$H$215 -> 0.6 | AF58: 5138 | AG58: Etiqueta 102x78 Bopp Term | AH58: =insumos!H113*10 -> 0.27009454 | AI58: 10 unid. X caja | AK58: 5524 | AL58: Fondo enfriado (nueva medida) 505x380x155 cm – MERCOPACK | AM58: =insumos!$H$217 -> 0.895 | AQ58: Costo x kls | AR58: =+AR56/AR57 -> 0.29391452 | AZ58: 6138 | BA58: FAJAS UMI - 8x19.5cm - IMPRIMEX | BB58: =insumos!$H$197*12 -> 1.7449412 | BC58: 12 unid. X caja | BE58: 6288 | BF58: ETIQUETAS BOPP MET. ADC 6000 60X110 LAMINADO MATE - EL RANCHO PASSION - RR | BG58: =insumos!$H$176*20 -> 1.08 | BH58: 20 unid. X caja | BY58: 6254 | BZ58: FONDO BARRERA TERMOFORMADORA TR NI 180 - MULTIPACK DIAMALER | CA58: =+insumos!$I$208*12 -> 0.5334894 | CB58: 12 unid. X caja | CE58: Total | CF58: =SUM(CF46:CF57) -> 4.0577864 | CI58: 6142 | CJ58: Faja iNK - 8x19.5 - IMPRIMEX | CK58: =insumos!$H$194*12 -> 2.4 | CL58: 12 unid. X caja | CO58: Total | CP58: =SUM(CP46:CP57) -> 4.5934642 | CT58: Costo x kls | CU58: =+CU56/CU57 -> 1.1618877 | DM58: 5868 | DN58: PADS BLANCOS 4.5" x 7" - TITE DRI | DO58: =insumos!$I$243*12 -> 0.22752 | DP58: 12 unid. X caja
B59: 6254 | C59: FONDO BARRERA TERMOFORMADORA TR NI 180 - MULTIPACK DIAMALER | D59: =+insumos!$I$208*8 -> 0.3556596 | E59: 8 unid. X caja | G59: 5523 | H59: TAPA VILA gris - 50x38x15.5 cm (nueva medida) - Mercopack | I59: =+insumos!$H$285 -> 1.1829611 | L59: 2055 | M59: TAPA BLANCA 136 (cartulina)- Mpack | N59: =+insumos!$H$266 -> 1.15 | Q59: 4542 | R59: Bolsa 95X60 | S59: =insumos!$I$35 -> 0.022058824 | V59: 2173 | W59: Fajas | X59: =+insumos!$H$149*2 -> 0.034950266 | Y59: 2 unidades | AA59: 2037 | AB59: Tapa blanca congelado | AC59: =+insumos!$H$268 -> 0.65 | AF59: 6258 | AG59: MP15 BAG 200X300 MM IMP PLENO NEGRO ONTILCOR - MERCOPACK | AH59: =insumos!$H$241*10 -> 1.85 | AI59: 10 unid. X caja | AK59: 5523 | AL59: TAPA VILA gris - 50x38x15.5 cm (nueva medida) - Mercopack | AM59: =+insumos!$H$285 -> 1.1829611 | AQ59: porcentaje cobertura ( fallas, roturas) + 3 % | AR59: =AR58*1.03 -> 0.30273196 | BA59: Total | BB59: =SUM(BB47:BB58) -> 5.5666029 | BF59: Total | BG59: =SUM(BG47:BG58) -> 6.2492459 | BP59: Total | BQ59: =SUM(BQ47:BQ58) -> 5.1119175 | BU59: Total | BV59: =SUM(BV47:BV58) -> 3.7917766 | BY59: 5868 | BZ59: PADS BLANCOS 4.5" x 7" - TITE DRI | CA59: =insumos!$I$243*12 -> 0.22752 | CB59: 12 unid. X caja | CE59: peso prom. Caja | CF59: =941.37/101 -> 9.320495 | CJ59: Total | CK59: =SUM(CK47:CK58) -> 6.6330522 | CO59: peso prom. Caja | CP59: =747.23/56 -> 13.343393 | CT59: porcentaje cobertura ( fallas, roturas) + 3 % | CU59: =CU58*1.03 -> 1.1967444 | DH59: 5516660 | DI59: Envase Asado s/h 3c INK | DN59: Total | DO59: =SUM(DO47:DO58) -> 3.7923999
B60: 5868 | C60: PADS BLANCOS 4.5" x 7" - TITE DRI | D60: =insumos!$I$243*8 -> 0.15168 | E60: 8 unid. X caja | G60: 4542 | H60: Bolsa 95X60 | I60: =insumos!$I$35 -> 0.022058824 | L60: 4542 | M60: Bolsa 95X60 | N60: =insumos!$I$35 -> 0.022058824 | Q60: 3817 | R60: Cinta adhesiva ( metros) | S60: =insumos!$I$103*1.8 -> 0.02088 | T60: 1.8 metros | V60: 3636 | W60: Etiqueta Caja | X60: =+insumos!$H$121 -> 0.0445 | AA60: 4542 | AB60: Bolsa 95X60 | AC60: =insumos!$I$35 -> 0.022058824 | AG60: Total | AH60: =SUM(AH49:AH59) -> 5.0859051 | AK60: 4542 | AL60: Bolsa 95X60 | AM60: =insumos!$I$35 -> 0.022058824 | BA60: peso prom. Caja | BB60: =1225.36/236 -> 5.1922034 | BF60: peso prom. Caja | BG60: =4080.73/363 -> 11.24168 | BP60: peso prom. Caja | BQ60: =276.05/23 -> 12.002174 | BU60: peso prom. Caja | BV60: =24984.64/2175 -> 11.487191 | BZ60: Total | CA60: =SUM(CA47:CA59) -> 5.1987398 | CE60: Costo x kls | CF60: =+CF58/CF59 -> 0.43536168 | CJ60: peso prom. Caja | CK60: 5.65 | CO60: Costo x kls | CP60: =+CP58/CP59 -> 0.34425009 | DH60: Código | DI60: Insumos | DJ60: Precio U$S | DN60: peso prom. Caja | DO60: 7.35
C61: Total | D61: =SUM(D48:D60) -> 4.3267037 | G61: 3817 | H61: Cinta adhesiva ( metros) | I61: =insumos!$I$103*1.8 -> 0.02088 | J61: 1,8 metros | L61: 3817 | M61: Cinta adhesiva ( metros) | N61: =insumos!$I$103*1.8 -> 0.02088 | O61: 1,8 metros | Q61: 2173 | R61: Fajas | S61: =+insumos!$H$149*2 -> 0.034950266 | T61: 2 unidades | W61: Paquete | AA61: 3817 | AB61: Cinta adhesiva ( metros) | AC61: =insumos!$I$103*1.8 -> 0.02088 | AD61: 1.8 metros | AG61: peso prom. Caja | AH61: 15.93 | AK61: 3817 | AL61: Cinta adhesiva ( metros) | AM61: =insumos!$I$103*1.8 -> 0.02088 | AN61: 1.8 metros | AP61: 3673199 | AQ61: Envase Molleja EL ROSADO | BA61: Costo x kls | BB61: =+BB59/BB60 -> 1.072108 | BF61: Costo x kls | BG61: =+BG59/BG60 -> 0.55589962 | BP61: Costo x kls | BQ61: =+BQ59/BQ60 -> 0.42591596 | BU61: Costo x kls | BV61: =+BV59/BV60 -> 0.33008737 | BZ61: peso prom. Caja | CA61: =2990.37/204 -> 14.658676 | CE61: porcentaje cobertura ( fallas, roturas) + 3 % | CF61: =CF60*1.03 -> 0.44842253 | CJ61: Costo x kls | CK61: =+CK59/CK60 -> 1.1739915 | CO61: porcentaje cobertura ( fallas, roturas) + 3 % | CP61: =CP60*1.03 -> 0.3545776 | CS61: 6172005 | CT61: Envase Hueso | DI61: Envasado | DN61: Costo x kls | DO61: =+DO59/DO60 -> 0.51597278
C62: peso prom. Caja | D62: 8 | G62: 2173 | H62: Fajas | I62: =+insumos!$H$149*2 -> 0.034950266 | J62: 2 unidades | L62: 2173 | M62: Fajas | N62: =+insumos!$H$149*2 -> 0.034950266 | O62: 2 unidades | Q62: 3636 | R62: Etiqueta Caja | S62: =+insumos!$H$121 -> 0.0445 | V62: 4745 | W62: Bolsa 31x40 | X62: =insumos!$H$93*6 -> 0.684 | Y62: 6 unid. X caja | AA62: 2173 | AB62: Fajas | AC62: =+insumos!$H$149*2 -> 0.034950266 | AD62: 2 unidades | AG62: Costo x kls | AH62: =+AH60/AH61 -> 0.31926586 | AK62: 2173 | AL62: Fajas | AM62: =+insumos!$H$149*2 -> 0.034950266 | AN62: 2 unidades | AP62: Código | AQ62: Insumos | AR62: Precio U$S | BA62: porcentaje cobertura ( fallas, roturas) + 3 % | BB62: =BB61*1.03 -> 1.1042713 | BF62: porcentaje cobertura ( fallas, roturas) + 3 % | BG62: =BG61*1.03 -> 0.57257661 | BP62: porcentaje cobertura ( fallas, roturas) + 3 % | BQ62: =BQ61*1.03 -> 0.43869344 | BU62: porcentaje cobertura ( fallas, roturas) + 3 % | BV62: =BV61*1.03 -> 0.33999 | BZ62: Costo x kls | CA62: =+CA60/CA61 -> 0.35465274 | CJ62: porcentaje cobertura ( fallas, roturas) + 3 % | CK62: =CK61*1.03 -> 1.2092113 | CS62: Código | CT62: Insumos | CU62: Precio U$S | DH62: 3741 | DI62: Fondo Cofre | DJ62: =insumos!$G$213 -> 0.83558719 | DN62: porcentaje cobertura ( fallas, roturas) + 3 % | DO62: =DO61*1.03 -> 0.53145196
C63: Costo x kls | D63: =+D61/D62 -> 0.54083796 | G63: 3636 | H63: Etiqueta Caja | I63: =+insumos!$H$121 -> 0.0445 | L63: 3636 | M63: Etiqueta Caja | N63: =+insumos!$H$121 -> 0.0445 | R63: Paquete | W63: Total | X63: =SUM(X55:X62) -> 2.0563891 | AA63: 3636 | AB63: Etiqueta Caja | AC63: =+insumos!$H$121 -> 0.0445 | AG63: porcentaje cobertura ( fallas, roturas) + 3 % | AH63: =AH62*1.03 -> 0.32884383 | AK63: 3636 | AL63: Etiqueta Caja | AM63: =+insumos!$H$121 -> 0.0445 | AQ63: Envasado | BZ63: porcentaje cobertura ( fallas, roturas) + 3 % | CA63: =CA62*1.03 -> 0.36529233 | CD63: 4545006 | CE63: Envasado Aguja (denver) UMI | CN63: 4865160 | CO63: Envase Asado 1/C Vila Brasil | CT63: Envasado | DH63: 5251 | DI63: TAPA INK COFRE - IMPRIMEX | DJ63: =+insumos!$H$274 -> 1.6
C64: porcentaje cobertura ( fallas, roturas) + 3 % | D64: =D63*1.03 -> 0.55706309 | H64: Paquete | M64: Paquete | R64: FALTA QUE INGRESEN ORDEN DE COMPRA (25x45) | W64: peso prom. Caja | X64: 21.5 | AB64: Paquete | AL64: Paquete | AP64: 3741 | AQ64: Fondo Cofre | AR64: =insumos!$G$213 -> 0.83558719 | AZ64: 441070 | BA64: Envasado Entraña | BE64: 442832 | BF64: Envasado Vacio EL RANCHO | BO64: 3516139 | BP64: Envasado Falda s/h UMI | CD64: Código | CE64: Insumos | CF64: Precio U$S | CI64: 4546070 | CJ64: Envasado Entraña INK | CN64: Código | CO64: Insumos | CP64: Precio U$S | CS64: 6184 | CT64: Fondo Congelado | CU64: =insumos!$H$215 -> 0.6 | DH64: 4986 | DI64: SEPARADORES 570x230 mm - MERCOPACK | DJ64: =insumos!$H$255*2 -> 0.37999976 | DK64: 1 unid. X caja | DM64: 1993931 | DN64: Envasado Bife Angosto TG Porcionado
G65: 6292 | H65: BOLSA PARA VACIO 18X67 IMP VILA - MERCOPACK | I65: =insumos!$H$54*12 -> 2.652 | J65: 12 unid. X caja | L65: 4741 | M65: Bolsa 20x50 | N65: =insumos!$H$90*25 -> 7.7 | O65: 25 unid. X caja | R65: Total | S65: =SUM(S57:S64) -> 1.3723891 | W65: Costo x kls | X65: =+X63/X64 -> 0.095646004 | AA65: 2119 | AB65: HOJA 70 x 70 /30ø impr. - STRONG | AC65: =insumos!$H$224*5 -> 0.5 | AD65: 5 unid. X caja | AK65: 5138 | AL65: ET. BOPP TERM. 102X78 - RR | AM65: =insumos!$H$113*3 -> 0.081028362 | AN65: 3 unid. X caja | AP65: 3759 | AQ65: TAPA VILA COFRE 156 (135)(gris) - Mpack | AR65: =+insumos!$G$284 -> 1.1352417 | AZ65: Código | BA65: Insumos | BB65: Precio U$S | BE65: Código | BF65: Insumos | BG65: Precio U$S | BO65: Código | BP65: Insumos | BQ65: Precio U$S | BY65: 4543011 | BZ65: Envasado Aguja Vila - Acem | CE65: Envasado | CI65: Código | CJ65: Insumos | CK65: Precio U$S | CO65: Envasado | CS65: 5523 | CT65: TAPA VILA gris - 50x38x15.5 cm (nueva medida) - Mercopack | CU65: =+insumos!$H$285 -> 1.1829611 | DH65: 4541 | DI65: Bolsa 85x60 | DJ65: =insumos!$H$43 -> 0.022058824 | DK65: 1.8 metros | DM65: Código | DN65: Insumos | DO65: Precio U$S
B66: 439024 | C66: Envase Colita de Cuadril | D66: 590 | E66: =D66/E2 -> 14.654744 | G66: 5138 | H66: ET. BOPP TERM. 102X78 - RR | I66: =insumos!$H$113*12 -> 0.32411345 | J66: 12 unid. X caja | L66: 5138 | M66: ET. BOPP TERM. 102X78 - RR | N66: =insumos!$H$113*25 -> 0.67523635 | O66: 25 unid. X caja | R66: peso prom. Caja | S66: =11124.76/613 -> 18.148059 | W66: porcentaje cobertura ( fallas, roturas) + 3 % | X66: =X65*1.03 -> 0.098515384 | AA66: 3887 | AB66: ET. BOPP TERMICO 100x050 LISA - RR | AC66: =insumos!$H$120*5 -> 0.0995 | AD66: 5 unid. X caja | AK66: 5454 | AL66: BOLSA VACIO 31x 65, impr.- MERCOPACK | AM66: =insumos!H77*3 -> 0.957001 | AN66: 3 unid. X caja | AP66: 4653 | AQ66: SEPARADORES 530X290 – MERCOPACK | AR66: =insumos!$H$254*3 -> 0.55921788 | AS66: 3 unid. X caja | BA66: Envasado | BF66: Envasado | BP66: Envasado | BY66: Código | BZ66: Insumos | CA66: Precio U$S | CD66: 3741 | CE66: Fondo Cofre | CF66: =insumos!$G$213 -> 0.83558719 | CJ66: Envasado | CN66: 3741 | CO66: Fondo Cofre | CP66: =insumos!$G$213 -> 0.83558719 | CS66: 4542 | CT66: Bolsa 95X60 | CU66: =insumos!$I$35 -> 0.022058824 | DH66: 3817 | DI66: Cinta adhesiva ( metros) | DJ66: =insumos!$I$103*1.8 -> 0.02088 | DK66: 2 unidades | DN66: Envasado
B67: Código | C67: Insumos | D67: Precio U$S | H67: Total | I67: =SUM(I58:I66) -> 5.1764637 | M67: Total | N67: =SUM(N58:N66) -> 10.542625 | R67: Costo x kls | S67: =+S65/S66 -> 0.075621812 | AB67: Total | AC67: =SUM(AC58:AC66) -> 1.9718891 | AL67: Total | AM67: =SUM(AM58:AM66) -> 3.2383796 | AP67: 4541 | AQ67: Bolsa 85X60 | AR67: =insumos!$H$43 -> 0.022058824 | AZ67: 3741 | BA67: Fondo Cofre | BB67: =insumos!$G$213 -> 0.83558719 | BE67: 3741 | BF67: Fondo Cofre | BG67: =insumos!$G$213 -> 0.83558719 | BO67: 6184 | BP67: Fondo Congelado | BQ67: =insumos!$H$215 -> 0.6 | BZ67: Envasado | CD67: 5653 | CE67: TAPA UMi CONGELADO (136) - IMPRIMEX | CF67: =+insumos!$G$283 -> 1.1 | CI67: 3741 | CJ67: Fondo Cofre | CK67: =insumos!$G$213 -> 0.83558719 | CN67: 3759 | CO67: TAPA VILA COFRE 156 (135)(gris) - Mpack | CP67: =+insumos!$G$284 -> 1.1352417 | CS67: 4986 | CT67: SEPARADORES 570x230 mm - MERCOPACK | CU67: =insumos!$H$255*4 -> 0.75999952 | CV67: 4 unid. X caja | DH67: 2173 | DI67: Fajas | DJ67: =+insumos!$H$149*2 -> 0.034950266 | DM67: 3741 | DN67: Fondo Cofre | DO67: =insumos!$G$213 -> 0.83558719
C68: Envasado | H68: peso prom. Caja | I68: 18 | M68: peso prom. Caja | N68: =1728.45/86 -> 20.098256 | R68: porcentaje cobertura ( fallas, roturas) + 3 % | S68: =S67*1.03 -> 0.077890467 | V68: 993133 | W68: Envase Bife de Vacio (interfoleado) | AB68: peso prom. Caja | AC68: =13191.03/635 -> 20.773276 | AL68: peso prom. Caja | AM68: =65733.97/3677 -> 17.877066 | AP68: 3817 | AQ68: Cinta adhesiva ( metros) | AR68: =insumos!$I$103*1.8 -> 0.02088 | AS68: 1.8 metros | AZ68: 5653 | BA68: TAPA UMi CONGELADO (136) - IMPRIMEX | BB68: =+insumos!$G$283 -> 1.1 | BE68: 6287 | BF68: TAPA 135 COFRE EL RANCHO - IMPRIMEX | BG68: =+insumos!$H$263 -> 1.6 | BO68: 5653 | BP68: TAPA UMi CONGELADO (136) - IMPRIMEX | BQ68: =+insumos!$G$283 -> 1.1 | BY68: 5524 | BZ68: FONDO ENFRIADO (nueva medida) 505x380x155 cm - MERCOPACK | CA68: =insumos!$H$217 -> 0.895 | CD68: 4986 | CE68: SEPARADORES 570x230 mm - MERCOPACK | CF68: =insumos!$H$255*3 -> 0.56999964 | CG68: 3 unid. X caja | CI68: 5251 | CJ68: TAPA INK COFRE - IMPRIMEX | CK68: =+insumos!$H$274 -> 1.6 | CN68: 4653 | CO68: SEPARADORES 530X290 – MERCOPACK | CP68: =insumos!$H$254 -> 0.18640596 | CS68: 3817 | CT68: Cinta adhesiva ( metros) | CU68: =insumos!$I$103*1.8 -> 0.02088 | CV68: 1.8 metros | DH68: 3636 | DI68: Etiqueta Caja | DJ68: =+insumos!$H$121 -> 0.0445 | DM68: 6265 | DN68: TAPA TAURUS BIFE ONTILCOR - MERCOPACK | DO68: =+insumos!$H$279 -> 1.25
B69: 3741 | C69: Fondo Cofre | D69: =insumos!$G$213 -> 0.83558719 | H69: Costo x kls | I69: =+I67/I68 -> 0.28758131 | M69: Costo x kls | N69: =+N67/N68 -> 0.52455425 | V69: Código | W69: Insumos | X69: Precio U$S | AB69: Costo x kls | AC69: =+AC67/AC68 -> 0.094924321 | AL69: Costo x kls | AM69: =+AM67/AM68 -> 0.18114716 | AP69: 2173 | AQ69: Fajas | AR69: =+insumos!$H$149*2 -> 0.034950266 | AS69: 2 unidades | AZ69: 4986 | BA69: SEPARADORES 570x230 mm - MERCOPACK | BB69: =insumos!$H$255*2 -> 0.37999976 | BC69: 2 unid. X caja | BE69: 4653 | BF69: SEPARADORES 530X290 – MERCOPACK | BG69: =insumos!$H$254*2 -> 0.37281192 | BH69: 2 unid. X caja | BO69: 4653 | BP69: SEPARADORES 530X290 – MERCOPACK | BQ69: =insumos!$H$254 -> 0.18640596 | BY69: 5523 | BZ69: TAPA VILA gris - 50x38x15.5 cm (nueva medida) - Mercopack | CA69: =+insumos!$H$285 -> 1.1829611 | CD69: 5315 | CE69: BOLSA COFRE 85(60)X46/ø40, impr. en rollo, ROSADA - STRONG | CF69: =insumos!$H$45 -> 0.028 | CI69: 4653 | CJ69: SEPARADORES 530X290 – MERCOPACK | CK69: =insumos!$H$254*3 -> 0.55921788 | CL69: 3 unid. X caja | CN69: 4541 | CO69: Bolsa 85X60 | CP69: =insumos!$H$43 -> 0.022058824 | CS69: 2173 | CT69: Fajas | CU69: =+insumos!$H$149*2 -> 0.034950266 | CV69: 2 unidades | DI69: Paquete | DM69: 4653 | DN69: SEPARADORES 530X290 – MERCOPACK | DO69: =insumos!$H$254*3 -> 0.55921788 | DP69: 3 unid. X caja
B70: 3759 | C70: TAPA VILA gris - 50x38x15.5 cm (nueva medida) - Mercopack | D70: =+insumos!$G$284 -> 1.1352417 | H70: porcentaje cobertura ( fallas, roturas) + 3 % | I70: =I69*1.03 -> 0.29620875 | M70: porcentaje cobertura ( fallas, roturas) + 3 % | N70: =N69*1.03 -> 0.54029087 | Q70: 998014 | R70: Envase Chingolo | W70: Envasado | AB70: porcentaje cobertura ( fallas, roturas) + 3 % | AC70: =AC69*1.03 -> 0.097772051 | AL70: porcentaje cobertura ( fallas, roturas) + 3 % | AM70: =AM69*1.03 -> 0.18658157 | AP70: 3636 | AQ70: Etiqueta Caja | AR70: =+insumos!$H$121 -> 0.0445 | AZ70: 5315 | BA70: BOLSA COFRE 85(60)X46/ø40, impr. en rollo, ROSADA - STRONG | BB70: =insumos!$H$45 -> 0.028 | BE70: 6280 | BF70: BOLSA NARANJA 85(60)X46/40 - STRONG | BG70: =insumos!$H$50 -> 0.027941176 | BO70: 5315 | BP70: BOLSA COFRE 85(60)X46/ø40, impr. en rollo, ROSADA - STRONG | BQ70: =insumos!$H$45 -> 0.028 | BY70: 4986 | BZ70: SEPARADORES 570x230 mm - MERCOPACK | CA70: =insumos!$H$255*3 -> 0.56999964 | CB70: 3 unid. X caja | CD70: 3817 | CE70: Cinta adhesiva ( metros) | CF70: =insumos!$I$103*1.8 -> 0.02088 | CG70: 1,8 metros | CI70: 4541 | CJ70: Bolsa 85X60 | CK70: =insumos!$H$43 -> 0.022058824 | CN70: 3817 | CO70: Cinta adhesiva ( metros) | CP70: =insumos!$I$103*1.8 -> 0.02088 | CQ70: 1.8 metros | CS70: 3636 | CT70: Etiqueta Caja | CU70: =+insumos!$H$121 -> 0.0445 | DH70: 5138 | DI70: ET. BOPP TERM. 102X78 - RR | DJ70: =insumos!$H$113*4 -> 0.10803782 | DK70: 4 unid. X caja | DM70: 5353 | DN70: BOLSA COFRE 85(60)X46/ø40, impr. en rollo, AMARILLA - STRONG | DO70: =insumos!$H$44 -> 0.028
B71: 4653 | C71: SEPARADORES 530X290 – MERCOPACK | D71: =insumos!$H$254*3 -> 0.55921788 | E71: 3 unid. X caja | Q71: Código | R71: Insumos | S71: Precio U$S | V71: 6184 | W71: Fondo Congelado | X71: =insumos!$H$215 -> 0.6 | AQ71: Paquete | AZ71: 3817 | BA71: Cinta adhesiva ( metros) | BB71: =insumos!$I$103*1.8 -> 0.02088 | BC71: 1,8 metros | BE71: 3817 | BF71: Cinta adhesiva ( metros) | BG71: =insumos!$I$103*1.8 -> 0.02088 | BH71: 1,8 metros | BO71: 3817 | BP71: Cinta adhesiva ( metros) | BQ71: =insumos!$I$103*1.8 -> 0.02088 | BR71: 1,8 metros | BY71: 4542 | BZ71: Bolsa 95X60 | CA71: =insumos!$I$35 -> 0.022058824 | CD71: 2173 | CE71: Fajas | CF71: =+insumos!$H$149*2 -> 0.034950266 | CG71: 2 unidades | CI71: 3817 | CJ71: Cinta adhesiva ( metros) | CK71: =insumos!$I$103*1.8 -> 0.02088 | CL71: 1.8 metros | CN71: 2173 | CO71: Fajas | CP71: =+insumos!$H$149*2 -> 0.034950266 | CQ71: 2 unidades | CT71: Paquete | DH71: 5250 | DI71: Et. INK OPP - 7.2X14 - IMPRIMEX | DJ71: =insumos!H186*4 -> 0.36691056 | DK71: 4 unid. X caja | DM71: 3817 | DN71: Cinta adhesiva ( metros) | DO71: =insumos!$I$103*1.8 -> 0.02088 | DP71: 1,8 metros
B72: 4541 | C72: Bolsa 85X60 | D72: =insumos!$H$43 -> 0.022058824 | G72: 437031 | H72: Envase Bife Angosto | I72: 815 | J72: =I72/E2 -> 20.243418 | L72: 436123 | M72: Envase Nalga S/T Feteada 6mm | N72: 420 | O72: =N72/E2 -> 10.432191 | R72: Envasado | V72: 2037 | W72: Tapa blanca congelado | X72: =+insumos!$H$268 -> 0.65 | AA72: 991028 | AB72: Envase Peceto | AK72: 1987193 | AL72: Envase Intercostales Largos Vila | AZ72: 2173 | BA72: Fajas | BB72: =+insumos!$H$149*2 -> 0.034950266 | BC72: 2 unidades | BE72: 2173 | BF72: Fajas | BG72: =+insumos!$H$149*2 -> 0.034950266 | BH72: 2 unidades | BO72: 2173 | BP72: Fajas | BQ72: =+insumos!$H$149*2 -> 0.034950266 | BR72: 2 unidades | BY72: 3817 | BZ72: Cinta adhesiva ( metros) | CA72: =insumos!$I$103*1.8 -> 0.02088 | CB72: 1,8 metros | CD72: 3636 | CE72: Etiqueta Caja | CF72: =+insumos!$H$121 -> 0.0445 | CI72: 2173 | CJ72: Fajas | CK72: =+insumos!$H$149*2 -> 0.034950266 | CL72: 2 unidades | CN72: 3636 | CO72: Etiqueta Caja | CP72: =+insumos!$H$121 -> 0.0445 | CS72: 5138 | CT72: ET. BOPP TERM. 102X78 - RR | CU72: =insumos!$H$113*12 -> 0.32411345 | CV72: 12 unid. X caja | DH72: 6297 | DI72: BOLSA PARA VACIO 18X45 | DJ72: =insumos!$H$53*4 -> 0.624 | DK72: 4 unid. X caja | DM72: 2173 | DN72: Fajas | DO72: =+insumos!$H$149*2 -> 0.034950266 | DP72: 2 unidades
B73: 3817 | C73: Cinta adhesiva ( metros) | D73: =insumos!$I$103*1.8 -> 0.02088 | E73: 1.8 metros | G73: Código | H73: Insumos | I73: Precio U$S | L73: Código | M73: Insumos | N73: Precio U$S | Q73: 6184 | R73: Fondo Congelado | S73: =insumos!$H$215 -> 0.6 | V73: 4542 | W73: Bolsa 95X60 | X73: =insumos!$I$35 -> 0.022058824 | AA73: Código | AB73: Insumos | AC73: Precio U$S | AK73: Código | AL73: Insumos | AM73: Precio U$S | AP73: 5138 | AQ73: ET. BOPP TERM. 102X78 - RR | AR73: =insumos!$H$113*16 -> 0.43215126 | AS73: 16 unid. X caja | AZ73: 3636 | BA73: Etiqueta Caja | BB73: =+insumos!$H$121 -> 0.0445 | BE73: 3636 | BF73: Etiqueta Caja | BG73: =+insumos!$H$121 -> 0.0445 | BO73: 3636 | BP73: Etiqueta Caja | BQ73: =+insumos!$H$121 -> 0.0445 | BY73: 2173 | BZ73: Fajas | CA73: =+insumos!$H$149*2 -> 0.034950266 | CB73: 2 unidades | CE73: Paquete | CI73: 3636 | CJ73: Etiqueta Caja | CK73: =+insumos!$H$121 -> 0.0445 | CO73: Paquete | DI73: Total | DJ73: =SUM(DJ62:DJ72) -> 4.0369244 | DM73: 3636 | DN73: Etiqueta Caja | DO73: =+insumos!$H$121 -> 0.0445
B74: 2173 | C74: Fajas | D74: =+insumos!$H$149*2 -> 0.034950266 | E74: 2 unidades | H74: Envasado | M74: Envasado | Q74: 2037 | R74: Tapa blanca congelado | S74: =+insumos!$H$268 -> 0.65 | V74: 3817 | W74: Cinta adhesiva ( metros) | X74: =insumos!$I$103*1.8 -> 0.02088 | Y74: 1.8 metros | AB74: Envasado | AL74: Envasado | AP74: 6229 | AQ74: TAPA BARRERA NEGRA 250 C (FILM PARA TERMOFORMADORA) - MULTIPACK DIAMALER | AR74: =insumos!$I$265*16 -> 0.34434027 | AS74: 16 unid. X caja | BA74: Paquete | BF74: Paquete | BP74: Paquete | BY74: 3636 | BZ74: Etiqueta Caja | CA74: =+insumos!$H$121 -> 0.0445 | CD74: 5138 | CE74: ET. BOPP TERM. 102X78 - RR | CF74: =insumos!$H$113*9 -> 0.24308508 | CG74: 9 unid. X caja | CJ74: Paquete | CN74: 6216 | CO74: ETIQUETAS BOPP MET.DOBLE CAPA 084X081 - ASADO 1 COSTILLA CONGELADO | CP74: =insumos!$H$181*16 -> 1.568 | CQ74: 16 unid. X caja | CS74: 4741 | CT74: BOLSA VACIO IMP. 20X50 - MERCOPACK | CU74: =insumos!$H$90*12 -> 3.696 | CV74: 12 unid. X caja | DI74: peso prom. Caja | DJ74: 13.65 | DN74: Paquete
B75: 3636 | C75: Etiqueta Caja | D75: =+insumos!$H$121 -> 0.0445 | G75: 5524 | H75: FONDO ENFRIADO (nueva medida) 505x380x155 cm - MERCOPACK | I75: =insumos!$H$217 -> 0.895 | L75: 5524 | M75: FONDO ENFRIADO (nueva medida) 505x380x155 cm - MERCOPACK | N75: =insumos!$H$217 -> 0.895 | Q75: 4542 | R75: Bolsa 95X60 | S75: =insumos!$I$35 -> 0.022058824 | V75: 2173 | W75: Fajas | X75: =+insumos!$H$149*2 -> 0.034950266 | Y75: 2 unidades | AA75: 6184 | AB75: Fondo Congelado | AC75: =insumos!$H$215 -> 0.6 | AK75: 3741 | AL75: Fondo Cofre | AM75: =insumos!$G$213 -> 0.83558719 | AP75: 6254 | AQ75: FONDO BARRERA TERMOFORMADORA TR NI 180 - MULTIPACK DIAMALER | AR75: =+insumos!$I$208*16 -> 0.7113192 | AS75: 16 unid. X caja | AZ75: 4102 | BA75: Etiqueta Trasera 100x100 | BB75: =insumos!$H$115*9 -> 0.297 | BC75: 9 unid. X caja | BE75: 5138 | BF75: ET. BOPP TERM. 102X78 - RR | BG75: =insumos!$H$113*12 -> 0.32411345 | BH75: 12 unid. X caja | BO75: 4102 | BP75: Etiqueta Trasera 100x100 | BQ75: =insumos!$H$115*3 -> 0.099 | BR75: 3 unid. X caja | BZ75: Paquete | CD75: 6229 | CE75: TAPA BARRERA NEGRA 250 C (FILM PARA TERMOFORMADORA) - MULTIPACK DIAMALER | CF75: =insumos!$I$265*9 -> 0.1936914 | CG75: 9 unid. X caja | CI75: 5138 | CJ75: ET. BOPP TERM. 102X78 - RR | CK75: =insumos!$H$113*12 -> 0.32411345 | CL75: 12 unid. X caja | CN75: 5202 | CO75: Etiqueta Trasera | CP75: =insumos!$H$114*16 -> 0.42151619 | CQ75: 16 unid. X caja | CT75: Total | CU75: =SUM(CU64:CU74) -> 6.6854632 | DI75: Costo x kls | DJ75: =+DJ73/DJ74 -> 0.29574538
C76: Paquete | G76: 5523 | H76: TAPA VILA gris - 50x38x15.5 cm (nueva medida) - Mercopack | I76: =+insumos!$H$285 -> 1.1829611 | L76: 2055 | M76: TAPA BLANCA 136 (cartulina)- Mpack | N76: =+insumos!$H$266 -> 1.15 | Q76: 3817 | R76: Cinta adhesiva ( metros) | S76: =insumos!$I$103*1.8 -> 0.02088 | T76: 1.8 metros | V76: 3636 | W76: Etiqueta Caja | X76: =+insumos!H185 -> 0.098 | AA76: 2037 | AB76: Tapa blanca congelado | AC76: =+insumos!$H$268 -> 0.65 | AK76: 3759 | AL76: TAPA VILA COFRE 156 (135)(gris) - Mpack | AM76: =+insumos!$G$284 -> 1.1352417 | AQ76: Total | AR76: =SUM(AR64:AR75) -> 4.1402465 | AZ76: 6229 | BA76: TAPA BARRERA NEGRA 250 C (FILM PARA TERMOFORMADORA) - MULTIPACK DIAMALER | BB76: =insumos!$I$265*9 -> 0.1936914 | BC76: 9 unid. X caja | BE76: 6229 | BF76: TAPA BARRERA NEGRA 250 C (FILM PARA TERMOFORMADORA) - MULTIPACK DIAMALER | BG76: =insumos!$I$265*12 -> 0.2582552 | BH76: 12 unid. X caja | BO76: 5403 | BP76: BOLSA VACIO 31X45 UMI - MERCOPACK | BQ76: =insumos!$H$80*3 -> 0.663 | BR76: 3 unid. X caja | BY76: 6208 | BZ76: Etiqueta delantera | CA76: =insumos!$H$188*12 -> 1.0929882 | CB76: 12 unid. X caja | CD76: 6254 | CE76: FONDO BARRERA TERMOFORMADORA TR NI 180 - MULTIPACK DIAMALER | CF76: =+insumos!$I$208*9 -> 0.40011705 | CG76: 9 unid. X caja | CI76: 6229 | CJ76: TAPA BARRERA NEGRA 250 C (FILM PARA TERMOFORMADORA) - MULTIPACK DIAMALER | CK76: =insumos!$I$265*12 -> 0.2582552 | CL76: 12 unid. X caja | CN76: 5214 | CO76: BOLSA VACIO 18X67 SOLDA V SB15- MERCOPACK | CP76: =insumos!$H$65*16 -> 2.2079968 | CQ76: 16 unid. X caja | CT76: peso prom. Caja | CU76: 11.45 | DI76: porcentaje cobertura ( fallas, roturas) + 3 % | DJ76: =DJ75*1.03 -> 0.30461774 | DM76: 6229 | DN76: TAPA BARRERA NEGRA 250 C (FILM PARA TERMOFORMADORA) - MULTIPACK DIAMALER | DO76: =insumos!$I$265*12 -> 0.2582552 | DP76: 12 unid. X caja
B77: 6206 | C77: Etiqueta delantera | D77: =insumos!$H$186*12 -> 1.1007317 | E77: 12 unid. X caja | G77: 4542 | H77: Bolsa 95X60 | I77: =insumos!$I$35 -> 0.022058824 | L77: 4542 | M77: Bolsa 95X60 | N77: =insumos!$I$35 -> 0.022058824 | Q77: 2173 | R77: Fajas | S77: =+insumos!$H$149*2 -> 0.034950266 | T77: 2 unidades | W77: Paquete | AA77: 4542 | AB77: Bolsa 95X60 | AC77: =insumos!$I$35 -> 0.022058824 | AK77: 4541 | AL77: Bolsa 85x60 | AM77: =insumos!$H$43 -> 0.022058824 | AQ77: peso prom. Caja | AR77: =195.35/26 -> 7.5134615 | AZ77: 6254 | BA77: FONDO BARRERA TERMOFORMADORA TR NI 180 - MULTIPACK DIAMALER | BB77: =+insumos!$I$208*9 -> 0.40011705 | BC77: 9 unid. X caja | BE77: 6254 | BF77: FONDO BARRERA TERMOFORMADORA TR NI 180 - MULTIPACK DIAMALER | BG77: =+insumos!$I$208*12 -> 0.5334894 | BH77: 12 unid. X caja | BY77: 5202 | BZ77: Etiqueta Trasera | CA77: =insumos!$H$114*12 -> 0.31613714 | CB77: 12 unid. X caja | CD77: 6138 | CE77: FAJAS UMI - 8x19.5cm - IMPRIMEX | CF77: =insumos!$H$197*9 -> 1.3087059 | CG77: 9 unid. X caja | CI77: 6254 | CJ77: FONDO BARRERA TERMOFORMADORA TR NI 180 - MULTIPACK DIAMALER | CK77: =+insumos!$I$208*12 -> 0.5334894 | CL77: 12 unid. X caja | CO77: Total | CP77: =SUM(CP66:CP76) -> 6.4771368 | CT77: Costo x kls | CU77: =+CU75/CU76 -> 0.58388325 | DM77: 6254 | DN77: FONDO BARRERA TERMOFORMADORA TR NI 180 - MULTIPACK DIAMALER | DO77: =+insumos!$I$208*12 -> 0.5334894 | DP77: 12 unid. X caja
B78: 5202 | C78: Etiqueta Trasera | D78: =insumos!$H$114*12 -> 0.31613714 | E78: 12 unid. X caja | G78: 3817 | H78: Cinta adhesiva ( metros) | I78: =insumos!$I$103*1.8 -> 0.02088 | J78: 1,8 metros | L78: 3817 | M78: Cinta adhesiva ( metros) | N78: =insumos!$I$103*1.8 -> 0.02088 | O78: 1,8 metros | Q78: 3636 | R78: Etiqueta Caja | S78: =+insumos!$H$121 -> 0.0445 | V78: 2119 | W78: HOJA 70 x 70 /30ø impr. - STRONG | X78: =insumos!$H$224*10 -> 1 | Y78: 10 unid. X caja | AA78: 3817 | AB78: Cinta adhesiva ( metros) | AC78: =insumos!$I$103*1.8 -> 0.02088 | AD78: 1.8 metros | AK78: 3817 | AL78: Cinta adhesiva ( metros) | AM78: =insumos!$I$103*1.8 -> 0.02088 | AN78: 1.8 metros | AQ78: Costo x kls | AR78: =+AR76/AR77 -> 0.55104382 | AZ78: 6138 | BA78: FAJAS UMI - 8x19.5cm - IMPRIMEX | BB78: =insumos!$H$197*9 -> 1.3087059 | BC78: 9 unid. X caja | BE78: 6288 | BF78: ETIQUETAS BOPP MET. ADC 6000 60X110 LAMINADO MATE - EL RANCHO PASSION - RR | BG78: =insumos!$H$176*12 -> 0.648 | BH78: 12 unid. X caja | BY78: 6229 | BZ78: TAPA BARRERA NEGRA 250 C (FILM PARA TERMOFORMADORA) - MULTIPACK DIAMALER | CA78: =insumos!$I$265*12 -> 0.2582552 | CB78: 12 unid. X caja | CE78: Total | CF78: =SUM(CF66:CF77) -> 4.7795165 | CI78: 6142 | CJ78: Faja iNK - 8x19.5 - IMPRIMEX | CK78: =insumos!$H$194*12 -> 2.4 | CL78: 12 unid. X caja | CO78: peso prom. Caja | CP78: =1992.58/164 -> 12.149878 | CT78: porcentaje cobertura ( fallas, roturas) + 3 % | CU78: =CU77*1.03 -> 0.60139975 | DM78: 5868 | DN78: PADS BLANCOS 4.5" x 7" - TITE DRI | DO78: =insumos!$I$243*12 -> 0.22752 | DP78: 12 unid. X caja
B79: 6229 | C79: TAPA BARRERA NEGRA 250 C (FILM PARA TERMOFORMADORA) - MULTIPACK DIAMALER | D79: =insumos!$I$265*12 -> 0.2582552 | E79: 12 unid. X caja | G79: 2173 | H79: Fajas | I79: =+insumos!$H$149*2 -> 0.034950266 | J79: 2 unidades | L79: 2173 | M79: Fajas | N79: =+insumos!$H$149*2 -> 0.034950266 | O79: 2 unidades | R79: Paquete | W79: Total | X79: =SUM(X71:X78) -> 2.4258891 | AA79: 2173 | AB79: Fajas | AC79: =+insumos!$H$149*2 -> 0.034950266 | AD79: 2 unidades | AK79: 2173 | AL79: Fajas | AM79: =+insumos!$H$149*2 -> 0.034950266 | AN79: 2 unidades | AQ79: porcentaje cobertura ( fallas, roturas) + 3 % | AR79: =AR78*1.03 -> 0.56757513 | BA79: Total | BB79: =SUM(BB67:BB78) -> 4.6434315 | BF79: Total | BG79: =SUM(BG67:BG78) -> 4.7005286 | BP79: Total | BQ79: =SUM(BQ67:BQ78) -> 2.7767362 | BY79: 6254 | BZ79: FONDO BARRERA TERMOFORMADORA TR NI 180 - MULTIPACK DIAMALER | CA79: =+insumos!$I$208*12 -> 0.5334894 | CB79: 12 unid. X caja | CE79: peso prom. Caja | CF79: 6.69 | CJ79: Total | CK79: =SUM(CK67:CK78) -> 6.6330522 | CO79: Costo x kls | CP79: =+CP77/CP78 -> 0.53310303 | DN79: Total | DO79: =SUM(DO67:DO78) -> 3.7923999
B80: 6254 | C80: FONDO BARRERA TERMOFORMADORA TR NI 180 - MULTIPACK DIAMALER | D80: =+insumos!$I$208*12 -> 0.5334894 | E80: 12 unid. X caja | G80: 3636 | H80: Etiqueta Caja | I80: =+insumos!$H$121 -> 0.0445 | L80: 3636 | M80: Etiqueta Caja | N80: =+insumos!$H$121 -> 0.0445 | Q80: 5312 | R80: BOLSA VACIO 15X40 - AMCOR -BEMIS | S80: =insumos!$H$63*16 -> 1.088 | T80: 16 unid. X caja | W80: peso prom. Caja | X80: 20.39 | AA80: 3636 | AB80: Etiqueta Caja | AC80: =+insumos!$H$121 -> 0.0445 | AK80: 3636 | AL80: Etiqueta Caja | AM80: =+insumos!$H$121 -> 0.0445 | BA80: peso prom. Caja | BB80: =1979.78/374 -> 5.2935294 | BF80: peso prom. Caja | BG80: =3025.3/306 -> 9.8866013 | BP80: peso prom. Caja | BQ80: 11.43 | BY80: 5868 | BZ80: PADS BLANCOS 4.5" x 7" - TITE DRI | CA80: =insumos!$I$243*12 -> 0.22752 | CB80: 12 unid. X caja | CE80: Costo x kls | CF80: =+CF78/CF79 -> 0.71442698 | CJ80: peso prom. Caja | CK80: 5.44 | CO80: porcentaje cobertura ( fallas, roturas) + 3 % | CP80: =CP79*1.03 -> 0.54909612 | CS80: 6172052 | CT80: Envase Lengua Vila | DN80: peso prom. Caja | DO80: 4.34
B81: 5868 | C81: PADS BLANCOS 4.5" x 7" - TITE DRI | D81: =+insumos!$I$243*12 -> 0.22752 | E81: 12 unid. X caja | H81: Paquete | M81: Paquete | Q81: 3382 | R81: ET. PAI 102X78 LISA - RR | S81: =insumos!$H$135*16 -> 0.328 | T81: 16 unid. X caja | W81: Costo x kls | X81: =+X79/X80 -> 0.11897445 | AB81: Paquete | AL81: Paquete | AP81: 3673024 | AQ81: Envase Colita de Cuadril EL ROSADO | BA81: Costo x kls | BB81: =+BB79/BB80 -> 0.87719009 | BF81: Costo x kls | BG81: =+BG79/BG80 -> 0.47544434 | BP81: Costo x kls | BQ81: =+BQ79/BQ80 -> 0.24293405 | BZ81: Total | CA81: =SUM(CA68:CA80) -> 5.1987398 | CE81: porcentaje cobertura ( fallas, roturas) + 3 % | CF81: =CF80*1.03 -> 0.73585979 | CJ81: Costo x kls | CK81: =+CK79/CK80 -> 1.2193111 | CS81: Código | CT81: Insumos | CU81: Precio U$S | DN81: Costo x kls | DO81: =+DO79/DO80 -> 0.87382487
C82: Total | D82: =SUM(D69:D81) -> 5.0885692 | G82: 6259 | H82: BOBINA 280x650 MM IMP VILA - MERCOPACK | I82: =insumos!$H$23*4 -> 1.1519995 | J82: 4 unid. X caja | L82: 4657 | M82: BOLSA VACIO IMPR. 40x50 - MERCOPACK | N82: =insumos!$H$96*4 -> 0.788 | O82: 4 unid. X caja | R82: Total | S82: =SUM(S73:S81) -> 2.7883891 | W82: porcentaje cobertura ( fallas, roturas) + 3 % | X82: =X81*1.03 -> 0.12254369 | AA82: 5214 | AB82: BOLSA VACIO 18X67 SOLDA V SB15- MERCOPACK | AC82: =insumos!$H$65*12 -> 1.6559976 | AD82: 12 unid. X caja | AK82: 5138 | AL82: ET. BOPP TERM. 102X78 - RR | AM82: =insumos!$H$113*12 -> 0.32411345 | AN82: 12 unid. X caja | AP82: Código | AQ82: Insumos | AR82: Precio U$S | BA82: porcentaje cobertura ( fallas, roturas) + 3 % | BB82: =BB81*1.03 -> 0.90350579 | BF82: porcentaje cobertura ( fallas, roturas) + 3 % | BG82: =BG81*1.03 -> 0.48970767 | BP82: porcentaje cobertura ( fallas, roturas) + 3 % | BQ82: =BQ81*1.03 -> 0.25022207 | BZ82: peso prom. Caja | CA82: 12.47 | CJ82: porcentaje cobertura ( fallas, roturas) + 3 % | CK82: =CK81*1.03 -> 1.2558904 | CN82: 4865132 | CO82: Envasado Vacio Grueso Vila - Fralda | CT82: Envasado | DN82: porcentaje cobertura ( fallas, roturas) + 3 % | DO82: =DO81*1.03 -> 0.90003962
C83: peso prom. Caja | D83: 11.45 | G83: 5138 | H83: ET. BOPP TERM. 102X78 - RR | I83: =insumos!$H$113*4 -> 0.10803782 | J83: 4 unid. X caja | L83: 5138 | M83: ET. BOPP TERM. 102X78 - RR | N83: =insumos!$H$113*4 -> 0.10803782 | O83: 4 unid. X caja | R83: peso prom. Caja | S83: =1031.93/57 -> 18.104035 | AA83: 3887 | AB83: ET. BOPP TERMICO 100x050 LISA - RR | AC83: =insumos!$H$120*12 -> 0.2388 | AD83: 12 unid. X caja | AK83: 6297 | AL83: BOLSA PARA VACIO 18X45 IMP VILA - MERCOPACK | AM83: =insumos!$H$53*12 -> 1.872 | AN83: 12 unid. X caja | AQ83: Envasado | BZ83: Costo x kls | CA83: =+CA81/CA82 -> 0.41689975 | CD83: 4545070 | CE83: Envasado Entraña UMI | CN83: Código | CO83: Insumos | CP83: Precio U$S | CS83: 6184 | CT83: Fondo Congelado | CU83: =insumos!$H$215 -> 0.6
C84: Costo x kls | D84: =+D82/D83 -> 0.44441653 | H84: Total | I84: =SUM(I75:I83) -> 3.4603875 | M84: Total | N84: =SUM(N75:N83) -> 3.0634269 | R84: Costo x kls | S84: =+S82/S83 -> 0.15402031 | V84: 993290 | W84: Envase Trimming Angus 75CL | AB84: Total | AC84: =SUM(AC75:AC83) -> 3.2671867 | AL84: Total | AM84: =SUM(AM75:AM83) -> 4.2893314 | AP84: 3741 | AQ84: Fondo Cofre | AR84: =insumos!$G$213 -> 0.83558719 | AZ84: 441931 | BA84: Envasado Bife Angosto Porcionado | BE84: 443799 | BF84: Envasado Molleja EL RANCHO | BZ84: porcentaje cobertura ( fallas, roturas) + 3 % | CA84: =CA83*1.03 -> 0.42940674 | CD84: Código | CE84: Insumos | CF84: Precio U$S | CI84: 4546916 | CJ84: Envasado B.Ancho INK 300g | CO84: Envasado | CS84: 5523 | CT84: TAPA VILA gris - 50x38x15.5 cm (nueva medida) - Mercopack | CU84: =+insumos!$H$285 -> 1.1829611 | DM84: 1993133 | DN84: Envase Bife de Vacio (interfoleado) GF
C85: porcentaje cobertura ( fallas, roturas) + 3 % | D85: =D84*1.03 -> 0.45774902 | H85: peso prom. Caja | I85: 17.6 | M85: peso prom. Caja | N85: =384.86/25 -> 15.3944 | R85: porcentaje cobertura ( fallas, roturas) + 3 % | S85: =S84*1.03 -> 0.15864092 | V85: Código | W85: Insumos | X85: Precio U$S | AB85: peso prom. Caja | AC85: =21952.69/988 -> 22.219322 | AL85: peso prom. Caja | AM85: =106.57/9 -> 11.841111 | AP85: 3759 | AQ85: TAPA VILA COFRE 156 (135)(gris) - Mpack | AR85: =+insumos!$G$284 -> 1.1352417 | AZ85: Código | BA85: Insumos | BB85: Precio U$S | BE85: Código | BF85: Insumos | BG85: Precio U$S | CE85: Envasado | CI85: Código | CJ85: Insumos | CK85: Precio U$S | CN85: 5524 | CO85: FONDO ENFRIADO (nueva medida) 505x380x155 cm - MERCOPACK | CP85: =insumos!$H$217 -> 0.895 | CS85: 4542 | CT85: Bolsa 95X60 | CU85: =insumos!$I$35 -> 0.022058824 | DM85: Código | DN85: Insumos | DO85: Precio U$S
H86: Costo x kls | I86: =+I84/I85 -> 0.19661293 | M86: Costo x kls | N86: =+N84/N85 -> 0.19899619 | W86: Envasado | AB86: Costo x kls | AC86: =+AC84/AC85 -> 0.14704259 | AL86: Costo x kls | AM86: =+AM84/AM85 -> 0.36224062 | AP86: 4541 | AQ86: Bolsa 85x60 | AR86: =insumos!$H$43 -> 0.022058824 | BA86: Envasado | BF86: Envasado | BY86: 4543025 | BZ86: Envasado Picaña Vila - Picanha | CD86: 3741 | CE86: Fondo Cofre | CF86: =insumos!$G$213 -> 0.83558719 | CJ86: Envasado | CN86: 5523 | CO86: TAPA VILA gris - 50x38x15.5 cm (nueva medida) - Mercopack | CP86: =+insumos!$H$285 -> 1.1829611 | CS86: 4986 | CT86: SEPARADORES 570x230 mm - MERCOPACK | CU86: =insumos!$H$255*4 -> 0.75999952 | CV86: 4 unid. X caja | DN86: Envasado
B87: 439025 | C87: Envase Picaña | D87: 775 | E87: =D87/E2 -> 19.249876 | H87: porcentaje cobertura ( fallas, roturas) + 3 % | I87: =I86*1.03 -> 0.20251131 | M87: porcentaje cobertura ( fallas, roturas) + 3 % | N87: =N86*1.03 -> 0.20496607 | Q87: 998017 | R87: Envase Pecho S/H | V87: 6184 | W87: Fondo Congelado | X87: =insumos!$H$215 -> 0.6 | AB87: porcentaje cobertura ( fallas, roturas) + 3 % | AC87: =AC86*1.03 -> 0.15145387 | AL87: porcentaje cobertura ( fallas, roturas) + 3 % | AM87: =AM86*1.03 -> 0.37310783 | AP87: 3817 | AQ87: Cinta adhesiva ( metros) | AR87: =insumos!$I$103*1.8 -> 0.02088 | AS87: 1,8 metros | AZ87: 3741 | BA87: Fondo Cofre | BB87: =insumos!$G$213 -> 0.83558719 | BE87: 3741 | BF87: Fondo Cofre | BG87: =insumos!$G$213 -> 0.83558719 | BY87: Código | BZ87: Insumos | CA87: Precio U$S | CD87: 5653 | CE87: TAPA UMi CONGELADO (136) - IMPRIMEX | CF87: =+insumos!$G$283 -> 1.1 | CI87: 3741 | CJ87: Fondo Cofre | CK87: =insumos!$G$213 -> 0.83558719 | CN87: 4986 | CO87: SEPARADORES 570x230 mm - MERCOPACK | CP87: =insumos!$H$255*3 -> 0.56999964 | CQ87: 3 unid. X caja | CS87: 3817 | CT87: Cinta adhesiva ( metros) | CU87: =insumos!$I$103*1.8 -> 0.02088 | CV87: 1.8 metros | DM87: 6184 | DN87: Fondo Congelado | DO87: =insumos!$H$215 -> 0.6
B88: Código | C88: Insumos | D88: Precio U$S | Q88: Código | R88: Insumos | S88: Precio U$S | V88: 2037 | W88: Tapa blanca congelado | X88: =+insumos!$H$268 -> 0.65 | AP88: 2173 | AQ88: Fajas | AR88: =+insumos!$H$149*2 -> 0.034950266 | AS88: 2 unidades | AZ88: 5653 | BA88: TAPA UMi CONGELADO (136) - IMPRIMEX | BB88: =+insumos!$G$283 -> 1.1 | BE88: 6287 | BF88: TAPA 135 COFRE EL RANCHO - IMPRIMEX | BG88: =+insumos!$H$263 -> 1.6 | BZ88: Envasado | CD88: 4986 | CE88: SEPARADORES 570x230 mm - MERCOPACK | CF88: =insumos!$H$255*3 -> 0.56999964 | CG88: 3 unid. X caja | CI88: 5251 | CJ88: TAPA INK COFRE - IMPRIMEX | CK88: =+insumos!$H$274 -> 1.6 | CN88: 4542 | CO88: Bolsa 95X60 | CP88: =insumos!$I$35 -> 0.022058824 | CS88: 2173 | CT88: Fajas | CU88: =+insumos!$H$149*2 -> 0.034950266 | CV88: 2 unidades | DM88: 5523 | DN88: TAPA VILA gris - 50x38x15.5 cm (nueva medida) - Mercopack | DO88: =+insumos!$H$285 -> 1.1829611
C89: Envasado | G89: 437033 | H89: Envase Bife de Vacio | I89: 630 | J89: =I89/E2 -> 15.648286 | L89: 436124 | M89: Envase Colita de Cuadril | N89: 399 | O89: =N89/E2 -> 9.9105812 | R89: Envasado | V89: 2105 | W89: BOLSA 80 (60) x 75 /ø80 AZUL, impresa EN ROLLO - STRONG | X89: =insumos!$I$33 -> 0.049999554 | AA89: 991031 | AB89: Envase Bife Angosto | AK89: 1987093 | AL89: Envase Intercostales Cortos Vila | AP89: 3636 | AQ89: Etiqueta Caja | AR89: =+insumos!$H$121 -> 0.0445 | AZ89: 4986 | BA89: SEPARADORES 570x230 mm - MERCOPACK | BB89: =insumos!$H$255*3 -> 0.56999964 | BC89: 3 unid. X caja | BE89: 4653 | BF89: SEPARADORES 530X290 – MERCOPACK | BG89: =insumos!$H$254*3 -> 0.55921788 | BH89: 3 unid. X caja | BY89: 5524 | BZ89: FONDO ENFRIADO (nueva medida) 505x380x155 cm - MERCOPACK | CA89: =insumos!$H$217 -> 0.895 | CD89: 5315 | CE89: BOLSA COFRE 85(60)X46/ø40, impr. en rollo, ROSADA - STRONG | CF89: =insumos!$H$45 -> 0.028 | CI89: 4653 | CJ89: SEPARADORES 530X290 – MERCOPACK | CK89: =insumos!$H$254*3 -> 0.55921788 | CL89: 3 unid. X caja | CN89: 3817 | CO89: Cinta adhesiva ( metros) | CP89: =insumos!$I$103*1.8 -> 0.02088 | CQ89: 1,8 metros | CS89: 3636 | CT89: Etiqueta Caja | CU89: =+insumos!$H$121 -> 0.0445 | DM89: 4542 | DN89: Bolsa 95X60 | DO89: =insumos!$I$35 -> 0.022058824
B90: 3741 | C90: Fondo Cofre | D90: =insumos!$G$213 -> 0.83558719 | G90: Código | H90: Insumos | I90: Precio U$S | L90: Código | M90: Insumos | N90: Precio U$S | Q90: 6184 | R90: Fondo Congelado | S90: =insumos!$H$215 -> 0.6 | V90: 3817 | W90: Cinta adhesiva ( metros) | X90: =insumos!$I$103*1.8 -> 0.02088 | Y90: 1.8 metros | AA90: Código | AB90: Insumos | AC90: Precio U$S | AK90: Código | AL90: Insumos | AM90: Precio U$S | AQ90: Paquete | AZ90: 5315 | BA90: BOLSA COFRE 85(60)X46/ø40, impr. en rollo, ROSADA - STRONG | BB90: =insumos!$H$45 -> 0.028 | BE90: 6280 | BF90: BOLSA NARANJA 85(60)X46/40 - STRONG | BG90: =insumos!$H$50 -> 0.027941176 | BY90: 5523 | BZ90: TAPA VILA gris - 50x38x15.5 cm (nueva medida) - Mercopack | CA90: =+insumos!$H$285 -> 1.1829611 | CD90: 3817 | CE90: Cinta adhesiva ( metros) | CF90: =insumos!$I$103*1.8 -> 0.02088 | CG90: 1,8 metros | CI90: 4541 | CJ90: Bolsa 85X60 | CK90: =insumos!$H$43 -> 0.022058824 | CN90: 2173 | CO90: Fajas | CP90: =+insumos!$H$149*2 -> 0.034950266 | CQ90: 2 unidades | CT90: Paquete | DM90: 3817 | DN90: Cinta adhesiva ( metros) | DO90: =insumos!$I$103*1.8 -> 0.02088 | DP90: 1.8 metros
B91: 3759 | C91: TAPA VILA COFRE 156 (135)(gris) - Mpack | D91: =+insumos!$G$284 -> 1.1352417 | H91: Envasado | M91: Envasado | Q91: 2037 | R91: Tapa blanca congelado | S91: =+insumos!$H$268 -> 0.65 | V91: 2173 | W91: Fajas | X91: =+insumos!$H$149*2 -> 0.034950266 | Y91: 2 unidades | AB91: Envasado | AL91: Envasado | AP91: 6294 | AQ91: BOLSA PARA VACIO 24X45 (PICANHA) IMP VILA - MERCOPACK | AR91: =insumos!$H$56*12 -> 2.304 | AS91: 12 unid. X Caja | AZ91: 3817 | BA91: Cinta adhesiva ( metros) | BB91: =insumos!$I$103*1.8 -> 0.02088 | BC91: 1,8 metros | BE91: 3817 | BF91: Cinta adhesiva ( metros) | BG91: =insumos!$I$103*1.8 -> 0.02088 | BH91: 1,8 metros | BY91: 4986 | BZ91: SEPARADORES 570x230 mm - MERCOPACK | CA91: =insumos!$H$255*3 -> 0.56999964 | CB91: 3 unid. X caja | CD91: 2173 | CE91: Fajas | CF91: =+insumos!$H$149*2 -> 0.034950266 | CG91: 2 unidades | CI91: 3817 | CJ91: Cinta adhesiva ( metros) | CK91: =insumos!$I$103*1.8 -> 0.02088 | CL91: 1.8 metros | CN91: 3636 | CO91: Etiqueta Caja | CP91: =+insumos!$H$121 -> 0.0445 | CS91: 5138 | CT91: ET. BOPP TERM. 102X78 - RR | CU91: =insumos!$H$113*15 -> 0.40514181 | CV91: 15 unid. X caja | DM91: 2173 | DN91: Fajas | DO91: =+insumos!$H$149*2 -> 0.034950266 | DP91: 2 unidades
B92: 4653 | C92: SEPARADORES 530X290 – MERCOPACK | D92: =insumos!$H$254*3 -> 0.55921788 | E92: 3 unid. X caja | G92: 5524 | H92: FONDO ENFRIADO (nueva medida) 505x380x155 cm - MERCOPACK | I92: =insumos!$H$217 -> 0.895 | L92: 5524 | M92: FONDO ENFRIADO (nueva medida) 505x380x155 cm - MERCOPACK | N92: =insumos!$H$217 -> 0.895 | Q92: 4542 | R92: Bolsa 95X60 | S92: =insumos!$I$35 -> 0.022058824 | V92: 3636 | W92: Etiqueta Caja | X92: =+insumos!$H$121 -> 0.0445 | AA92: 6184 | AB92: Fondo Congelado | AC92: =insumos!$H$215 -> 0.6 | AK92: 6184 | AL92: Fondo Congelado | AM92: =insumos!$H$215 -> 0.6 | AP92: 5138 | AQ92: ET. BOPP TERM. 102X78 - RR | AR92: =insumos!$H$113*12 -> 0.32411345 | AS92: 12 unid. X Caja | AZ92: 2173 | BA92: Fajas | BB92: =+insumos!$H$149*2 -> 0.034950266 | BC92: 2 unidades | BE92: 2173 | BF92: Fajas | BG92: =+insumos!$H$149*2 -> 0.034950266 | BH92: 2 unidades | BY92: 4542 | BZ92: Bolsa 95X60 | CA92: =insumos!$I$35 -> 0.022058824 | CD92: 3636 | CE92: Etiqueta Caja | CF92: =+insumos!$H$121 -> 0.0445 | CI92: 2173 | CJ92: Fajas | CK92: =+insumos!$H$149*2 -> 0.034950266 | CL92: 2 unidades | CO92: Paquete | CS92: 6297 | CT92: BOLSA PARA VACIO 18X45 IMP VILA - MERCOPACK | CU92: =insumos!$H$53*15 -> 2.34 | CV92: 15 unid. X caja | DM92: 3636 | DN92: Etiqueta Caja | DO92: =+insumos!$H$121 -> 0.0445
B93: 4541 | C93: Bolsa 85x60 | D93: =insumos!$H$43 -> 0.022058824 | G93: 5523 | H93: TAPA VILA gris - 50x38x15.5 cm (nueva medida) - Mercopack | I93: =+insumos!$H$285 -> 1.1829611 | L93: 2055 | M93: TAPA BLANCA 136 (cartulina)- Mpack | N93: =+insumos!$H$266 -> 1.15 | Q93: 3817 | R93: Cinta adhesiva ( metros) | S93: =insumos!$I$103*1.8 -> 0.02088 | T93: 1.8 metros | W93: Paquete | AA93: 2037 | AB93: Tapa blanca congelado | AC93: =+insumos!$H$268 -> 0.65 | AK93: 5523 | AL93: TAPA VILA gris - 50x38x15.5 cm (nueva medida) - Mercopack | AM93: =+insumos!$H$285 -> 1.1829611 | AQ93: Total | AR93: =SUM(AR84:AR92) -> 4.7213314 | AZ93: 3636 | BA93: Etiqueta Caja | BB93: =+insumos!$H$121 -> 0.0445 | BE93: 3636 | BF93: Etiqueta Caja | BG93: =+insumos!$H$121 -> 0.0445 | BY93: 3817 | BZ93: Cinta adhesiva ( metros) | CA93: =insumos!$I$103*1.8 -> 0.02088 | CB93: 1,8 metros | CE93: Paquete | CI93: 3636 | CJ93: Etiqueta Caja | CK93: =+insumos!$H$121 -> 0.0445 | CN93: 6208 | CO93: Etiqueta delantera | CP93: =insumos!$H$188*12 -> 1.0929882 | CQ93: 12 unid. X caja | DN93: Paquete
B94: 3817 | C94: Cinta adhesiva ( metros) | D94: =insumos!$I$103*1.8 -> 0.02088 | E94: 1,8 metros | G94: 4542 | H94: Bolsa 95X60 | I94: =insumos!$I$35 -> 0.022058824 | L94: 4542 | M94: Bolsa 95X60 | N94: =insumos!$I$35 -> 0.022058824 | Q94: 2173 | R94: Fajas | S94: =+insumos!$H$149*2 -> 0.034950266 | T94: 2 unidades | AA94: 4542 | AB94: Bolsa 95X60 | AC94: =insumos!$I$35 -> 0.022058824 | AK94: 4542 | AL94: Bolsa 95X60 | AM94: =insumos!$I$35 -> 0.022058824 | AQ94: peso prom. Caja | AR94: =24848.3/1994 -> 12.461535 | BA94: Paquete | BF94: Paquete | BY94: 2173 | BZ94: Fajas | CA94: =+insumos!$H$149*2 -> 0.034950266 | CB94: 2 unidades | CD94: 5138 | CE94: ET. BOPP TERM. 102X78 - RR | CF94: =insumos!$H$113*9 -> 0.24308508 | CG94: 9 unid. X caja | CJ94: Paquete | CN94: 5202 | CO94: Etiqueta Trasera | CP94: =insumos!$H$114*12 -> 0.31613714 | CQ94: 12 unid. X caja | CT94: Total | CU94: =SUM(CU83:CU93) -> 5.4104915 | DM94: 2119 | DN94: HOJA 70 x 70 /30ø impr. - STRONG | DO94: =insumos!$H$224*10 -> 1 | DP94: 10 unid. X caja
B95: 2173 | C95: Fajas | D95: =+insumos!$H$149*2 -> 0.034950266 | E95: 2 unidades | G95: 3817 | H95: Cinta adhesiva ( metros) | I95: =insumos!$I$103*1.8 -> 0.02088 | J95: 1,8 metros | L95: 3817 | M95: Cinta adhesiva ( metros) | N95: =insumos!$I$103*1.8 -> 0.02088 | O95: 1,8 metros | Q95: 3636 | R95: Etiqueta Caja | S95: =+insumos!$H$121 -> 0.0445 | AA95: 3817 | AB95: Cinta adhesiva ( metros) | AC95: =insumos!$I$103*1.8 -> 0.02088 | AD95: 1.8 metros | AK95: 3817 | AL95: Cinta adhesiva ( metros) | AM95: =insumos!$I$103*1.8 -> 0.02088 | AN95: 1.8 metros | AQ95: Costo x kls | AR95: =+AR93/AR94 -> 0.37887239 | AZ95: 4102 | BA95: Etiqueta Trasera 100x100 | BB95: =insumos!$H$115*12 -> 0.396 | BC95: 12 unid. X caja | BE95: 5138 | BF95: ET. BOPP TERM. 102X78 - RR | BG95: =insumos!$H$113*16 -> 0.43215126 | BH95: 16 unid. X caja | BY95: 3636 | BZ95: Etiqueta Caja | CA95: =+insumos!$H$121 -> 0.0445 | CD95: 6229 | CE95: TAPA BARRERA NEGRA 250 C (FILM PARA TERMOFORMADORA) - MULTIPACK DIAMALER | CF95: =insumos!$I$265*9 -> 0.1936914 | CG95: 9 unid. X caja | CI95: 5138 | CJ95: ET. BOPP TERM. 102X78 - RR | CK95: =insumos!$H$113*12 -> 0.32411345 | CL95: 12 unid. X caja | CN95: 6229 | CO95: TAPA BARRERA NEGRA 250 C (FILM PARA TERMOFORMADORA) - MULTIPACK DIAMALER | CP95: =insumos!$I$265*12 -> 0.2582552 | CQ95: 12 unid. X caja | CT95: peso prom. Caja | CU95: 17.55 | DN95: Total | DO95: =SUM(DO87:DO94) -> 2.9053502
B96: 3636 | C96: Etiqueta Caja | D96: =+insumos!$H$121 -> 0.0445 | G96: 2173 | H96: Fajas | I96: =+insumos!$H$149*2 -> 0.034950266 | J96: 2 unidades | L96: 2173 | M96: Fajas | N96: =+insumos!$H$149*2 -> 0.034950266 | O96: 2 unidades | R96: Paquete | W96: Total | X96: =SUM(X87:X95) -> 1.4003298 | AA96: 2173 | AB96: Fajas | AC96: =+insumos!$H$149*2 -> 0.034950266 | AD96: 2 unidades | AK96: 2173 | AL96: Fajas | AM96: =+insumos!$H$149*2 -> 0.034950266 | AN96: 2 unidades | AQ96: porcentaje cobertura ( fallas, roturas) + 3 % | AR96: =AR95*1.03 -> 0.39023856 | AZ96: 6229 | BA96: TAPA BARRERA NEGRA 250 C (FILM PARA TERMOFORMADORA) - MULTIPACK DIAMALER | BB96: =insumos!$I$265*12 -> 0.2582552 | BC96: 12 unid. X caja | BE96: 6229 | BF96: TAPA BARRERA NEGRA 250 C (FILM PARA TERMOFORMADORA) - MULTIPACK DIAMALER | BG96: =insumos!$I$265*16 -> 0.34434027 | BH96: 16 unid. X caja | BZ96: Paquete | CD96: 6254 | CE96: FONDO BARRERA TERMOFORMADORA TR NI 180 - MULTIPACK DIAMALER | CF96: =+insumos!$I$208*9 -> 0.40011705 | CG96: 9 unid. X caja | CI96: 6229 | CJ96: TAPA BARRERA NEGRA 250 C (FILM PARA TERMOFORMADORA) - MULTIPACK DIAMALER | CK96: =insumos!$I$265*12 -> 0.2582552 | CL96: 12 unid. X caja | CN96: 6254 | CO96: FONDO BARRERA TERMOFORMADORA TR NI 180 - MULTIPACK DIAMALER | CP96: =+insumos!$I$208*12 -> 0.5334894 | CQ96: 12 unid. X caja | CT96: Costo x kls | CU96: =+CU94/CU95 -> 0.30829012 | DN96: peso prom. Caja | DO96: 27.21
C97: Paquete | G97: 3636 | H97: Etiqueta Caja | I97: =+insumos!$H$121 -> 0.0445 | L97: 3636 | M97: Etiqueta Caja | N97: =+insumos!$H$121 -> 0.0445 | Q97: 2021 | R97: BOLSA VACIO 30x65 - impr. en rollo - BEMIS | S97: =insumos!$H$75*5 -> 0.975 | T97: 5 unid. X caja | W97: peso prom. Caja | X97: =146362.59/5379 -> 27.21 | AA97: 3636 | AB97: Etiqueta Caja | AC97: =+insumos!$H$121 -> 0.0445 | AK97: 3636 | AL97: Etiqueta Caja | AM97: =+insumos!$H$121 -> 0.0445 | AZ97: 6254 | BA97: FONDO BARRERA TERMOFORMADORA TR NI 180 - MULTIPACK DIAMALER | BB97: =+insumos!$I$208*12 -> 0.5334894 | BC97: 12 unid. X caja | BE97: 6254 | BF97: FONDO BARRERA TERMOFORMADORA TR NI 180 - MULTIPACK DIAMALER | BG97: =+insumos!$I$208*16 -> 0.7113192 | BH97: 16 unid. X caja | BY97: 6208 | BZ97: Etiqueta delantera | CA97: =insumos!$H$188*12 -> 1.0929882 | CB97: 12 unid. X caja | CD97: 6138 | CE97: FAJAS UMI - 8x19.5cm - IMPRIMEX | CF97: =insumos!$H$197*9 -> 1.3087059 | CG97: 9 unid. X caja | CI97: 6254 | CJ97: FONDO BARRERA TERMOFORMADORA TR NI 180 - MULTIPACK DIAMALER | CK97: =+insumos!$I$208*12 -> 0.5334894 | CL97: 12 unid. X caja | CN97: 5868 | CO97: PADS BLANCOS 4.5" x 7" - TITE DRI | CP97: =insumos!$I$243*12 -> 0.22752 | CQ97: 12 unid. X caja | CT97: porcentaje cobertura ( fallas, roturas) + 3 % | CU97: =CU96*1.03 -> 0.31753882 | DN97: Costo x kls | DO97: =+DO95/DO96 -> 0.10677509
B98: 6214 | C98: Etiqueta delantera | D98: =insumos!H167*8 -> 0.3394437 | E98: 8 unid. X caja | H98: Paquete | M98: Paquete | Q98: 3382 | R98: ET. PAI 102X78 LISA - RR | S98: =insumos!$H$135*5 -> 0.1025 | T98: 5 unid. X caja | W98: Costo x kls | X98: =+X96/X97 -> 0.051463793 | AB98: Paquete | AL98: Paquete | AP98: 3673025 | AQ98: Envase Picanha EL ROSADO | AZ98: 6138 | BA98: FAJAS UMI - 8x19.5cm - IMPRIMEX | BB98: =insumos!$H$197*12 -> 1.7449412 | BC98: 12 unid. X caja | BE98: 6288 | BF98: ETIQUETAS BOPP MET. ADC 6000 60X110 LAMINADO MATE - EL RANCHO PASSION - RR | BG98: =insumos!$H$176*16 -> 0.864 | BH98: 16 unid. X caja | BY98: 5202 | BZ98: Etiqueta Trasera | CA98: =insumos!$H$114*12 -> 0.31613714 | CB98: 12 unid. X caja | CE98: Total | CF98: =SUM(CF86:CF97) -> 4.7795165 | CI98: 6142 | CJ98: Faja iNK - 8x19.5 - IMPRIMEX | CK98: =insumos!$H$194*12 -> 2.4 | CL98: 12 unid. X caja | CO98: Total | CP98: =SUM(CP85:CP97) -> 5.1987398 | DN98: porcentaje cobertura ( fallas, roturas) + 3 % | DO98: =DO97*1.03 -> 0.10997834
B99: 5202 | C99: Etiqueta Trasera | D99: =insumos!$H$114*8 -> 0.2107581 | E99: 8 unid. X caja | G99: 6294 | H99: BOLSA PARA VACIO 24X45 (PICANHA) IMP VILA - MERCOPACK | I99: =insumos!H56*13 -> 2.496 | J99: 13 unid. X caja | M99: FALTA QUE INGRESEN ORDEN DE COMPRA (25x45) | R99: Total | S99: =SUM(S90:S98) -> 2.4498891 | W99: porcentaje cobertura ( fallas, roturas) + 3 % | X99: =X98*1.03 -> 0.053007707 | AB99: Bolsa 25 x 60 No figuran en insumos | AD99: 6 unid. X caja | AK99: 5138 | AL99: ET. BOPP TERM. 102X78 - RR | AM99: =insumos!$H$113*16 -> 0.43215126 | AN99: 16 unid. X caja | AP99: Código | AQ99: Insumos | AR99: Precio U$S | BA99: Total | BB99: =SUM(BB87:BB98) -> 5.5666029 | BF99: Total | BG99: =SUM(BG87:BG98) -> 5.4748872 | BY99: 6229 | BZ99: TAPA BARRERA NEGRA 250 C (FILM PARA TERMOFORMADORA) - MULTIPACK DIAMALER | CA99: =insumos!$I$265*12 -> 0.2582552 | CB99: 12 unid. X caja | CE99: peso prom. Caja | CF99: 6.69 | CJ99: Total | CK99: =SUM(CK87:CK98) -> 6.6330522 | CO99: peso prom. Caja | CP99: =1962.87/138 -> 14.223696 | CS99: 6172072 | CT99: Envase Entraña gruesa Vila
B100: 6229 | C100: TAPA BARRERA NEGRA 250 C (FILM PARA TERMOFORMADORA) - MULTIPACK DIAMALER | D100: =insumos!$I$265*8 -> 0.17217013 | E100: 8 unid. X caja | G100: 5138 | H100: ET. BOPP TERM. 102X78 - RR | I100: =insumos!$H$113*13 -> 0.3511229 | J100: 13 unid. X caja | L100: 5138 | M100: ET. BOPP TERM. 102X78 - RR | N100: =insumos!$H$113*17 -> 0.45916072 | O100: 17 unid. X caja | R100: peso prom. Caja | S100: =1683.06/85 -> 19.800706 | AA100: 3887 | AB100: ET. BOPP TERMICO 100x050 LISA - RR | AC100: =insumos!$H$120*6 -> 0.1194 | AD100: 6 unid. X caja | AK100: 6297 | AL100: BOLSA PARA VACIO 18X45 IMP VILA - MERCOPACK | AM100: =insumos!$H$53*16 -> 2.496 | AN100: 16 unid. X caja | AQ100: Envasado | BA100: peso prom. Caja | BB100: =1225.36/236 -> 5.1922034 | BF100: peso prom. Caja | BG100: =856.46/108 -> 7.9301852 | BY100: 6254 | BZ100: FONDO BARRERA TERMOFORMADORA TR NI 180 - MULTIPACK DIAMALER | CA100: =+insumos!$I$208*12 -> 0.5334894 | CB100: 12 unid. X caja | CE100: Costo x kls | CF100: =+CF98/CF99 -> 0.71442698 | CJ100: peso prom. Caja | CK100: =904.53/182 -> 4.9699451 | CO100: Costo x kls | CP100: =+CP98/CP99 -> 0.36549853 | CS100: Código | CT100: Insumos | CU100: Precio U$S
...

Sheet resultado
A2: PANDO SETIEMBRE 2026 NEGOCIOS ELABORADOS RESULTADO POR PRODUCCIÓN ESTIMADO
A3: Tons. Producidas | B3: =(logs!AB67+logs!AB66)/1000 -> 260.42955 | C3: =porcionados!AB297/1000 -> 248.30874
B4: Logs | C4: Porc/Asados | D4: Acumulado
A5: Conceptos | B5: U$S | C5: U$S | D5: U$S
A6: Producción a Precio de Venta | B6: =logs!AD68 -> 1859590.9 | C6: =porcionados!AD297 -> 1934154.6 | D6: =+B6+C6 -> 3793745.6
A7: Reintegros | B7: =+logs!AE68 -> 55304.95 | C7: =porcionados!AF297 -> 31269.602 | D7: =+B7+C7 -> 86574.551
A8: Deducciones de vtas | B8: =logs!AF68 -> -27652.475 | C8: =porcionados!AG297 -> -15634.801 | D8: =+B8+C8 -> -43287.276
A9: Ventas Netas | B9: =SUM(B6:B8) -> 1887243.4 | C9: =SUM(C6:C8) -> 1949789.4 | D9: =SUM(D6:D8) -> 3837032.8
A11: Costos de Elaboración | B11: U$S | C11: U$S | D11: U$S
A12: Mat. Primas | B12: =-logs!AD59 -> -1172456.3 | C12: =porcionados!AD131 -> -1495389.1 | D12: =+B12+C12 -> -2667845.4
A13: Mano de Obra | B13: =-logs!AD77 -> -62232.422 | C13: =porcionados!AD308 -> -164586.3 | D13: =+B13+C13 -> -226818.72
A14: Envases | B14: =-envases!EG18*(logs!AB67/1000) -> -13718.183 | C14: =porcionados!AE297 -> -46947.211 | D14: =+B14+C14 -> -60665.394
A15: Insumos (especias) | B15: =-envases!EJ30*(logs!AB82+logs!AB80) -> -32692.731 | D15: =+B15+C15 -> -32692.731
A16: Servicios | B16: =-0.1*logs!AB67 -> -22789.868 | C16: =porcionados!AD307 -> -24830.874 | D16: =+B16+C16 -> -47620.742
A17: Total | B17: =SUM(B12:B16) -> -1303889.5 | C17: =SUM(C12:C16) -> -1731753.4 | D17: =SUM(D12:D16) -> -3035642.9
A18: Margen Contrib. Bruto | B18: =+B9+B17 -> 583353.9 | C18: =+C9+C17 -> 218035.99 | D18: =+D9+D17 -> 801389.9
A19: Gtos Vbles Vtas | B19: =-0.178*logs!AB67 -> -40565.965 | C19: =porcionados!AD309 -> -44198.956 | D19: =+B19+C19 -> -84764.921
A20: Margen Contrib. Neto | B20: =+B18+B19 -> 542787.94 | C20: =+C18+C19 -> 173837.04 | D20: =+D18+D19 -> 716624.98
A22: En el caso de los Porcionados y los Asados los agrupamos porque a nivel de producción es dificil de separar
A23: todo lo que se genera (trimmings, grasas, huesos) del producto final ya que se hace todo en el mismo sector
A24: en el Caso de los Asados de grano que entran como mat. Prima estamos considerando el precio de este
A25: el equivalente al 95 % del Costo de hacienda de los animales de Grano faenados en el periódo.
B28: Logs | C28: Porcionados
A29: Conceptos | B29: U$S/Tons. | C29: U$S/Tons.
A30: Producción a Precio de Venta | B30: =B6/$B$3 -> 7140.4759 | C30: =C6/C3 -> 7789.3135
A31: Reintegros | B31: =B7/$B$3 -> 212.3605 | C31: =C7/C3 -> 125.93033
A32: Deducciones de vtas | B32: =B8/$B$3 -> -106.18025 | C32: =C8/C3 -> -62.965166
A33: Ventas Netas | B33: =SUM(B30:B32) -> 7246.6562 | C33: =SUM(C30:C32) -> 7852.2787
A35: Costos de Elaboración | B35: U$S/Tons. | C35: U$S/Tons.
A36: Mat. Primas | B36: =B12/$B$3 -> -4502.0095 | C36: =C12/C3 -> -6022.2973
A37: Mano de Obra | B37: =B13/$B$3 -> -238.96068 | C37: =C13/C3 -> -662.82927
A38: Envases | B38: =B14/$B$3 -> -52.675216 | C38: =C14/C3 -> -189.0679
A39: Insumos (especias) | B39: =B15/$B$3 -> -125.53388
A40: Servicios | B40: =B16/$B$3 -> -87.508764 | C40: =C16/C3 -> -100
A41: Total | B41: =SUM(B36:B40) -> -5006.688 | C41: =SUM(C36:C40) -> -6974.1945
A42: Margen Contrib. Bruto | B42: =+B33+B41 -> 2239.9682 | C42: =C18/C3 -> 878.08425
A43: Gtos Vbles Vtas | B43: =B19/$B$3 -> -155.7656 | C43: =C19/C3 -> -178
A44: Margen Contrib. Neto | B44: =+B42+B43 -> 2084.2026 | C44: =+C42+C43 -> 700.08425

Sheet insumos
A2: Inventario valorizado 01/04/26 al 30/04/26
A4: Unidad organizacional | B4: 1 - FRIGORÍFICO MATADERO PANDO
A5: Período | B5: 01/04/26 al 30/04/26
A6: Criterio de valorización | B6: FIFO
A7: Agrupar por moneda
A9: Código | B9: Producto | C9: Cantidad | D9: Unidad | E9: Moneda | F9: Valor
A10: 5661 | B10: TAPA iNK CONGELADO (136) - IMPRIMEX | C10: 700 | D10: UNID | E10: USD | F10: 770
A11: 3862 | B11: ACIDO LACTICO - PURAC 85 - ABASTECIMIENTOS | C11: 2400 | D11: KG | E11: USD | F11: 7200
A12: 3740 | B12: ADHESIVO HENKEL TECHNOMELT - IMPRIMEX | C12: 165 | D12: KG | E12: USD | F12: 1138.5
A13: 2069 | B13: ADHESIVO HOT MELT - Mpack | C13: 755 | D13: KG | E13: USD | F13: 4756.5
A14: 1651 | B14: AGUA OXIGENADA 220 VOL. - NORTE SUR | C14: 700 | D14: LIT | E14: USD | F14: 644
A15: 2188 | B15: ALCOHOL EN GEL - GEL SANIT - LINOVELL | C15: 30 | D15: LIT | E15: UYU | F15: 3660
A16: 2192 | B16: ANTICORROSIVO - A 11 - CALDERA - SERTIN | C16: 200 | D16: KG | E16: UYU | F16: 50000
A17: 2189 | B17: ANTICORROSIVO - A 48 - SALA DE MAQUINAS - SERTIN | C17: 220 | D17: LIT | E17: UYU | F17: 54120
A18: 4786 | B18: ANTIESPUMANTE AFE 1520 (grasería) - WILLIAMS | C18: 70 | D18: KG | E18: UYU | F18: 47390
A19: 2191 | B19: ANTIINCRUSTANTE - A 18 - CALDERA - SERTIN | C19: 80 | D19: LIT | E19: UYU | F19: 19920
A20: 2190 | B20: BACTERICIDA - A 42 - SALA DE MAQUINAS - SERTIN | C20: 120 | D20: LIT | E20: UYU | F20: 29760
A21: 2195 | B21: BACTERICIDA GERM OFF - SEBAMEL | C21: 80 | D21: UNID | E21: UYU | F21: 21680
A22: 6238 | B22: BOBINA 220X800MM IMP VILA ONTILCOR - MERCOPACK | C22: 50900 | D22: UNID | E22: USD | F22: 14150.2
A23: 6259 | B23: BOBINA 280x650 MM IMP VILA - MERCOPACK | C23: 14884 | D23: UNID | E23: USD | F23: 4286.59 | H23: =F23/C23 -> 0.28799987
A24: 6260 | B24: BOBINA 310x450 MM IMP VILA - MERCOPACK | C24: 1700 | D24: UNID | E24: USD | F24: 375.7 | H24: =F24/C24 -> 0.221
A25: 6309 | B25: BOBINA FLOWPACK 720 MM (BZN19S) - MERCOPACK | C25: 20 | D25: BOB | E25: USD | F25: 8140
A26: 2112 | B26: BOLSA 40 x 70 /ø40 impr. - STRONG | C26: 1225 | D26: KG | E26: USD | F26: 3675
A27: 6099 | B27: BOLSA 100X130/ø80 - harina de sangre - DISPLAST | C27: 1900 | D27: KG | E27: USD | F27: 4626.85
A28: 2114 | B28: BOLSA 20 x 30 /ø30 AD - STRONG | C28: 238 | D28: KG | E28: USD | F28: 1166.2 | H28: =F28/C28 -> 4.9 | I28: =+H28/136 -> 0.036029412
A29: 2113 | B29: BOLSA 35 x 50 /ø30 impr. AD - STRONG | C29: 1340.4 | D29: KG | E29: USD | F29: 5227.56
A30: 6227 | B30: BOLSA 400 X 700 LISO | C30: 2400 | D30: UNID | E30: USD | F30: 1560
A31: 3283 | B31: bolsa 40x70/ø40 - impresa- DISPLAST | C31: 497 | D31: KG | E31: USD | F31: 1292.2 | H31: =F31/C31 -> 2.6 | I31: =H31/40 -> 0.065
A32: 2103 | B32: BOLSA 70 x 90 /ø80 lisa - STRONG | C32: 423.9 | D32: KG | E32: USD | F32: 1271.7
A33: 2105 | B33: BOLSA 80 (60) x 75 /ø80 AZUL, impresa EN ROLLO - STRONG | C33: 748.1 | D33: KG | E33: USD | F33: 2244.28 | H33: =F33/C33 -> 2.9999733 | I33: =H33/60 -> 0.049999554
A34: 3581 | B34: BOLSA 95(60)X60/ø40, impr. en rollo - (136) - DISPLAST | C34: 1369.27 | D34: KG | E34: USD | F34: 3152.04
A35: 4542 | B35: BOLSA 95(60)X60/ø40, impr. en rollo - (136) - STRONG | C35: 4006.8 | D35: KG | E35: USD | F35: 12020.4 | H35: =+F35/C35 -> 3 | I35: =+H35/136 -> 0.022058824
A36: 3829 | B36: BOLSA AD 20x30/30ø - DISPLAST | C36: 313 | D36: KG | E36: USD | F36: 782.5
A37: 3625 | B37: bolsa AD 35x50/ø20 (lavadero) - STRONG | C37: 779 | D37: KG | E37: USD | F37: 3603.1
A38: 6143 | B38: BOLSA AD impresa, 20X50/ø30 (lenguas) - DISPLAST | C38: 15.95 | D38: KG | E38: USD | F38: 42.9
A39: 3458 | B39: bolsa blanca 28x40/ø40 - DISPLAST | C39: 543.78 | D39: KG | E39: USD | F39: 1362.93
A40: 3537 | B40: BOLSA CELESTE 100(80)x120/ø60 - DISPLAST | C40: 188 | D40: KG | E40: USD | F40: 436.16
A41: 6205 | B41: BOLSA CELESTE 100X120/ø60 - GREENLAB | C41: 410 | D41: KG | E41: UYU | F41: 48057.33
A42: 3580 | B42: BOLSA COFRE 85(60)X46/ø40, impr. en rollo - DISPLAST | C42: 1080.4 | D42: KG | E42: USD | F42: 2389.14
A43: 4541 | B43: BOLSA COFRE 85(60)X46/ø40, impr. en rollo - STRONG | C43: 1673 | D43: KG | E43: USD | F43: 5019 | G43: =+F43/C43 -> 3 | H43: =G43/136 -> 0.022058824
A44: 5353 | B44: BOLSA COFRE 85(60)X46/ø40, impr. en rollo, AMARILLA - STRONG | C44: 1912.2 | D44: KG | E44: USD | F44: 6653.56 | H44: 0.028
A45: 5315 | B45: BOLSA COFRE 85(60)X46/ø40, impr. en rollo, ROSADA - STRONG | C45: 673 | D45: KG | E45: USD | F45: 2557.4 | H45: 0.028
A46: 4540 | B46: BOLSA EN ROLLO 80x90/ø40 nat. lisa - STRONG | C46: 306.8 | D46: KG | E46: USD | F46: 920.4
A47: 3535 | B47: BOLSA MARRON 80X90/ø40 - DISPLAST | C47: 809.65 | D47: KG | E47: USD | F47: 2018.28
A48: 3536 | B48: BOLSA NARANJA 80X90/ø80 - DISPLAST | C48: 776.6 | D48: KG | E48: USD | F48: 1960.76
A49: 6281 | B49: BOLSA NARANJA 85(60)X46/40 - DISPLAST | C49: 747 | D49: KG | E49: USD | F49: 1860.03
A50: 6280 | B50: BOLSA NARANJA 85(60)X46/40 - STRONG | C50: 676 | D50: KG | E50: USD | F50: 2568.8 | G50: =F50/C50 -> 3.8 | H50: =G50/136 -> 0.027941176
A51: 5383 | B51: BOLSA P/HUESO AZUL (BINS), 225(120)x250/ø60 - STRONG | C51: 494.1 | D51: KG | E51: USD | F51: 1877.58
A52: 6203 | B52: BOLSA PARA RESIDUO NEGRAS 50X55- GREENLAB | C52: 331.9 | D52: UNID | E52: UYU | F52: 23677.41
A53: 6297 | B53: BOLSA PARA VACIO 18X45 IMP VILA - MERCOPACK | C53: 105900 | D53: UNID | E53: USD | F53: 16520.4 | H53: =F53/C53 -> 0.156
A54: 6292 | B54: BOLSA PARA VACIO 18X67 IMP VILA - MERCOPACK | C54: 41800 | D54: UNID | E54: USD | F54: 9237.8 | H54: =F54/C54 -> 0.221
A55: 6293 | B55: BOLSA PARA VACIO 20X50 IMP VILA - MERCOPACK | C55: 31950 | D55: UNID | E55: USD | F55: 5143.95 | H55: =F55/C55 -> 0.161
A56: 6294 | B56: BOLSA PARA VACIO 24X45 (PICANHA) IMP VILA - MERCOPACK | C56: 48900 | D56: UNID | E56: USD | F56: 9388.8 | H56: =F56/C56 -> 0.192
A57: 6295 | B57: BOLSA PARA VACIO UMI 28X65 - MERCOPACK | C57: 13300 | D57: UNID | E57: USD | F57: 3830.4
A58: 4394 | B58: BOLSA PLASTILLERA BCA., 70x120 - ULIREN | C58: 4550 | D58: UNID | E58: USD | F58: 1569.75
A59: 3827 | B59: BOLSA ROLLO AZUL impr. 80x(60)75/80 - DISPLAST | C59: 884.3 | D59: KG | E59: USD | F59: 2034.99
A60: 6231 | B60: BOLSA ROLLO IMPRESA 35X80/40-STRONG | C60: 3.15 | D60: KG | E60: USD | F60: 12.26
A61: 4032 | B61: BOLSA UMI - 28X75/ø45 - FLEXOPACK | C61: 850 | D61: UNID | E61: EUR | F61: 221
A62: 4032 | B62: BOLSA UMI - 28X75/ø45 - FLEXOPACK | C62: 14570 | D62: UNID | E62: USD | F62: 4851.81 | H62: =F62/C62 -> 0.333
A63: 5312 | B63: BOLSA VACIO 15X40 - AMCOR -BEMIS | C63: 7500 | D63: UNID | E63: USD | F63: 510 | H63: =F63/C63 -> 0.068
A64: 5399 | B64: BOLSA VACIO 15X60 - BEMIS-AMCOR | C64: 9000 | D64: UNID | E64: USD | F64: 972 | H64: =F64/C64 -> 0.108
A65: 5214 | B65: BOLSA VACIO 18X67 SOLDA V SB15- MERCOPACK | C65: 20700.9 | D65: UNID | E65: USD | F65: 2856.72 | H65: =F65/C65 -> 0.1379998
A66: 4970 | B66: BOLSA VACIO 18X70 impr. TAURUS GOLD - MERCOPACK | C66: 50800 | D66: UNID | E66: USD | F66: 10820.4
A67: 2012 | B67: BOLSA VACIO 20x30 - impr. en rollo - BEMIS | C67: 1483.42 | D67: UNID | E67: USD | F67: 90.49 | H67: =F67/C67 -> 0.06100093
A68: 5433 | B68: BOLSA VACIO 22 x 55 TAURUS GOLD - MERCOPACK | C68: 18800 | D68: UNID | E68: USD | F68: 3102
A69: 6078 | B69: BOLSA VACIO 22X56 BLOCK HOUSE- MERCOPACK | C69: 11000 | D69: UNID | E69: USD | F69: 2008
A70: 6079 | B70: BOLSA VACIO 22X76 BLOCK HOUSE-MERCOPACK | C70: 3310 | D70: UNID | E70: USD | F70: 860.6
A71: 4972 | B71: BOLSA VACIO 24x40 impr. TAURUS GOLD - MERCOPACK | C71: 42000 | D71: UNID | E71: USD | F71: 5082 | H71: =F71/C71 -> 0.121
A72: 4976 | B72: BOLSA VACIO 24X45, SOLDA V (picaña) impr. TAURUS GOLD - MERCOPACK | C72: 29200 | D72: UNID | E72: USD | F72: 8326.8
A73: 2019 | B73: BOLSA VACIO 25x80 - impr. en rollo - BEMIS | C73: 8750 | D73: UNID | E73: USD | F73: 1793.76 | H73: =F73/C73 -> 0.20500114
A74: 2020 | B74: BOLSA VACIO 30x45 - impr. en rollo - BEMIS | C74: 18400 | D74: UNID | E74: USD | F74: 2852.01
A75: 2021 | B75: BOLSA VACIO 30x65 - impr. en rollo - BEMIS | C75: 600 | D75: UNID | E75: USD | F75: 117 | H75: =F75/C75 -> 0.195
A76: 5462 | B76: BOLSA VACIO 30x65/ø45 UMi - BEMIS | C76: 43200 | D76: UNID | E76: USD | F76: 8916.51 | H76: =F76/C76 -> 0.20640069
A77: 5454 | B77: BOLSA VACIO 31x 65, impr.- MERCOPACK | C77: 5992 | D77: UNID | E77: USD | F77: 1911.45 | H77: =F77/C77 -> 0.31900033
A78: 6080 | B78: BOLSA VACIO 31X40 BLOCK HOUSE-MERCOPACK | C78: 20000 | D78: UNID | E78: USD | F78: 3633
A79: 4973 | B79: BOLSA VACIO 31X40 impr. TAURUS GOLD - MERCOPACK | C79: 43200 | D79: UNID | E79: USD | F79: 9244.8 | H79: =F79/C79 -> 0.214
A80: 5403 | B80: BOLSA VACIO 31X45 UMI - MERCOPACK | C80: 22000 | D80: UNID | E80: USD | F80: 4862 | H80: =F80/C80 -> 0.221
A81: 5604 | B81: BOLSA VACIO 31X50 TAURUS GOLD - MERCO PACK | C81: 15500 | D81: UNID | E81: USD | F81: 3317
A82: 4974 | B82: BOLSA VACIO 34X70 impr. TAURUS GOLD - MERCOPACK | C82: 100 | D82: UNID | E82: USD | F82: 35.6
A83: 2023 | B83: BOLSA VACIO 40x50 - impr. en rollo - BEMIS | C83: 100 | D83: UNID | E83: USD | F83: 19
A84: 4975 | B84: BOLSA VACIO 40X50 impr. TAURUS GOLD - MERCOPACK | C84: 15600 | D84: UNID | E84: USD | F84: 2948.4
A85: 2025 | B85: BOLSA VACIO 45x55 - impr. en rollo - BEMIS | C85: 33900 | D85: UNID | E85: USD | F85: 9085.2 | H85: =F85/C85 -> 0.268
A86: 4969 | B86: BOLSA VACIO HP15 - 31x50 - MERCOPACK | C86: 12000 | D86: UNID | E86: USD | F86: 5820 | H86: =F86/C86 -> 0.485
A87: 5410 | B87: BOLSA VACIO HP15 31X40 IMP. - MERCOPACK | C87: 156.25 | D87: UNID | E87: USD | F87: 17.81
A88: 4651 | B88: BOLSA VACIO HP15- p/carne c/ hueso 40x80/ø120 - MERCOPACK | C88: 4000 | D88: UNID | E88: USD | F88: 3956 | H88: =F88/C88 -> 0.989
A89: 4652 | B89: BOLSA VACIO HP15-p/carne c/ hueso 43x70/ø120, impr. - MERCOPACK | C89: 7200 | D89: UNID | E89: USD | F89: 6228 | H89: 0.865
A90: 4741 | B90: BOLSA VACIO IMP. 20X50 - MERCOPACK | C90: 1900 | D90: UNID | E90: USD | F90: 585.2 | H90: 0.308
A91: 5450 | B91: BOLSA VACIO IMP. 22X55 - MERCOPACK | C91: 294 | D91: UNID | E91: USD | F91: 34.69 | H91: 0.1179932
A92: 4673 | B92: BOLSA VACIO IMP. 24X40 - MERCOPACK | C92: 13500 | D92: UNID | E92: USD | F92: 1228.5 | H92: 0.091
A93: 4745 | B93: BOLSA VACIO IMP. 31X40 (30X40) - MERCOPACK | C93: 70200 | D93: UNID | E93: USD | F93: 8002.8 | H93: 0.114
A94: 4744 | B94: BOLSA VACIO IMP. 46x70 - MERCOPACK | C94: 33200 | D94: UNID | E94: USD | F94: 9628
A95: 4661 | B95: BOLSA VACIO IMPR. 20x40 - MERCOPACK | C95: 34800 | D95: UNID | E95: USD | F95: 8560.8
A96: 4657 | B96: BOLSA VACIO IMPR. 40x50 - MERCOPACK | C96: 45000 | D96: UNID | E96: USD | F96: 8865 | H96: =F96/C96 -> 0.197
